Workbook

Sheet Détails
A1: SCPI Fair Invest
A3: Données d'une part
A5: Prix part | C5: 181.5 | D5: 202
A6: dont droits et frais | C6: 14 | D6: 14
A7: dont frais collecte | C7: 4.5833333 | D7: 20
A9: Délai de jouissance | C9: 4 | D9: mois
C10: 6 | D10: mois
A13: Données souscription
A15: Profil | C15: =+Résumé!F2 -> Non Fondateur
A16: Catégorie | C16: Pleine Propriété
A17: Durée de souscription | C17: =+Résumé!F3 -> 10
A18: Montant de souscription | C18: =+C26*Résumé!F4 -> 10100
A19: Recurring | C19: =C26*Résumé!F5 -> 404
A23: Résumé de souscription
A25: Montant de souscription | C25: =C18 -> 10100 | I25: Investissement | J25: Gains | K25: TRI
A26: Prix d'une part | C26: =+IF($C$15="fondateur",C5,D5) -> 202
A27: dont droits et frais | C27: =+IF($C$15="fondateur",C6,D6) -> 14 | H27: =+C16 -> Pleine Propriété | I27: =+C49 -> 46803.789 | J27: =+C65 -> 14385.94 | K27: =+XIRR(D65:IW65,D64:IW64) -> 0.039029887
A28: dont frais collecte | C28: =+IF($C$15="fondateur",C7,D7) -> 20
A29: Nombre de parts | C29: =+C18/C26 -> 50
A31: Profil | C31: =+C15 -> Non Fondateur | J31: =2+1 -> 3 | K31: =+J31+1 -> 4 | L31: =+K31+1 -> 5 | M31: =+L31+1 -> 6 | N31: =+M31+1 -> 7 | O31: =+N31+1 -> 8 | P31: =+O31+1 -> 9 | Q31: =+P31+1 -> 10 | R31: =+Q31+1 -> 11 | ... AB31: =+AA31+1 -> 21
A32: Durée de souscription | C32: =+C17 -> 10 | I32: =+K27 -> 0.039029887 | J32: #REF! | K32: #REF! | L32: #REF! | M32: #REF! | N32: #REF! | O32: 0.034366289 | P32: 0.038743731 | Q32: 0.041718391 | R32: 0.043862954 | S32: 0.045453891 | T32: 0.046663108 | U32: 0.047588769 | V32: 0.048321977 | W32: 0.048901322 | X32: 0.04936147 | Y32: 0.046696177 | Z32: 0.045964125 | AA32: 0.045416412 | AB32: 0.045060536
A33: Catégorie | C33: =+C16 -> Pleine Propriété
A34: DVM | C34: =+Résumé!F7 -> 0.0472 | J34: =2+1 -> 3 | K34: =+J34+1 -> 4 | L34: =+K34+1 -> 5 | M34: =+L34+1 -> 6 | N34: =+M34+1 -> 7 | O34: =+N34+1 -> 8 | P34: =+O34+1 -> 9 | Q34: =+P34+1 -> 10 | R34: =+Q34+1 -> 11 | ... AB34: =+AA34+1 -> 21
A35: Valeur de la part pour calcul du rendement | C35: =+D5 -> 202 | I35: =+J27 -> 14385.94 | J35: #REF! | K35: #REF! | L35: #REF! | M35: #REF! | N35: #REF! | O35: 8854.3553 | P35: 12223.619 | Q35: 15605.198 | R35: 18999.278 | S35: 22406.046 | T35: 25825.692 | U35: 29258.411 | V35: 32704.397 | W35: 36163.85 | X35: 39636.971 | Y35: 40790.485 | Z35: 46235.894 | AA35: 53124.883 | AB35: 61607.739
A36: Valeur de la part pour calcul de sortie | C36: =+C26-C28 -> 182
A37: Revalorisation d'une part | C37: =+Résumé!F8 -> 0.01 | J37: =2+1 -> 3 | K37: =+J37+1 -> 4 | L37: =+K37+1 -> 5 | M37: =+L37+1 -> 6 | N37: =+M37+1 -> 7 | O37: =+N37+1 -> 8 | P37: =+O37+1 -> 9 | Q37: =+P37+1 -> 10 | R37: =+Q37+1 -> 11 | ... AB37: =+AA37+1 -> 21 | CV37: =200*(1+1%)^(8-1) -> 214.42707
I38: =+C43 -> 61189.729 | J38: #REF! | K38: #REF! | L38: #REF! | M38: #REF! | N38: #REF! | O38: 56224.417 | P38: 59593.681 | Q38: 62975.26 | R38: 66369.34 | S38: 69776.108 | T38: 73195.754 | U38: 76628.473 | V38: 80074.459 | W38: 83533.912 | X38: 87007.033 | Y38: 94335.431 | Z38: 112131.98 | AA38: 131376.21 | AB38: 152221.15
A39: CF
A41: Disponible dans le wallet client début du mois | C41: =SUM(D41:XEG41) -> 121678.31 | E41: =+IF(E$63>$C$17,0,D46) -> 0 | F41: =+IF(F$63>$C$17,0,E46) -> 0 | G41: =+IF(G$63>$C$17,0,F46) -> 0 | H41: =+IF(H$63>$C$17,0,G46) -> 0 | I41: =+IF(I$63>$C$17,0,H46) -> 0 | J41: =+IF(J$63>$C$17,0,I46) -> 39.726667 | K41: =+IF(K$63>$C$17,0,J46) -> 81.0424 | L41: =+IF(L$63>$C$17,0,K46) -> 123.9472 | ... IV41: =+IF(IV$63>$C$17,0,IU46) -> 0
A42: Profit périodique | C42: =SUM(D42:XEG42) -> 70873.172 | E42: =+SUM(OFFSET(E66,0,0,COUNTA($D$42:D42)+1)) -> 0 | F42: =+SUM(OFFSET(F66,0,0,COUNTA($D$42:E42)+1)) -> 0 | G42: =+SUM(OFFSET(G66,0,0,COUNTA($D$42:F42)+1)) -> 0 | H42: =+SUM(OFFSET(H66,0,0,COUNTA($D$42:G42)+1)) -> 0 | I42: =+SUM(OFFSET(I66,0,0,COUNTA($D$42:H42)+1)) -> 39.726667 | J42: =+SUM(OFFSET(J66,0,0,COUNTA($D$42:I42)+1)) -> 41.315733 | K42: =+SUM(OFFSET(K66,0,0,COUNTA($D$42:J42)+1)) -> 42.9048 | L42: =+SUM(OFFSET(L66,0,0,COUNTA($D$42:K42)+1)) -> 44.493867 | ... IV42: =+SUM(OFFSET(IV66,0,0,COUNTA($D$42:IU42)+1)) -> 0
A43: Disponible dans le wallet client fin du mois (avant souscription du mois) | C43: =+MAX(E43:IV43) -> 61189.729 | E43: =+IF(E$63>$C$17,0,E42+D43-D44) -> 0 | F43: =+IF(F$63>$C$17,0,F42+E43-E44) -> 0 | G43: =+IF(G$63>$C$17,0,G42+F43-F44) -> 0 | H43: =+IF(H$63>$C$17,0,H42+G43-G44) -> 0 | I43: =+IF(I$63>$C$17,0,I42+H43-H44) -> 39.726667 | J43: =+IF(J$63>$C$17,0,J42+I43-I44) -> 81.0424 | K43: =+IF(K$63>$C$17,0,K42+J43-J44) -> 123.9472 | L43: =+IF(L$63>$C$17,0,L42+K43-K44) -> 168.44107 | ... IV43: =+IF(IV$63>$C$17,0,IV42+IU43-IU44) -> 0
A44: Nouvelles souscriptions (montant payé) | C44: =SUM(D44:XEG44) -> 9683.4429 | E44: =+E45*E58 -> 0 | F44: =+F45*F58 -> 0 | G44: =+G45*G58 -> 0 | H44: =+H45*H58 -> 0 | I44: =+I45*I58 -> 0 | J44: =+J45*J58 -> 0 | K44: =+K45*K58 -> 0 | L44: =+L45*L58 -> 0 | ... IV44: =+IV45*IV58 -> 0
A45: Nouvelles souscriptions (nb de parts) | C45: =SUM(D45:XEG45) -> 46 | E45: =+IF(Résumé!$F$6="oui",IF(OFFSET(F$63,,$A$63)>$C$17,0,IF(F$63>$C$17,0,ROUNDDOWN(E43/E58,0))),0) -> 0 | F45: =+IF(Résumé!$F$6="oui",IF(OFFSET(G$63,,$A$63)>$C$17,0,IF(G$63>$C$17,0,ROUNDDOWN(F43/F58,0))),0) -> 0 | G45: =+IF(Résumé!$F$6="oui",IF(OFFSET(H$63,,$A$63)>$C$17,0,IF(H$63>$C$17,0,ROUNDDOWN(G43/G58,0))),0) -> 0 | H45: =+IF(Résumé!$F$6="oui",IF(OFFSET(I$63,,$A$63)>$C$17,0,IF(I$63>$C$17,0,ROUNDDOWN(H43/H58,0))),0) -> 0 | I45: =+IF(Résumé!$F$6="oui",IF(OFFSET(J$63,,$A$63)>$C$17,0,IF(J$63>$C$17,0,ROUNDDOWN(I43/I58,0))),0) -> 0 | J45: =+IF(Résumé!$F$6="oui",IF(OFFSET(K$63,,$A$63)>$C$17,0,IF(K$63>$C$17,0,ROUNDDOWN(J43/J58,0))),0) -> 0 | K45: =+IF(Résumé!$F$6="oui",IF(OFFSET(L$63,,$A$63)>$C$17,0,IF(L$63>$C$17,0,ROUNDDOWN(K43/K58,0))),0) -> 0 | L45: =+IF(Résumé!$F$6="oui",IF(OFFSET(M$63,,$A$63)>$C$17,0,IF(M$63>$C$17,0,ROUNDDOWN(L43/L58,0))),0) -> 0 | ... IV45: =+IF(Résumé!$F$6="oui",IF(OFFSET(IW$63,,$A$63)>$C$17,0,IF(IW$63>$C$17,0,ROUNDDOWN(IV43/IV58,0))),0) -> 0
A46: Disponible dans le wallet client fin du mois (après souscription du mois) | C46: =+IV46 -> 0 | E46: =+E43-E44 -> 0 | F46: =+F43-F44 -> 0 | G46: =+G43-G44 -> 0 | H46: =+H43-H44 -> 0 | I46: =+I43-I44 -> 39.726667 | J46: =+J43-J44 -> 81.0424 | K46: =+K43-K44 -> 123.9472 | L46: =+L43-L44 -> 168.44107 | ... IV46: =+IV43-IV44 -> 0
A47: Check | C47: {=+E47:IV47=TRUE} -> TRUE | E47: =+AND(ROUND(E41+E42-E44,2)=ROUND(E46,2),ROUND(E41+E42,2)=ROUND(E43,2)) -> TRUE | F47: =+AND(ROUND(F41+F42-F44,2)=ROUND(F46,2),ROUND(F41+F42,2)=ROUND(F43,2)) -> TRUE | G47: =+AND(ROUND(G41+G42-G44,2)=ROUND(G46,2),ROUND(G41+G42,2)=ROUND(G43,2)) -> TRUE | H47: =+AND(ROUND(H41+H42-H44,2)=ROUND(H46,2),ROUND(H41+H42,2)=ROUND(H43,2)) -> TRUE | I47: =+AND(ROUND(I41+I42-I44,2)=ROUND(I46,2),ROUND(I41+I42,2)=ROUND(I43,2)) -> TRUE | J47: =+AND(ROUND(J41+J42-J44,2)=ROUND(J46,2),ROUND(J41+J42,2)=ROUND(J43,2)) -> TRUE | K47: =+AND(ROUND(K41+K42-K44,2)=ROUND(K46,2),ROUND(K41+K42,2)=ROUND(K43,2)) -> TRUE | L47: =+AND(ROUND(L41+L42-L44,2)=ROUND(L46,2),ROUND(L41+L42,2)=ROUND(L43,2)) -> TRUE | ... IV47: =+AND(ROUND(IV41+IV42-IV44,2)=ROUND(IV46,2),ROUND(IV41+IV42,2)=ROUND(IV43,2)) -> TRUE
A49: Souscription Initiale + récurrente (montant payé) | C49: =SUM(D49:XEG49) -> 46803.789 | D49: =+D50*Détails!$D$58 -> 10100 | E49: =IF(F$63>$C$17,0,E50*E$58) -> 404 | F49: =IF(G$63>$C$17,0,F50*F$58) -> 404 | G49: =IF(H$63>$C$17,0,G50*G$58) -> 404 | H49: =IF(I$63>$C$17,0,H50*H$58) -> 404 | I49: =IF(J$63>$C$17,0,I50*I$58) -> 404 | J49: =IF(K$63>$C$17,0,J50*J$58) -> 404 | K49: =IF(L$63>$C$17,0,K50*K$58) -> 404 | L49: =IF(M$63>$C$17,0,L50*L$58) -> 404 | ... IV49: =IF(IW$63>$C$17,0,IV50*IV$58) -> 0
A50: Souscription Initiale + récurrente (nb de parts) | C50: =SUM(D50:XEG50) -> 226 | D50: =+Résumé!$F$4 -> 50 | E50: =IF(OR(OFFSET(F$63,,$A$63)>$C$17,F$63>$C$17),0,Résumé!$F$5) -> 2 | F50: =IF(OR(OFFSET(G$63,,$A$63)>$C$17,G$63>$C$17),0,Résumé!$F$5) -> 2 | G50: =IF(OR(OFFSET(H$63,,$A$63)>$C$17,H$63>$C$17),0,Résumé!$F$5) -> 2 | H50: =IF(OR(OFFSET(I$63,,$A$63)>$C$17,I$63>$C$17),0,Résumé!$F$5) -> 2 | I50: =IF(OR(OFFSET(J$63,,$A$63)>$C$17,J$63>$C$17),0,Résumé!$F$5) -> 2 | J50: =IF(OR(OFFSET(K$63,,$A$63)>$C$17,K$63>$C$17),0,Résumé!$F$5) -> 2 | K50: =IF(OR(OFFSET(L$63,,$A$63)>$C$17,L$63>$C$17),0,Résumé!$F$5) -> 2 | L50: =IF(OR(OFFSET(M$63,,$A$63)>$C$17,M$63>$C$17),0,Résumé!$F$5) -> 2 | ... IV50: =IF(OR(OFFSET(IW$63,,$A$63)>$C$17,IW$63>$C$17),0,Résumé!$F$5) -> 0
A52: Souscription totale (nb de parts) | C52: =SUM(D52:XEG52) -> 272 | D52: =+D50+D45 -> 50 | E52: =+E50+E45 -> 2 | F52: =+F50+F45 -> 2 | G52: =+G50+G45 -> 2 | H52: =+H50+H45 -> 2 | I52: =+I50+I45 -> 2 | J52: =+J50+J45 -> 2 | K52: =+K50+K45 -> 2 | ... IV52: =+IV50+IV45 -> 0
A53: Souscription totale (montant payé) | C53: =SUM(D53:XEG53) -> 56487.232 | D53: =+D49+D44 -> 10100 | E53: =+E49+E44 -> 404 | F53: =+F49+F44 -> 404 | G53: =+G49+G44 -> 404 | H53: =+H49+H44 -> 404 | I53: =+I49+I44 -> 404 | J53: =+J49+J44 -> 404 | K53: =+K49+K44 -> 404 | ... IV53: =+IV49+IV44 -> 0
A55: zakat | B55: 0.02579 | C55: =SUM(D55:XEG55) -> 6158.8107 | P55: =IF((OFFSET(Q$63,,$A$63)-1)>$C$17,0,$B$55*P56) -> 385.50892 | AB55: =IF((OFFSET(AC$63,,$A$63)-1)>$C$17,0,$B$55*AB56) -> 501.84686 | AN55: =IF((OFFSET(AO$63,,$A$63)-1)>$C$17,0,$B$55*AN56) -> 616.44725 | AZ55: =IF((OFFSET(BA$63,,$A$63)-1)>$C$17,0,$B$55*AZ56) -> 729.36753 | BL55: =IF((OFFSET(BM$63,,$A$63)-1)>$C$17,0,$B$55*BL56) -> 840.66378 | BX55: =IF((OFFSET(BY$63,,$A$63)-1)>$C$17,0,$B$55*BX56) -> 950.39076 | CJ55: =IF((OFFSET(CK$63,,$A$63)-1)>$C$17,0,$B$55*CJ56) -> 1058.602 | CV55: =IF((OFFSET(CW$63,,$A$63)-1)>$C$17,0,$B$55*CV56) -> 1075.9836 | DH55: =IF((OFFSET(DI$63,,$A$63)-1)>$C$17,0,$B$55*DH56) -> 0 | DT55: =IF((OFFSET(DU$63,,$A$63)-1)>$C$17,0,$B$55*DT56) -> 0 | EF55: =IF((OFFSET(EG$63,,$A$63)-1)>$C$17,0,$B$55*EF56) -> 0 | ER55: =IF((OFFSET(ES$63,,$A$63)-1)>$C$17,0,$B$55*ER56) -> 0 | FD55: =IF((OFFSET(FE$63,,$A$63)-1)>$C$17,0,$B$55*FD56) -> 0 | FP55: =IF((OFFSET(FQ$63,,$A$63)-1)>$C$17,0,$B$55*FP56) -> 0 | GB55: =IF((OFFSET(GC$63,,$A$63)-1)>$C$17,0,$B$55*GB56) -> 0 | GN55: =IF((OFFSET(GO$63,,$A$63)-1)>$C$17,0,$B$55*GN56) -> 0 | GZ55: =IF((OFFSET(HA$63,,$A$63)-1)>$C$17,0,$B$55*GZ56) -> 0 | HL55: =IF((OFFSET(HM$63,,$A$63)-1)>$C$17,0,$B$55*HL56) -> 0 | HX55: =IF((OFFSET(HY$63,,$A$63)-1)>$C$17,0,$B$55*HX56) -> 0 | IJ55: =IF((OFFSET(IK$63,,$A$63)-1)>$C$17,0,$B$55*IJ56) -> 0 | IV55: =IF((OFFSET(IW$63,,$A$63)-1)>$C$17,0,$B$55*IV56) -> 0
D56: =+D49 -> 10100 | E56: =+E49+D56 -> 10504 | F56: =+F49+E56 -> 10908 | G56: =+G49+F56 -> 11312 | H56: =+H49+G56 -> 11716 | I56: =+I49+H56 -> 12120 | J56: =+J49+I56 -> 12524 | K56: =+K49+J56 -> 12928 | L56: =+L49+K56 -> 13332 | ... P56: =+P49+O56 -> 14948 | Q56: =+Q49+P56-P55 -> 14970.531 | R56: =+R49+Q56-Q55 -> 15378.571 | S56: =+S49+R56-R55 -> 15786.611 | T56: =+T49+S56-S55 -> 16194.651 | U56: =+U49+T56-T55 -> 16602.691 | V56: =+V49+U56-U55 -> 17010.731 | W56: =+W49+V56-V55 -> 17418.771 | X56: =+X49+W56-W55 -> 17826.811 | ... IV56: =+IV49+IU56-IU55 -> 40644.979
A58: Prix d'une part | D58: =+$C$26 -> 202 | E58: =+D58 -> 202 | F58: =+IF(F63=E63,E58,E58*(1+Résumé!$F$8)) -> 202 | G58: =+IF(G63=F63,F58,F58*(1+Résumé!$F$8)) -> 202 | H58: =+IF(H63=G63,G58,G58*(1+Résumé!$F$8)) -> 202 | I58: =+IF(I63=H63,H58,H58*(1+Résumé!$F$8)) -> 202 | J58: =+IF(J63=I63,I58,I58*(1+Résumé!$F$8)) -> 202 | K58: =+IF(K63=J63,J58,J58*(1+Résumé!$F$8)) -> 202 | L58: =+IF(L63=K63,K58,K58*(1+Résumé!$F$8)) -> 202 | M58: =+IF(M63=L63,L58,L58*(1+Résumé!$F$8)) -> 202 | ... IV58: =+IF(IV63=IU63,IU58,IU58*(1+Résumé!$F$8)) -> 246.47839
A59: Valeur de la part pour calcul du rendement | D59: =+$C$35 -> 202 | E59: =+$C$35 -> 202 | F59: =+$C$35 -> 202 | G59: =+$C$35 -> 202 | H59: =+$C$35 -> 202 | I59: =+$C$35 -> 202 | J59: =+$C$35 -> 202 | K59: =+$C$35 -> 202 | ... IV59: =+$C$35 -> 202
A60: Valeur de la part pour calcul de sortie | D60: =+$C$36 -> 182 | E60: =+E58*(1-IF($C$15="fondateur",2.52525%,10%)) -> 181.8 | F60: =+F58*(1-IF($C$15="fondateur",2.52525%,10%)) -> 181.8 | G60: =+G58*(1-IF($C$15="fondateur",2.52525%,10%)) -> 181.8 | H60: =+H58*(1-IF($C$15="fondateur",2.52525%,10%)) -> 181.8 | I60: =+I58*(1-IF($C$15="fondateur",2.52525%,10%)) -> 181.8 | J60: =+J58*(1-IF($C$15="fondateur",2.52525%,10%)) -> 181.8 | K60: =+K58*(1-IF($C$15="fondateur",2.52525%,10%)) -> 181.8 | L60: =+L58*(1-IF($C$15="fondateur",2.52525%,10%)) -> 181.8 | ... IV60: =+IV58*(1-IF($C$15="fondateur",2.52525%,10%)) -> 221.83055
A63: =+IF(Résumé!F5=0,((C35-C36)*((1+C37)^(C32-4)))/((C35*C34)/12),C63*C32-'Détails (2)'!A62-1) -> 31 | B63: =+IF(C32-(A63/C63)<0,0,C32-(A63/C63)) -> 7.4166667 | C63: =+IF($A$64="Monthly",12,4) -> 12 | E63: =+ROUNDUP(COUNTA($E$64:E64)/$C$63,0) -> 1 | F63: =+ROUNDUP(COUNTA($E$64:F64)/$C$63,0) -> 1 | G63: =+ROUNDUP(COUNTA($E$64:G64)/$C$63,0) -> 1 | H63: =+ROUNDUP(COUNTA($E$64:H64)/$C$63,0) -> 1 | I63: =+ROUNDUP(COUNTA($E$64:I64)/$C$63,0) -> 1 | J63: =+ROUNDUP(COUNTA($E$64:J64)/$C$63,0) -> 1 | K63: =+ROUNDUP(COUNTA($E$64:K64)/$C$63,0) -> 1 | L63: =+ROUNDUP(COUNTA($E$64:L64)/$C$63,0) -> 1 | ... LV63: =+ROUNDUP(COUNTA($E$64:LV64)/$C$63,0) -> 28
A64: Monthly | C64: Total | D64: 43191 | E64: =EOMONTH(D64-1,1) -> 43220 | F64: =EOMONTH(E64,12/$C$63) -> 43251 | G64: =EOMONTH(F64,12/$C$63) -> 43281 | H64: =EOMONTH(G64,12/$C$63) -> 43312 | I64: =EOMONTH(H64,12/$C$63) -> 43343 | J64: =EOMONTH(I64,12/$C$63) -> 43373 | K64: =EOMONTH(J64,12/$C$63) -> 43404 | L64: =EOMONTH(K64,12/$C$63) -> 43434 | M64: =EOMONTH(L64,12/$C$63) -> 43465 | ... LV64: =EOMONTH(LU64,12/$C$63) -> 53235
A65: =MIN(Détails!C66:C318)>=0 -> TRUE | C65: =SUM(C66:C1258) -> 14385.94 | D65: =SUM(D66:D1258) -> -10100 | E65: =SUM(E66:E1258) -> -404 | F65: =SUM(F66:F1258) -> -404 | G65: =SUM(G66:G1258) -> -404 | H65: =SUM(H66:H1258) -> -404 | I65: =SUM(I66:I1258) -> -364.27333 | J65: =SUM(J66:J1258) -> -362.68427 | ... IW65: =SUM(IW66:IW1258) -> 0
A66: Versement initial | B66: =+D52 -> 50 | C66: =SUM(D66:XEG66) -> 4449.8925 | D66: =-$C$25 -> -10100 | E66: =IF(E$63<=$C$17,($C$34*E$59*($C$25/E$59)/$C$63)*IF(D66>0,1,(IF(COUNTA($E$63:E63)*(12/$C$63)<=IF($C$15="Fondateur",$C$10,$C$9),0,(COUNTA($E$63:E63)*(12/$C$63)-IF($C$15="Fondateur",$C$10,$C$9))/(12/$C$63)))),0)+IF(F63=$C$17,0,IF(E63=$C$17,$B66*E$60,0)) -> 0 | F66: =IF(F$63<=$C$17,($C$34*F$59*($C$25/F$59)/$C$63)*IF(E66>0,1,(IF(COUNTA($E$63:F63)*(12/$C$63)<=IF($C$15="Fondateur",$C$10,$C$9),0,(COUNTA($E$63:F63)*(12/$C$63)-IF($C$15="Fondateur",$C$10,$C$9))/(12/$C$63)))),0)+IF(G63=$C$17,0,IF(F63=$C$17,$B66*F$60,0)) -> 0 | G66: =IF(G$63<=$C$17,($C$34*G$59*($C$25/G$59)/$C$63)*IF(F66>0,1,(IF(COUNTA($E$63:G63)*(12/$C$63)<=IF($C$15="Fondateur",$C$10,$C$9),0,(COUNTA($E$63:G63)*(12/$C$63)-IF($C$15="Fondateur",$C$10,$C$9))/(12/$C$63)))),0)+IF(H63=$C$17,0,IF(G63=$C$17,$B66*G$60,0)) -> 0 | H66: =IF(H$63<=$C$17,($C$34*H$59*($C$25/H$59)/$C$63)*IF(G66>0,1,(IF(COUNTA($E$63:H63)*(12/$C$63)<=IF($C$15="Fondateur",$C$10,$C$9),0,(COUNTA($E$63:H63)*(12/$C$63)-IF($C$15="Fondateur",$C$10,$C$9))/(12/$C$63)))),0)+IF(I63=$C$17,0,IF(H63=$C$17,$B66*H$60,0)) -> 0 | I66: =IF(I$63<=$C$17,($C$34*I$59*($C$25/I$59)/$C$63)*IF(H66>0,1,(IF(COUNTA($E$63:I63)*(12/$C$63)<=IF($C$15="Fondateur",$C$10,$C$9),0,(COUNTA($E$63:I63)*(12/$C$63)-IF($C$15="Fondateur",$C$10,$C$9))/(12/$C$63)))),0)+IF(J63=$C$17,0,IF(I63=$C$17,$B66*I$60,0)) -> 39.726667 | J66: =IF(J$63<=$C$17,($C$34*J$59*($C$25/J$59)/$C$63)*IF(I66>0,1,(IF(COUNTA($E$63:J63)*(12/$C$63)<=IF($C$15="Fondateur",$C$10,$C$9),0,(COUNTA($E$63:J63)*(12/$C$63)-IF($C$15="Fondateur",$C$10,$C$9))/(12/$C$63)))),0)+IF(K63=$C$17,0,IF(J63=$C$17,$B66*J$60,0)) -> 39.726667 | K66: =IF(K$63<=$C$17,($C$34*K$59*($C$25/K$59)/$C$63)*IF(J66>0,1,(IF(COUNTA($E$63:K63)*(12/$C$63)<=IF($C$15="Fondateur",$C$10,$C$9),0,(COUNTA($E$63:K63)*(12/$C$63)-IF($C$15="Fondateur",$C$10,$C$9))/(12/$C$63)))),0)+IF(L63=$C$17,0,IF(K63=$C$17,$B66*K$60,0)) -> 39.726667 | L66: =IF(L$63<=$C$17,($C$34*L$59*($C$25/L$59)/$C$63)*IF(K66>0,1,(IF(COUNTA($E$63:L63)*(12/$C$63)<=IF($C$15="Fondateur",$C$10,$C$9),0,(COUNTA($E$63:L63)*(12/$C$63)-IF($C$15="Fondateur",$C$10,$C$9))/(12/$C$63)))),0)+IF(M63=$C$17,0,IF(L63=$C$17,$B66*L$60,0)) -> 39.726667 | ... IW66: =IF(IW$63<=$C$17,($C$34*IW$59*($C$25/IW$59)/$C$63)*IF(IV66>0,1,(IF(COUNTA($E$63:IW63)*(12/$C$63)<=IF($C$15="Fondateur",$C$10,$C$9),0,(COUNTA($E$63:IW63)*(12/$C$63)-IF($C$15="Fondateur",$C$10,$C$9))/(12/$C$63)))),0)+IF(IX63=$C$17,0,IF(IW63=$C$17,$B66*IW$60,0)) -> 0
A67: Versement programmé | B67: =+OFFSET($D$52,0,COUNTA($B$66:B66),,) -> 2 | C67: =SUM(D67:XEG67) -> 176.40663 | E67: =IF(F$63>$C$17,0,-E$53*(12/$C$63)) -> -404 | F67: =IF(F$63<=$C$17,($C$34*F$59*$B67/$C$63)*(IF(COUNTA($D67:E67)*(12/$C$63)<=$C$9,0,1)),0)+IF(G$63=$C$17,0,IF(F$63=$C$17,$B67*(F$60),0)) -> 0 | G67: =IF(G$63<=$C$17,($C$34*G$59*$B67/$C$63)*(IF(COUNTA($D67:F67)*(12/$C$63)<=$C$9,0,1)),0)+IF(H$63=$C$17,0,IF(G$63=$C$17,$B67*(G$60),0)) -> 0 | H67: =IF(H$63<=$C$17,($C$34*H$59*$B67/$C$63)*(IF(COUNTA($D67:G67)*(12/$C$63)<=$C$9,0,1)),0)+IF(I$63=$C$17,0,IF(H$63=$C$17,$B67*(H$60),0)) -> 0 | I67: =IF(I$63<=$C$17,($C$34*I$59*$B67/$C$63)*(IF(COUNTA($D67:H67)*(12/$C$63)<=$C$9,0,1)),0)+IF(J$63=$C$17,0,IF(I$63=$C$17,$B67*(I$60),0)) -> 0 | J67: =IF(J$63<=$C$17,($C$34*J$59*$B67/$C$63)*(IF(COUNTA($D67:I67)*(12/$C$63)<=$C$9,0,1)),0)+IF(K$63=$C$17,0,IF(J$63=$C$17,$B67*(J$60),0)) -> 1.5890667 | K67: =IF(K$63<=$C$17,($C$34*K$59*$B67/$C$63)*(IF(COUNTA($D67:J67)*(12/$C$63)<=$C$9,0,1)),0)+IF(L$63=$C$17,0,IF(K$63=$C$17,$B67*(K$60),0)) -> 1.5890667 | L67: =IF(L$63<=$C$17,($C$34*L$59*$B67/$C$63)*(IF(COUNTA($D67:K67)*(12/$C$63)<=$C$9,0,1)),0)+IF(M$63=$C$17,0,IF(L$63=$C$17,$B67*(L$60),0)) -> 1.5890667 | M67: =IF(M$63<=$C$17,($C$34*M$59*$B67/$C$63)*(IF(COUNTA($D67:L67)*(12/$C$63)<=$C$9,0,1)),0)+IF(N$63=$C$17,0,IF(M$63=$C$17,$B67*(M$60),0)) -> 1.5890667 | ... IW67: =IF(IW$63<=$C$17,($C$34*IW$59*$B67/$C$63)*(IF(COUNTA($D67:IV67)*(12/$C$63)<=$C$9,0,1)),0)+IF(IX$63=$C$17,0,IF(IW$63=$C$17,$B67*(IW$60),0)) -> 0
A68: Versement programmé | B68: =+OFFSET($D$52,0,COUNTA($B$66:B67),,) -> 2 | C68: =SUM(D68:XEG68) -> 174.81757 | F68: =IF(G$63>$C$17,0,-F$53*(12/$C$63)) -> -404 | G68: =IF(G$63<=$C$17,($C$34*G$59*$B68/$C$63)*(IF(COUNTA($D68:F68)*(12/$C$63)<=$C$9,0,1)),0)+IF(H$63=$C$17,0,IF(G$63=$C$17,$B68*(G$60),0)) -> 0 | H68: =IF(H$63<=$C$17,($C$34*H$59*$B68/$C$63)*(IF(COUNTA($D68:G68)*(12/$C$63)<=$C$9,0,1)),0)+IF(I$63=$C$17,0,IF(H$63=$C$17,$B68*(H$60),0)) -> 0 | I68: =IF(I$63<=$C$17,($C$34*I$59*$B68/$C$63)*(IF(COUNTA($D68:H68)*(12/$C$63)<=$C$9,0,1)),0)+IF(J$63=$C$17,0,IF(I$63=$C$17,$B68*(I$60),0)) -> 0 | J68: =IF(J$63<=$C$17,($C$34*J$59*$B68/$C$63)*(IF(COUNTA($D68:I68)*(12/$C$63)<=$C$9,0,1)),0)+IF(K$63=$C$17,0,IF(J$63=$C$17,$B68*(J$60),0)) -> 0 | K68: =IF(K$63<=$C$17,($C$34*K$59*$B68/$C$63)*(IF(COUNTA($D68:J68)*(12/$C$63)<=$C$9,0,1)),0)+IF(L$63=$C$17,0,IF(K$63=$C$17,$B68*(K$60),0)) -> 1.5890667 | L68: =IF(L$63<=$C$17,($C$34*L$59*$B68/$C$63)*(IF(COUNTA($D68:K68)*(12/$C$63)<=$C$9,0,1)),0)+IF(M$63=$C$17,0,IF(L$63=$C$17,$B68*(L$60),0)) -> 1.5890667 | M68: =IF(M$63<=$C$17,($C$34*M$59*$B68/$C$63)*(IF(COUNTA($D68:L68)*(12/$C$63)<=$C$9,0,1)),0)+IF(N$63=$C$17,0,IF(M$63=$C$17,$B68*(M$60),0)) -> 1.5890667 | N68: =IF(N$63<=$C$17,($C$34*N$59*$B68/$C$63)*(IF(COUNTA($D68:M68)*(12/$C$63)<=$C$9,0,1)),0)+IF(O$63=$C$17,0,IF(N$63=$C$17,$B68*(N$60),0)) -> 1.5890667 | ... IW68: =IF(IW$63<=$C$17,($C$34*IW$59*$B68/$C$63)*(IF(COUNTA($D68:IV68)*(12/$C$63)<=$C$9,0,1)),0)+IF(IX$63=$C$17,0,IF(IW$63=$C$17,$B68*(IW$60),0)) -> 0
A69: Versement programmé | B69: =+OFFSET($D$52,0,COUNTA($B$66:B68),,) -> 2 | C69: =SUM(D69:XEG69) -> 173.2285 | G69: =IF(H$63>$C$17,0,-G$53*(12/$C$63)) -> -404 | H69: =IF(H$63<=$C$17,($C$34*H$59*$B69/$C$63)*(IF(COUNTA($D69:G69)*(12/$C$63)<=$C$9,0,1)),0)+IF(I$63=$C$17,0,IF(H$63=$C$17,$B69*(H$60),0)) -> 0 | I69: =IF(I$63<=$C$17,($C$34*I$59*$B69/$C$63)*(IF(COUNTA($D69:H69)*(12/$C$63)<=$C$9,0,1)),0)+IF(J$63=$C$17,0,IF(I$63=$C$17,$B69*(I$60),0)) -> 0 | J69: =IF(J$63<=$C$17,($C$34*J$59*$B69/$C$63)*(IF(COUNTA($D69:I69)*(12/$C$63)<=$C$9,0,1)),0)+IF(K$63=$C$17,0,IF(J$63=$C$17,$B69*(J$60),0)) -> 0 | K69: =IF(K$63<=$C$17,($C$34*K$59*$B69/$C$63)*(IF(COUNTA($D69:J69)*(12/$C$63)<=$C$9,0,1)),0)+IF(L$63=$C$17,0,IF(K$63=$C$17,$B69*(K$60),0)) -> 0 | L69: =IF(L$63<=$C$17,($C$34*L$59*$B69/$C$63)*(IF(COUNTA($D69:K69)*(12/$C$63)<=$C$9,0,1)),0)+IF(M$63=$C$17,0,IF(L$63=$C$17,$B69*(L$60),0)) -> 1.5890667 | M69: =IF(M$63<=$C$17,($C$34*M$59*$B69/$C$63)*(IF(COUNTA($D69:L69)*(12/$C$63)<=$C$9,0,1)),0)+IF(N$63=$C$17,0,IF(M$63=$C$17,$B69*(M$60),0)) -> 1.5890667 | N69: =IF(N$63<=$C$17,($C$34*N$59*$B69/$C$63)*(IF(COUNTA($D69:M69)*(12/$C$63)<=$C$9,0,1)),0)+IF(O$63=$C$17,0,IF(N$63=$C$17,$B69*(N$60),0)) -> 1.5890667 | O69: =IF(O$63<=$C$17,($C$34*O$59*$B69/$C$63)*(IF(COUNTA($D69:N69)*(12/$C$63)<=$C$9,0,1)),0)+IF(P$63=$C$17,0,IF(O$63=$C$17,$B69*(O$60),0)) -> 1.5890667 | ... IW69: =IF(IW$63<=$C$17,($C$34*IW$59*$B69/$C$63)*(IF(COUNTA($D69:IV69)*(12/$C$63)<=$C$9,0,1)),0)+IF(IX$63=$C$17,0,IF(IW$63=$C$17,$B69*(IW$60),0)) -> 0
A70: Versement programmé | B70: =+OFFSET($D$52,0,COUNTA($B$66:B69),,) -> 2 | C70: =SUM(D70:XEG70) -> 171.63943 | H70: =IF(I$63>$C$17,0,-H$53*(12/$C$63)) -> -404 | I70: =IF(I$63<=$C$17,($C$34*I$59*$B70/$C$63)*(IF(COUNTA($D70:H70)*(12/$C$63)<=$C$9,0,1)),0)+IF(J$63=$C$17,0,IF(I$63=$C$17,$B70*(I$60),0)) -> 0 | J70: =IF(J$63<=$C$17,($C$34*J$59*$B70/$C$63)*(IF(COUNTA($D70:I70)*(12/$C$63)<=$C$9,0,1)),0)+IF(K$63=$C$17,0,IF(J$63=$C$17,$B70*(J$60),0)) -> 0 | K70: =IF(K$63<=$C$17,($C$34*K$59*$B70/$C$63)*(IF(COUNTA($D70:J70)*(12/$C$63)<=$C$9,0,1)),0)+IF(L$63=$C$17,0,IF(K$63=$C$17,$B70*(K$60),0)) -> 0 | L70: =IF(L$63<=$C$17,($C$34*L$59*$B70/$C$63)*(IF(COUNTA($D70:K70)*(12/$C$63)<=$C$9,0,1)),0)+IF(M$63=$C$17,0,IF(L$63=$C$17,$B70*(L$60),0)) -> 0 | M70: =IF(M$63<=$C$17,($C$34*M$59*$B70/$C$63)*(IF(COUNTA($D70:L70)*(12/$C$63)<=$C$9,0,1)),0)+IF(N$63=$C$17,0,IF(M$63=$C$17,$B70*(M$60),0)) -> 1.5890667 | N70: =IF(N$63<=$C$17,($C$34*N$59*$B70/$C$63)*(IF(COUNTA($D70:M70)*(12/$C$63)<=$C$9,0,1)),0)+IF(O$63=$C$17,0,IF(N$63=$C$17,$B70*(N$60),0)) -> 1.5890667 | O70: =IF(O$63<=$C$17,($C$34*O$59*$B70/$C$63)*(IF(COUNTA($D70:N70)*(12/$C$63)<=$C$9,0,1)),0)+IF(P$63=$C$17,0,IF(O$63=$C$17,$B70*(O$60),0)) -> 1.5890667 | P70: =IF(P$63<=$C$17,($C$34*P$59*$B70/$C$63)*(IF(COUNTA($D70:O70)*(12/$C$63)<=$C$9,0,1)),0)+IF(Q$63=$C$17,0,IF(P$63=$C$17,$B70*(P$60),0)) -> 1.5890667 | ... IW70: =IF(IW$63<=$C$17,($C$34*IW$59*$B70/$C$63)*(IF(COUNTA($D70:IV70)*(12/$C$63)<=$C$9,0,1)),0)+IF(IX$63=$C$17,0,IF(IW$63=$C$17,$B70*(IW$60),0)) -> 0
A71: Versement programmé | B71: =+OFFSET($D$52,0,COUNTA($B$66:B70),,) -> 2 | C71: =SUM(D71:XEG71) -> 170.05037 | I71: =IF(J$63>$C$17,0,-I$53*(12/$C$63)) -> -404 | J71: =IF(J$63<=$C$17,($C$34*J$59*$B71/$C$63)*(IF(COUNTA($D71:I71)*(12/$C$63)<=$C$9,0,1)),0)+IF(K$63=$C$17,0,IF(J$63=$C$17,$B71*(J$60),0)) -> 0 | K71: =IF(K$63<=$C$17,($C$34*K$59*$B71/$C$63)*(IF(COUNTA($D71:J71)*(12/$C$63)<=$C$9,0,1)),0)+IF(L$63=$C$17,0,IF(K$63=$C$17,$B71*(K$60),0)) -> 0 | L71: =IF(L$63<=$C$17,($C$34*L$59*$B71/$C$63)*(IF(COUNTA($D71:K71)*(12/$C$63)<=$C$9,0,1)),0)+IF(M$63=$C$17,0,IF(L$63=$C$17,$B71*(L$60),0)) -> 0 | M71: =IF(M$63<=$C$17,($C$34*M$59*$B71/$C$63)*(IF(COUNTA($D71:L71)*(12/$C$63)<=$C$9,0,1)),0)+IF(N$63=$C$17,0,IF(M$63=$C$17,$B71*(M$60),0)) -> 0 | N71: =IF(N$63<=$C$17,($C$34*N$59*$B71/$C$63)*(IF(COUNTA($D71:M71)*(12/$C$63)<=$C$9,0,1)),0)+IF(O$63=$C$17,0,IF(N$63=$C$17,$B71*(N$60),0)) -> 1.5890667 | O71: =IF(O$63<=$C$17,($C$34*O$59*$B71/$C$63)*(IF(COUNTA($D71:N71)*(12/$C$63)<=$C$9,0,1)),0)+IF(P$63=$C$17,0,IF(O$63=$C$17,$B71*(O$60),0)) -> 1.5890667 | P71: =IF(P$63<=$C$17,($C$34*P$59*$B71/$C$63)*(IF(COUNTA($D71:O71)*(12/$C$63)<=$C$9,0,1)),0)+IF(Q$63=$C$17,0,IF(P$63=$C$17,$B71*(P$60),0)) -> 1.5890667 | Q71: =IF(Q$63<=$C$17,($C$34*Q$59*$B71/$C$63)*(IF(COUNTA($D71:P71)*(12/$C$63)<=$C$9,0,1)),0)+IF(R$63=$C$17,0,IF(Q$63=$C$17,$B71*(Q$60),0)) -> 1.5890667 | ... IW71: =IF(IW$63<=$C$17,($C$34*IW$59*$B71/$C$63)*(IF(COUNTA($D71:IV71)*(12/$C$63)<=$C$9,0,1)),0)+IF(IX$63=$C$17,0,IF(IW$63=$C$17,$B71*(IW$60),0)) -> 0
A72: Versement programmé | B72: =+OFFSET($D$52,0,COUNTA($B$66:B71),,) -> 2 | C72: =SUM(D72:XEG72) -> 168.4613 | J72: =IF(K$63>$C$17,0,-J$53*(12/$C$63)) -> -404 | K72: =IF(K$63<=$C$17,($C$34*K$59*$B72/$C$63)*(IF(COUNTA($D72:J72)*(12/$C$63)<=$C$9,0,1)),0)+IF(L$63=$C$17,0,IF(K$63=$C$17,$B72*(K$60),0)) -> 0 | L72: =IF(L$63<=$C$17,($C$34*L$59*$B72/$C$63)*(IF(COUNTA($D72:K72)*(12/$C$63)<=$C$9,0,1)),0)+IF(M$63=$C$17,0,IF(L$63=$C$17,$B72*(L$60),0)) -> 0 | M72: =IF(M$63<=$C$17,($C$34*M$59*$B72/$C$63)*(IF(COUNTA($D72:L72)*(12/$C$63)<=$C$9,0,1)),0)+IF(N$63=$C$17,0,IF(M$63=$C$17,$B72*(M$60),0)) -> 0 | N72: =IF(N$63<=$C$17,($C$34*N$59*$B72/$C$63)*(IF(COUNTA($D72:M72)*(12/$C$63)<=$C$9,0,1)),0)+IF(O$63=$C$17,0,IF(N$63=$C$17,$B72*(N$60),0)) -> 0 | O72: =IF(O$63<=$C$17,($C$34*O$59*$B72/$C$63)*(IF(COUNTA($D72:N72)*(12/$C$63)<=$C$9,0,1)),0)+IF(P$63=$C$17,0,IF(O$63=$C$17,$B72*(O$60),0)) -> 1.5890667 | P72: =IF(P$63<=$C$17,($C$34*P$59*$B72/$C$63)*(IF(COUNTA($D72:O72)*(12/$C$63)<=$C$9,0,1)),0)+IF(Q$63=$C$17,0,IF(P$63=$C$17,$B72*(P$60),0)) -> 1.5890667 | Q72: =IF(Q$63<=$C$17,($C$34*Q$59*$B72/$C$63)*(IF(COUNTA($D72:P72)*(12/$C$63)<=$C$9,0,1)),0)+IF(R$63=$C$17,0,IF(Q$63=$C$17,$B72*(Q$60),0)) -> 1.5890667 | R72: =IF(R$63<=$C$17,($C$34*R$59*$B72/$C$63)*(IF(COUNTA($D72:Q72)*(12/$C$63)<=$C$9,0,1)),0)+IF(S$63=$C$17,0,IF(R$63=$C$17,$B72*(R$60),0)) -> 1.5890667 | ... IW72: =IF(IW$63<=$C$17,($C$34*IW$59*$B72/$C$63)*(IF(COUNTA($D72:IV72)*(12/$C$63)<=$C$9,0,1)),0)+IF(IX$63=$C$17,0,IF(IW$63=$C$17,$B72*(IW$60),0)) -> 0
A73: Versement programmé | B73: =+OFFSET($D$52,0,COUNTA($B$66:B72),,) -> 2 | C73: =SUM(D73:XEG73) -> 166.87223 | K73: =IF(L$63>$C$17,0,-K$53*(12/$C$63)) -> -404 | L73: =IF(L$63<=$C$17,($C$34*L$59*$B73/$C$63)*(IF(COUNTA($D73:K73)*(12/$C$63)<=$C$9,0,1)),0)+IF(M$63=$C$17,0,IF(L$63=$C$17,$B73*(L$60),0)) -> 0 | M73: =IF(M$63<=$C$17,($C$34*M$59*$B73/$C$63)*(IF(COUNTA($D73:L73)*(12/$C$63)<=$C$9,0,1)),0)+IF(N$63=$C$17,0,IF(M$63=$C$17,$B73*(M$60),0)) -> 0 | N73: =IF(N$63<=$C$17,($C$34*N$59*$B73/$C$63)*(IF(COUNTA($D73:M73)*(12/$C$63)<=$C$9,0,1)),0)+IF(O$63=$C$17,0,IF(N$63=$C$17,$B73*(N$60),0)) -> 0 | O73: =IF(O$63<=$C$17,($C$34*O$59*$B73/$C$63)*(IF(COUNTA($D73:N73)*(12/$C$63)<=$C$9,0,1)),0)+IF(P$63=$C$17,0,IF(O$63=$C$17,$B73*(O$60),0)) -> 0 | P73: =IF(P$63<=$C$17,($C$34*P$59*$B73/$C$63)*(IF(COUNTA($D73:O73)*(12/$C$63)<=$C$9,0,1)),0)+IF(Q$63=$C$17,0,IF(P$63=$C$17,$B73*(P$60),0)) -> 1.5890667 | Q73: =IF(Q$63<=$C$17,($C$34*Q$59*$B73/$C$63)*(IF(COUNTA($D73:P73)*(12/$C$63)<=$C$9,0,1)),0)+IF(R$63=$C$17,0,IF(Q$63=$C$17,$B73*(Q$60),0)) -> 1.5890667 | R73: =IF(R$63<=$C$17,($C$34*R$59*$B73/$C$63)*(IF(COUNTA($D73:Q73)*(12/$C$63)<=$C$9,0,1)),0)+IF(S$63=$C$17,0,IF(R$63=$C$17,$B73*(R$60),0)) -> 1.5890667 | S73: =IF(S$63<=$C$17,($C$34*S$59*$B73/$C$63)*(IF(COUNTA($D73:R73)*(12/$C$63)<=$C$9,0,1)),0)+IF(T$63=$C$17,0,IF(S$63=$C$17,$B73*(S$60),0)) -> 1.5890667 | ... IW73: =IF(IW$63<=$C$17,($C$34*IW$59*$B73/$C$63)*(IF(COUNTA($D73:IV73)*(12/$C$63)<=$C$9,0,1)),0)+IF(IX$63=$C$17,0,IF(IW$63=$C$17,$B73*(IW$60),0)) -> 0
A74: Versement programmé | B74: =+OFFSET($D$52,0,COUNTA($B$66:B73),,) -> 2 | C74: =SUM(D74:XEG74) -> 165.28317 | L74: =IF(M$63>$C$17,0,-L$53*(12/$C$63)) -> -404 | M74: =IF(M$63<=$C$17,($C$34*M$59*$B74/$C$63)*(IF(COUNTA($D74:L74)*(12/$C$63)<=$C$9,0,1)),0)+IF(N$63=$C$17,0,IF(M$63=$C$17,$B74*(M$60),0)) -> 0 | N74: =IF(N$63<=$C$17,($C$34*N$59*$B74/$C$63)*(IF(COUNTA($D74:M74)*(12/$C$63)<=$C$9,0,1)),0)+IF(O$63=$C$17,0,IF(N$63=$C$17,$B74*(N$60),0)) -> 0 | O74: =IF(O$63<=$C$17,($C$34*O$59*$B74/$C$63)*(IF(COUNTA($D74:N74)*(12/$C$63)<=$C$9,0,1)),0)+IF(P$63=$C$17,0,IF(O$63=$C$17,$B74*(O$60),0)) -> 0 | P74: =IF(P$63<=$C$17,($C$34*P$59*$B74/$C$63)*(IF(COUNTA($D74:O74)*(12/$C$63)<=$C$9,0,1)),0)+IF(Q$63=$C$17,0,IF(P$63=$C$17,$B74*(P$60),0)) -> 0 | Q74: =IF(Q$63<=$C$17,($C$34*Q$59*$B74/$C$63)*(IF(COUNTA($D74:P74)*(12/$C$63)<=$C$9,0,1)),0)+IF(R$63=$C$17,0,IF(Q$63=$C$17,$B74*(Q$60),0)) -> 1.5890667 | R74: =IF(R$63<=$C$17,($C$34*R$59*$B74/$C$63)*(IF(COUNTA($D74:Q74)*(12/$C$63)<=$C$9,0,1)),0)+IF(S$63=$C$17,0,IF(R$63=$C$17,$B74*(R$60),0)) -> 1.5890667 | S74: =IF(S$63<=$C$17,($C$34*S$59*$B74/$C$63)*(IF(COUNTA($D74:R74)*(12/$C$63)<=$C$9,0,1)),0)+IF(T$63=$C$17,0,IF(S$63=$C$17,$B74*(S$60),0)) -> 1.5890667 | T74: =IF(T$63<=$C$17,($C$34*T$59*$B74/$C$63)*(IF(COUNTA($D74:S74)*(12/$C$63)<=$C$9,0,1)),0)+IF(U$63=$C$17,0,IF(T$63=$C$17,$B74*(T$60),0)) -> 1.5890667 | ... IW74: =IF(IW$63<=$C$17,($C$34*IW$59*$B74/$C$63)*(IF(COUNTA($D74:IV74)*(12/$C$63)<=$C$9,0,1)),0)+IF(IX$63=$C$17,0,IF(IW$63=$C$17,$B74*(IW$60),0)) -> 0
A75: Versement programmé | B75: =+OFFSET($D$52,0,COUNTA($B$66:B74),,) -> 3 | C75: =SUM(D75:XEG75) -> 245.54115 | M75: =IF(N$63>$C$17,0,-M$53*(12/$C$63)) -> -606 | N75: =IF(N$63<=$C$17,($C$34*N$59*$B75/$C$63)*(IF(COUNTA($D75:M75)*(12/$C$63)<=$C$9,0,1)),0)+IF(O$63=$C$17,0,IF(N$63=$C$17,$B75*(N$60),0)) -> 0 | O75: =IF(O$63<=$C$17,($C$34*O$59*$B75/$C$63)*(IF(COUNTA($D75:N75)*(12/$C$63)<=$C$9,0,1)),0)+IF(P$63=$C$17,0,IF(O$63=$C$17,$B75*(O$60),0)) -> 0 | P75: =IF(P$63<=$C$17,($C$34*P$59*$B75/$C$63)*(IF(COUNTA($D75:O75)*(12/$C$63)<=$C$9,0,1)),0)+IF(Q$63=$C$17,0,IF(P$63=$C$17,$B75*(P$60),0)) -> 0 | Q75: =IF(Q$63<=$C$17,($C$34*Q$59*$B75/$C$63)*(IF(COUNTA($D75:P75)*(12/$C$63)<=$C$9,0,1)),0)+IF(R$63=$C$17,0,IF(Q$63=$C$17,$B75*(Q$60),0)) -> 0 | R75: =IF(R$63<=$C$17,($C$34*R$59*$B75/$C$63)*(IF(COUNTA($D75:Q75)*(12/$C$63)<=$C$9,0,1)),0)+IF(S$63=$C$17,0,IF(R$63=$C$17,$B75*(R$60),0)) -> 2.3836 | S75: =IF(S$63<=$C$17,($C$34*S$59*$B75/$C$63)*(IF(COUNTA($D75:R75)*(12/$C$63)<=$C$9,0,1)),0)+IF(T$63=$C$17,0,IF(S$63=$C$17,$B75*(S$60),0)) -> 2.3836 | T75: =IF(T$63<=$C$17,($C$34*T$59*$B75/$C$63)*(IF(COUNTA($D75:S75)*(12/$C$63)<=$C$9,0,1)),0)+IF(U$63=$C$17,0,IF(T$63=$C$17,$B75*(T$60),0)) -> 2.3836 | U75: =IF(U$63<=$C$17,($C$34*U$59*$B75/$C$63)*(IF(COUNTA($D75:T75)*(12/$C$63)<=$C$9,0,1)),0)+IF(V$63=$C$17,0,IF(U$63=$C$17,$B75*(U$60),0)) -> 2.3836 | ... IW75: =IF(IW$63<=$C$17,($C$34*IW$59*$B75/$C$63)*(IF(COUNTA($D75:IV75)*(12/$C$63)<=$C$9,0,1)),0)+IF(IX$63=$C$17,0,IF(IW$63=$C$17,$B75*(IW$60),0)) -> 0
A76: Versement programmé | B76: =+OFFSET($D$52,0,COUNTA($B$66:B75),,) -> 2 | C76: =SUM(D76:XEG76) -> 162.10503 | N76: =IF(O$63>$C$17,0,-N$53*(12/$C$63)) -> -404 | O76: =IF(O$63<=$C$17,($C$34*O$59*$B76/$C$63)*(IF(COUNTA($D76:N76)*(12/$C$63)<=$C$9,0,1)),0)+IF(P$63=$C$17,0,IF(O$63=$C$17,$B76*(O$60),0)) -> 0 | P76: =IF(P$63<=$C$17,($C$34*P$59*$B76/$C$63)*(IF(COUNTA($D76:O76)*(12/$C$63)<=$C$9,0,1)),0)+IF(Q$63=$C$17,0,IF(P$63=$C$17,$B76*(P$60),0)) -> 0 | Q76: =IF(Q$63<=$C$17,($C$34*Q$59*$B76/$C$63)*(IF(COUNTA($D76:P76)*(12/$C$63)<=$C$9,0,1)),0)+IF(R$63=$C$17,0,IF(Q$63=$C$17,$B76*(Q$60),0)) -> 0 | R76: =IF(R$63<=$C$17,($C$34*R$59*$B76/$C$63)*(IF(COUNTA($D76:Q76)*(12/$C$63)<=$C$9,0,1)),0)+IF(S$63=$C$17,0,IF(R$63=$C$17,$B76*(R$60),0)) -> 0 | S76: =IF(S$63<=$C$17,($C$34*S$59*$B76/$C$63)*(IF(COUNTA($D76:R76)*(12/$C$63)<=$C$9,0,1)),0)+IF(T$63=$C$17,0,IF(S$63=$C$17,$B76*(S$60),0)) -> 1.5890667 | T76: =IF(T$63<=$C$17,($C$34*T$59*$B76/$C$63)*(IF(COUNTA($D76:S76)*(12/$C$63)<=$C$9,0,1)),0)+IF(U$63=$C$17,0,IF(T$63=$C$17,$B76*(T$60),0)) -> 1.5890667 | U76: =IF(U$63<=$C$17,($C$34*U$59*$B76/$C$63)*(IF(COUNTA($D76:T76)*(12/$C$63)<=$C$9,0,1)),0)+IF(V$63=$C$17,0,IF(U$63=$C$17,$B76*(U$60),0)) -> 1.5890667 | V76: =IF(V$63<=$C$17,($C$34*V$59*$B76/$C$63)*(IF(COUNTA($D76:U76)*(12/$C$63)<=$C$9,0,1)),0)+IF(W$63=$C$17,0,IF(V$63=$C$17,$B76*(V$60),0)) -> 1.5890667 | ... IW76: =IF(IW$63<=$C$17,($C$34*IW$59*$B76/$C$63)*(IF(COUNTA($D76:IV76)*(12/$C$63)<=$C$9,0,1)),0)+IF(IX$63=$C$17,0,IF(IW$63=$C$17,$B76*(IW$60),0)) -> 0
A77: Versement programmé | B77: =+OFFSET($D$52,0,COUNTA($B$66:B76),,) -> 2 | C77: =SUM(D77:XEG77) -> 160.51597 | O77: =IF(P$63>$C$17,0,-O$53*(12/$C$63)) -> -404 | P77: =IF(P$63<=$C$17,($C$34*P$59*$B77/$C$63)*(IF(COUNTA($D77:O77)*(12/$C$63)<=$C$9,0,1)),0)+IF(Q$63=$C$17,0,IF(P$63=$C$17,$B77*(P$60),0)) -> 0 | Q77: =IF(Q$63<=$C$17,($C$34*Q$59*$B77/$C$63)*(IF(COUNTA($D77:P77)*(12/$C$63)<=$C$9,0,1)),0)+IF(R$63=$C$17,0,IF(Q$63=$C$17,$B77*(Q$60),0)) -> 0 | R77: =IF(R$63<=$C$17,($C$34*R$59*$B77/$C$63)*(IF(COUNTA($D77:Q77)*(12/$C$63)<=$C$9,0,1)),0)+IF(S$63=$C$17,0,IF(R$63=$C$17,$B77*(R$60),0)) -> 0 | S77: =IF(S$63<=$C$17,($C$34*S$59*$B77/$C$63)*(IF(COUNTA($D77:R77)*(12/$C$63)<=$C$9,0,1)),0)+IF(T$63=$C$17,0,IF(S$63=$C$17,$B77*(S$60),0)) -> 0 | T77: =IF(T$63<=$C$17,($C$34*T$59*$B77/$C$63)*(IF(COUNTA($D77:S77)*(12/$C$63)<=$C$9,0,1)),0)+IF(U$63=$C$17,0,IF(T$63=$C$17,$B77*(T$60),0)) -> 1.5890667 | U77: =IF(U$63<=$C$17,($C$34*U$59*$B77/$C$63)*(IF(COUNTA($D77:T77)*(12/$C$63)<=$C$9,0,1)),0)+IF(V$63=$C$17,0,IF(U$63=$C$17,$B77*(U$60),0)) -> 1.5890667 | V77: =IF(V$63<=$C$17,($C$34*V$59*$B77/$C$63)*(IF(COUNTA($D77:U77)*(12/$C$63)<=$C$9,0,1)),0)+IF(W$63=$C$17,0,IF(V$63=$C$17,$B77*(V$60),0)) -> 1.5890667 | W77: =IF(W$63<=$C$17,($C$34*W$59*$B77/$C$63)*(IF(COUNTA($D77:V77)*(12/$C$63)<=$C$9,0,1)),0)+IF(X$63=$C$17,0,IF(W$63=$C$17,$B77*(W$60),0)) -> 1.5890667 | ... IW77: =IF(IW$63<=$C$17,($C$34*IW$59*$B77/$C$63)*(IF(COUNTA($D77:IV77)*(12/$C$63)<=$C$9,0,1)),0)+IF(IX$63=$C$17,0,IF(IW$63=$C$17,$B77*(IW$60),0)) -> 0
A78: Versement programmé | B78: =+OFFSET($D$52,0,COUNTA($B$66:B77),,) -> 2 | C78: =SUM(D78:XEG78) -> 158.9269 | P78: =IF(Q$63>$C$17,0,-P$53*(12/$C$63)) -> -404 | Q78: =IF(Q$63<=$C$17,($C$34*Q$59*$B78/$C$63)*(IF(COUNTA($D78:P78)*(12/$C$63)<=$C$9,0,1)),0)+IF(R$63=$C$17,0,IF(Q$63=$C$17,$B78*(Q$60),0)) -> 0 | R78: =IF(R$63<=$C$17,($C$34*R$59*$B78/$C$63)*(IF(COUNTA($D78:Q78)*(12/$C$63)<=$C$9,0,1)),0)+IF(S$63=$C$17,0,IF(R$63=$C$17,$B78*(R$60),0)) -> 0 | S78: =IF(S$63<=$C$17,($C$34*S$59*$B78/$C$63)*(IF(COUNTA($D78:R78)*(12/$C$63)<=$C$9,0,1)),0)+IF(T$63=$C$17,0,IF(S$63=$C$17,$B78*(S$60),0)) -> 0 | T78: =IF(T$63<=$C$17,($C$34*T$59*$B78/$C$63)*(IF(COUNTA($D78:S78)*(12/$C$63)<=$C$9,0,1)),0)+IF(U$63=$C$17,0,IF(T$63=$C$17,$B78*(T$60),0)) -> 0 | U78: =IF(U$63<=$C$17,($C$34*U$59*$B78/$C$63)*(IF(COUNTA($D78:T78)*(12/$C$63)<=$C$9,0,1)),0)+IF(V$63=$C$17,0,IF(U$63=$C$17,$B78*(U$60),0)) -> 1.5890667 | V78: =IF(V$63<=$C$17,($C$34*V$59*$B78/$C$63)*(IF(COUNTA($D78:U78)*(12/$C$63)<=$C$9,0,1)),0)+IF(W$63=$C$17,0,IF(V$63=$C$17,$B78*(V$60),0)) -> 1.5890667 | W78: =IF(W$63<=$C$17,($C$34*W$59*$B78/$C$63)*(IF(COUNTA($D78:V78)*(12/$C$63)<=$C$9,0,1)),0)+IF(X$63=$C$17,0,IF(W$63=$C$17,$B78*(W$60),0)) -> 1.5890667 | X78: =IF(X$63<=$C$17,($C$34*X$59*$B78/$C$63)*(IF(COUNTA($D78:W78)*(12/$C$63)<=$C$9,0,1)),0)+IF(Y$63=$C$17,0,IF(X$63=$C$17,$B78*(X$60),0)) -> 1.5890667 | ... IW78: =IF(IW$63<=$C$17,($C$34*IW$59*$B78/$C$63)*(IF(COUNTA($D78:IV78)*(12/$C$63)<=$C$9,0,1)),0)+IF(IX$63=$C$17,0,IF(IW$63=$C$17,$B78*(IW$60),0)) -> 0
A79: Versement programmé | B79: =+OFFSET($D$52,0,COUNTA($B$66:B78),,) -> 3 | C79: =SUM(D79:XEG79) -> 229.94675 | Q79: =IF(R$63>$C$17,0,-Q$53*(12/$C$63)) -> -612.06 | R79: =IF(R$63<=$C$17,($C$34*R$59*$B79/$C$63)*(IF(COUNTA($D79:Q79)*(12/$C$63)<=$C$9,0,1)),0)+IF(S$63=$C$17,0,IF(R$63=$C$17,$B79*(R$60),0)) -> 0 | S79: =IF(S$63<=$C$17,($C$34*S$59*$B79/$C$63)*(IF(COUNTA($D79:R79)*(12/$C$63)<=$C$9,0,1)),0)+IF(T$63=$C$17,0,IF(S$63=$C$17,$B79*(S$60),0)) -> 0 | T79: =IF(T$63<=$C$17,($C$34*T$59*$B79/$C$63)*(IF(COUNTA($D79:S79)*(12/$C$63)<=$C$9,0,1)),0)+IF(U$63=$C$17,0,IF(T$63=$C$17,$B79*(T$60),0)) -> 0 | U79: =IF(U$63<=$C$17,($C$34*U$59*$B79/$C$63)*(IF(COUNTA($D79:T79)*(12/$C$63)<=$C$9,0,1)),0)+IF(V$63=$C$17,0,IF(U$63=$C$17,$B79*(U$60),0)) -> 0 | V79: =IF(V$63<=$C$17,($C$34*V$59*$B79/$C$63)*(IF(COUNTA($D79:U79)*(12/$C$63)<=$C$9,0,1)),0)+IF(W$63=$C$17,0,IF(V$63=$C$17,$B79*(V$60),0)) -> 2.3836 | W79: =IF(W$63<=$C$17,($C$34*W$59*$B79/$C$63)*(IF(COUNTA($D79:V79)*(12/$C$63)<=$C$9,0,1)),0)+IF(X$63=$C$17,0,IF(W$63=$C$17,$B79*(W$60),0)) -> 2.3836 | X79: =IF(X$63<=$C$17,($C$34*X$59*$B79/$C$63)*(IF(COUNTA($D79:W79)*(12/$C$63)<=$C$9,0,1)),0)+IF(Y$63=$C$17,0,IF(X$63=$C$17,$B79*(X$60),0)) -> 2.3836 | Y79: =IF(Y$63<=$C$17,($C$34*Y$59*$B79/$C$63)*(IF(COUNTA($D79:X79)*(12/$C$63)<=$C$9,0,1)),0)+IF(Z$63=$C$17,0,IF(Y$63=$C$17,$B79*(Y$60),0)) -> 2.3836 | ... IW79: =IF(IW$63<=$C$17,($C$34*IW$59*$B79/$C$63)*(IF(COUNTA($D79:IV79)*(12/$C$63)<=$C$9,0,1)),0)+IF(IX$63=$C$17,0,IF(IW$63=$C$17,$B79*(IW$60),0)) -> 0
A80: Versement programmé | B80: =+OFFSET($D$52,0,COUNTA($B$66:B79),,) -> 2 | C80: =SUM(D80:XEG80) -> 151.70877 | R80: =IF(S$63>$C$17,0,-R$53*(12/$C$63)) -> -408.04 | S80: =IF(S$63<=$C$17,($C$34*S$59*$B80/$C$63)*(IF(COUNTA($D80:R80)*(12/$C$63)<=$C$9,0,1)),0)+IF(T$63=$C$17,0,IF(S$63=$C$17,$B80*(S$60),0)) -> 0 | T80: =IF(T$63<=$C$17,($C$34*T$59*$B80/$C$63)*(IF(COUNTA($D80:S80)*(12/$C$63)<=$C$9,0,1)),0)+IF(U$63=$C$17,0,IF(T$63=$C$17,$B80*(T$60),0)) -> 0 | U80: =IF(U$63<=$C$17,($C$34*U$59*$B80/$C$63)*(IF(COUNTA($D80:T80)*(12/$C$63)<=$C$9,0,1)),0)+IF(V$63=$C$17,0,IF(U$63=$C$17,$B80*(U$60),0)) -> 0 | V80: =IF(V$63<=$C$17,($C$34*V$59*$B80/$C$63)*(IF(COUNTA($D80:U80)*(12/$C$63)<=$C$9,0,1)),0)+IF(W$63=$C$17,0,IF(V$63=$C$17,$B80*(V$60),0)) -> 0 | W80: =IF(W$63<=$C$17,($C$34*W$59*$B80/$C$63)*(IF(COUNTA($D80:V80)*(12/$C$63)<=$C$9,0,1)),0)+IF(X$63=$C$17,0,IF(W$63=$C$17,$B80*(W$60),0)) -> 1.5890667 | X80: =IF(X$63<=$C$17,($C$34*X$59*$B80/$C$63)*(IF(COUNTA($D80:W80)*(12/$C$63)<=$C$9,0,1)),0)+IF(Y$63=$C$17,0,IF(X$63=$C$17,$B80*(X$60),0)) -> 1.5890667 | Y80: =IF(Y$63<=$C$17,($C$34*Y$59*$B80/$C$63)*(IF(COUNTA($D80:X80)*(12/$C$63)<=$C$9,0,1)),0)+IF(Z$63=$C$17,0,IF(Y$63=$C$17,$B80*(Y$60),0)) -> 1.5890667 | Z80: =IF(Z$63<=$C$17,($C$34*Z$59*$B80/$C$63)*(IF(COUNTA($D80:Y80)*(12/$C$63)<=$C$9,0,1)),0)+IF(AA$63=$C$17,0,IF(Z$63=$C$17,$B80*(Z$60),0)) -> 1.5890667 | ... IW80: =IF(IW$63<=$C$17,($C$34*IW$59*$B80/$C$63)*(IF(COUNTA($D80:IV80)*(12/$C$63)<=$C$9,0,1)),0)+IF(IX$63=$C$17,0,IF(IW$63=$C$17,$B80*(IW$60),0)) -> 0
A81: Versement programmé | B81: =+OFFSET($D$52,0,COUNTA($B$66:B80),,) -> 2 | C81: =SUM(D81:XEG81) -> 150.1197 | S81: =IF(T$63>$C$17,0,-S$53*(12/$C$63)) -> -408.04 | T81: =IF(T$63<=$C$17,($C$34*T$59*$B81/$C$63)*(IF(COUNTA($D81:S81)*(12/$C$63)<=$C$9,0,1)),0)+IF(U$63=$C$17,0,IF(T$63=$C$17,$B81*(T$60),0)) -> 0 | U81: =IF(U$63<=$C$17,($C$34*U$59*$B81/$C$63)*(IF(COUNTA($D81:T81)*(12/$C$63)<=$C$9,0,1)),0)+IF(V$63=$C$17,0,IF(U$63=$C$17,$B81*(U$60),0)) -> 0 | V81: =IF(V$63<=$C$17,($C$34*V$59*$B81/$C$63)*(IF(COUNTA($D81:U81)*(12/$C$63)<=$C$9,0,1)),0)+IF(W$63=$C$17,0,IF(V$63=$C$17,$B81*(V$60),0)) -> 0 | W81: =IF(W$63<=$C$17,($C$34*W$59*$B81/$C$63)*(IF(COUNTA($D81:V81)*(12/$C$63)<=$C$9,0,1)),0)+IF(X$63=$C$17,0,IF(W$63=$C$17,$B81*(W$60),0)) -> 0 | X81: =IF(X$63<=$C$17,($C$34*X$59*$B81/$C$63)*(IF(COUNTA($D81:W81)*(12/$C$63)<=$C$9,0,1)),0)+IF(Y$63=$C$17,0,IF(X$63=$C$17,$B81*(X$60),0)) -> 1.5890667 | Y81: =IF(Y$63<=$C$17,($C$34*Y$59*$B81/$C$63)*(IF(COUNTA($D81:X81)*(12/$C$63)<=$C$9,0,1)),0)+IF(Z$63=$C$17,0,IF(Y$63=$C$17,$B81*(Y$60),0)) -> 1.5890667 | Z81: =IF(Z$63<=$C$17,($C$34*Z$59*$B81/$C$63)*(IF(COUNTA($D81:Y81)*(12/$C$63)<=$C$9,0,1)),0)+IF(AA$63=$C$17,0,IF(Z$63=$C$17,$B81*(Z$60),0)) -> 1.5890667 | AA81: =IF(AA$63<=$C$17,($C$34*AA$59*$B81/$C$63)*(IF(COUNTA($D81:Z81)*(12/$C$63)<=$C$9,0,1)),0)+IF(AB$63=$C$17,0,IF(AA$63=$C$17,$B81*(AA$60),0)) -> 1.5890667 | ... IW81: =IF(IW$63<=$C$17,($C$34*IW$59*$B81/$C$63)*(IF(COUNTA($D81:IV81)*(12/$C$63)<=$C$9,0,1)),0)+IF(IX$63=$C$17,0,IF(IW$63=$C$17,$B81*(IW$60),0)) -> 0
A82: Versement programmé | B82: =+OFFSET($D$52,0,COUNTA($B$66:B81),,) -> 2 | C82: =SUM(D82:XEG82) -> 148.53063 | T82: =IF(U$63>$C$17,0,-T$53*(12/$C$63)) -> -408.04 | U82: =IF(U$63<=$C$17,($C$34*U$59*$B82/$C$63)*(IF(COUNTA($D82:T82)*(12/$C$63)<=$C$9,0,1)),0)+IF(V$63=$C$17,0,IF(U$63=$C$17,$B82*(U$60),0)) -> 0 | V82: =IF(V$63<=$C$17,($C$34*V$59*$B82/$C$63)*(IF(COUNTA($D82:U82)*(12/$C$63)<=$C$9,0,1)),0)+IF(W$63=$C$17,0,IF(V$63=$C$17,$B82*(V$60),0)) -> 0 | W82: =IF(W$63<=$C$17,($C$34*W$59*$B82/$C$63)*(IF(COUNTA($D82:V82)*(12/$C$63)<=$C$9,0,1)),0)+IF(X$63=$C$17,0,IF(W$63=$C$17,$B82*(W$60),0)) -> 0 | X82: =IF(X$63<=$C$17,($C$34*X$59*$B82/$C$63)*(IF(COUNTA($D82:W82)*(12/$C$63)<=$C$9,0,1)),0)+IF(Y$63=$C$17,0,IF(X$63=$C$17,$B82*(X$60),0)) -> 0 | Y82: =IF(Y$63<=$C$17,($C$34*Y$59*$B82/$C$63)*(IF(COUNTA($D82:X82)*(12/$C$63)<=$C$9,0,1)),0)+IF(Z$63=$C$17,0,IF(Y$63=$C$17,$B82*(Y$60),0)) -> 1.5890667 | Z82: =IF(Z$63<=$C$17,($C$34*Z$59*$B82/$C$63)*(IF(COUNTA($D82:Y82)*(12/$C$63)<=$C$9,0,1)),0)+IF(AA$63=$C$17,0,IF(Z$63=$C$17,$B82*(Z$60),0)) -> 1.5890667 | AA82: =IF(AA$63<=$C$17,($C$34*AA$59*$B82/$C$63)*(IF(COUNTA($D82:Z82)*(12/$C$63)<=$C$9,0,1)),0)+IF(AB$63=$C$17,0,IF(AA$63=$C$17,$B82*(AA$60),0)) -> 1.5890667 | AB82: =IF(AB$63<=$C$17,($C$34*AB$59*$B82/$C$63)*(IF(COUNTA($D82:AA82)*(12/$C$63)<=$C$9,0,1)),0)+IF(AC$63=$C$17,0,IF(AB$63=$C$17,$B82*(AB$60),0)) -> 1.5890667 | ... IW82: =IF(IW$63<=$C$17,($C$34*IW$59*$B82/$C$63)*(IF(COUNTA($D82:IV82)*(12/$C$63)<=$C$9,0,1)),0)+IF(IX$63=$C$17,0,IF(IW$63=$C$17,$B82*(IW$60),0)) -> 0
A83: Versement programmé | B83: =+OFFSET($D$52,0,COUNTA($B$66:B82),,) -> 3 | C83: =SUM(D83:XEG83) -> 220.41235 | U83: =IF(V$63>$C$17,0,-U$53*(12/$C$63)) -> -612.06 | V83: =IF(V$63<=$C$17,($C$34*V$59*$B83/$C$63)*(IF(COUNTA($D83:U83)*(12/$C$63)<=$C$9,0,1)),0)+IF(W$63=$C$17,0,IF(V$63=$C$17,$B83*(V$60),0)) -> 0 | W83: =IF(W$63<=$C$17,($C$34*W$59*$B83/$C$63)*(IF(COUNTA($D83:V83)*(12/$C$63)<=$C$9,0,1)),0)+IF(X$63=$C$17,0,IF(W$63=$C$17,$B83*(W$60),0)) -> 0 | X83: =IF(X$63<=$C$17,($C$34*X$59*$B83/$C$63)*(IF(COUNTA($D83:W83)*(12/$C$63)<=$C$9,0,1)),0)+IF(Y$63=$C$17,0,IF(X$63=$C$17,$B83*(X$60),0)) -> 0 | Y83: =IF(Y$63<=$C$17,($C$34*Y$59*$B83/$C$63)*(IF(COUNTA($D83:X83)*(12/$C$63)<=$C$9,0,1)),0)+IF(Z$63=$C$17,0,IF(Y$63=$C$17,$B83*(Y$60),0)) -> 0 | Z83: =IF(Z$63<=$C$17,($C$34*Z$59*$B83/$C$63)*(IF(COUNTA($D83:Y83)*(12/$C$63)<=$C$9,0,1)),0)+IF(AA$63=$C$17,0,IF(Z$63=$C$17,$B83*(Z$60),0)) -> 2.3836 | AA83: =IF(AA$63<=$C$17,($C$34*AA$59*$B83/$C$63)*(IF(COUNTA($D83:Z83)*(12/$C$63)<=$C$9,0,1)),0)+IF(AB$63=$C$17,0,IF(AA$63=$C$17,$B83*(AA$60),0)) -> 2.3836 | AB83: =IF(AB$63<=$C$17,($C$34*AB$59*$B83/$C$63)*(IF(COUNTA($D83:AA83)*(12/$C$63)<=$C$9,0,1)),0)+IF(AC$63=$C$17,0,IF(AB$63=$C$17,$B83*(AB$60),0)) -> 2.3836 | AC83: =IF(AC$63<=$C$17,($C$34*AC$59*$B83/$C$63)*(IF(COUNTA($D83:AB83)*(12/$C$63)<=$C$9,0,1)),0)+IF(AD$63=$C$17,0,IF(AC$63=$C$17,$B83*(AC$60),0)) -> 2.3836 | ... IW83: =IF(IW$63<=$C$17,($C$34*IW$59*$B83/$C$63)*(IF(COUNTA($D83:IV83)*(12/$C$63)<=$C$9,0,1)),0)+IF(IX$63=$C$17,0,IF(IW$63=$C$17,$B83*(IW$60),0)) -> 0
A84: Versement programmé | B84: =+OFFSET($D$52,0,COUNTA($B$66:B83),,) -> 2 | C84: =SUM(D84:XEG84) -> 145.3525 | V84: =IF(W$63>$C$17,0,-V$53*(12/$C$63)) -> -408.04 | W84: =IF(W$63<=$C$17,($C$34*W$59*$B84/$C$63)*(IF(COUNTA($D84:V84)*(12/$C$63)<=$C$9,0,1)),0)+IF(X$63=$C$17,0,IF(W$63=$C$17,$B84*(W$60),0)) -> 0 | X84: =IF(X$63<=$C$17,($C$34*X$59*$B84/$C$63)*(IF(COUNTA($D84:W84)*(12/$C$63)<=$C$9,0,1)),0)+IF(Y$63=$C$17,0,IF(X$63=$C$17,$B84*(X$60),0)) -> 0 | Y84: =IF(Y$63<=$C$17,($C$34*Y$59*$B84/$C$63)*(IF(COUNTA($D84:X84)*(12/$C$63)<=$C$9,0,1)),0)+IF(Z$63=$C$17,0,IF(Y$63=$C$17,$B84*(Y$60),0)) -> 0 | Z84: =IF(Z$63<=$C$17,($C$34*Z$59*$B84/$C$63)*(IF(COUNTA($D84:Y84)*(12/$C$63)<=$C$9,0,1)),0)+IF(AA$63=$C$17,0,IF(Z$63=$C$17,$B84*(Z$60),0)) -> 0 | AA84: =IF(AA$63<=$C$17,($C$34*AA$59*$B84/$C$63)*(IF(COUNTA($D84:Z84)*(12/$C$63)<=$C$9,0,1)),0)+IF(AB$63=$C$17,0,IF(AA$63=$C$17,$B84*(AA$60),0)) -> 1.5890667 | AB84: =IF(AB$63<=$C$17,($C$34*AB$59*$B84/$C$63)*(IF(COUNTA($D84:AA84)*(12/$C$63)<=$C$9,0,1)),0)+IF(AC$63=$C$17,0,IF(AB$63=$C$17,$B84*(AB$60),0)) -> 1.5890667 | AC84: =IF(AC$63<=$C$17,($C$34*AC$59*$B84/$C$63)*(IF(COUNTA($D84:AB84)*(12/$C$63)<=$C$9,0,1)),0)+IF(AD$63=$C$17,0,IF(AC$63=$C$17,$B84*(AC$60),0)) -> 1.5890667 | AD84: =IF(AD$63<=$C$17,($C$34*AD$59*$B84/$C$63)*(IF(COUNTA($D84:AC84)*(12/$C$63)<=$C$9,0,1)),0)+IF(AE$63=$C$17,0,IF(AD$63=$C$17,$B84*(AD$60),0)) -> 1.5890667 | ... IW84: =IF(IW$63<=$C$17,($C$34*IW$59*$B84/$C$63)*(IF(COUNTA($D84:IV84)*(12/$C$63)<=$C$9,0,1)),0)+IF(IX$63=$C$17,0,IF(IW$63=$C$17,$B84*(IW$60),0)) -> 0
A85: Versement programmé | B85: =+OFFSET($D$52,0,COUNTA($B$66:B84),,) -> 2 | C85: =SUM(D85:XEG85) -> 143.76343 | W85: =IF(X$63>$C$17,0,-W$53*(12/$C$63)) -> -408.04 | X85: =IF(X$63<=$C$17,($C$34*X$59*$B85/$C$63)*(IF(COUNTA($D85:W85)*(12/$C$63)<=$C$9,0,1)),0)+IF(Y$63=$C$17,0,IF(X$63=$C$17,$B85*(X$60),0)) -> 0 | Y85: =IF(Y$63<=$C$17,($C$34*Y$59*$B85/$C$63)*(IF(COUNTA($D85:X85)*(12/$C$63)<=$C$9,0,1)),0)+IF(Z$63=$C$17,0,IF(Y$63=$C$17,$B85*(Y$60),0)) -> 0 | Z85: =IF(Z$63<=$C$17,($C$34*Z$59*$B85/$C$63)*(IF(COUNTA($D85:Y85)*(12/$C$63)<=$C$9,0,1)),0)+IF(AA$63=$C$17,0,IF(Z$63=$C$17,$B85*(Z$60),0)) -> 0 | AA85: =IF(AA$63<=$C$17,($C$34*AA$59*$B85/$C$63)*(IF(COUNTA($D85:Z85)*(12/$C$63)<=$C$9,0,1)),0)+IF(AB$63=$C$17,0,IF(AA$63=$C$17,$B85*(AA$60),0)) -> 0 | AB85: =IF(AB$63<=$C$17,($C$34*AB$59*$B85/$C$63)*(IF(COUNTA($D85:AA85)*(12/$C$63)<=$C$9,0,1)),0)+IF(AC$63=$C$17,0,IF(AB$63=$C$17,$B85*(AB$60),0)) -> 1.5890667 | AC85: =IF(AC$63<=$C$17,($C$34*AC$59*$B85/$C$63)*(IF(COUNTA($D85:AB85)*(12/$C$63)<=$C$9,0,1)),0)+IF(AD$63=$C$17,0,IF(AC$63=$C$17,$B85*(AC$60),0)) -> 1.5890667 | AD85: =IF(AD$63<=$C$17,($C$34*AD$59*$B85/$C$63)*(IF(COUNTA($D85:AC85)*(12/$C$63)<=$C$9,0,1)),0)+IF(AE$63=$C$17,0,IF(AD$63=$C$17,$B85*(AD$60),0)) -> 1.5890667 | AE85: =IF(AE$63<=$C$17,($C$34*AE$59*$B85/$C$63)*(IF(COUNTA($D85:AD85)*(12/$C$63)<=$C$9,0,1)),0)+IF(AF$63=$C$17,0,IF(AE$63=$C$17,$B85*(AE$60),0)) -> 1.5890667 | ... IW85: =IF(IW$63<=$C$17,($C$34*IW$59*$B85/$C$63)*(IF(COUNTA($D85:IV85)*(12/$C$63)<=$C$9,0,1)),0)+IF(IX$63=$C$17,0,IF(IW$63=$C$17,$B85*(IW$60),0)) -> 0
A86: Versement programmé | B86: =+OFFSET($D$52,0,COUNTA($B$66:B85),,) -> 3 | C86: =SUM(D86:XEG86) -> 213.26155 | X86: =IF(Y$63>$C$17,0,-X$53*(12/$C$63)) -> -612.06 | Y86: =IF(Y$63<=$C$17,($C$34*Y$59*$B86/$C$63)*(IF(COUNTA($D86:X86)*(12/$C$63)<=$C$9,0,1)),0)+IF(Z$63=$C$17,0,IF(Y$63=$C$17,$B86*(Y$60),0)) -> 0 | Z86: =IF(Z$63<=$C$17,($C$34*Z$59*$B86/$C$63)*(IF(COUNTA($D86:Y86)*(12/$C$63)<=$C$9,0,1)),0)+IF(AA$63=$C$17,0,IF(Z$63=$C$17,$B86*(Z$60),0)) -> 0 | AA86: =IF(AA$63<=$C$17,($C$34*AA$59*$B86/$C$63)*(IF(COUNTA($D86:Z86)*(12/$C$63)<=$C$9,0,1)),0)+IF(AB$63=$C$17,0,IF(AA$63=$C$17,$B86*(AA$60),0)) -> 0 | AB86: =IF(AB$63<=$C$17,($C$34*AB$59*$B86/$C$63)*(IF(COUNTA($D86:AA86)*(12/$C$63)<=$C$9,0,1)),0)+IF(AC$63=$C$17,0,IF(AB$63=$C$17,$B86*(AB$60),0)) -> 0 | AC86: =IF(AC$63<=$C$17,($C$34*AC$59*$B86/$C$63)*(IF(COUNTA($D86:AB86)*(12/$C$63)<=$C$9,0,1)),0)+IF(AD$63=$C$17,0,IF(AC$63=$C$17,$B86*(AC$60),0)) -> 2.3836 | AD86: =IF(AD$63<=$C$17,($C$34*AD$59*$B86/$C$63)*(IF(COUNTA($D86:AC86)*(12/$C$63)<=$C$9,0,1)),0)+IF(AE$63=$C$17,0,IF(AD$63=$C$17,$B86*(AD$60),0)) -> 2.3836 | AE86: =IF(AE$63<=$C$17,($C$34*AE$59*$B86/$C$63)*(IF(COUNTA($D86:AD86)*(12/$C$63)<=$C$9,0,1)),0)+IF(AF$63=$C$17,0,IF(AE$63=$C$17,$B86*(AE$60),0)) -> 2.3836 | AF86: =IF(AF$63<=$C$17,($C$34*AF$59*$B86/$C$63)*(IF(COUNTA($D86:AE86)*(12/$C$63)<=$C$9,0,1)),0)+IF(AG$63=$C$17,0,IF(AF$63=$C$17,$B86*(AF$60),0)) -> 2.3836 | ... IW86: =IF(IW$63<=$C$17,($C$34*IW$59*$B86/$C$63)*(IF(COUNTA($D86:IV86)*(12/$C$63)<=$C$9,0,1)),0)+IF(IX$63=$C$17,0,IF(IW$63=$C$17,$B86*(IW$60),0)) -> 0
A87: Versement programmé | B87: =+OFFSET($D$52,0,COUNTA($B$66:B86),,) -> 2 | C87: =SUM(D87:XEG87) -> 140.5853 | Y87: =IF(Z$63>$C$17,0,-Y$53*(12/$C$63)) -> -408.04 | Z87: =IF(Z$63<=$C$17,($C$34*Z$59*$B87/$C$63)*(IF(COUNTA($D87:Y87)*(12/$C$63)<=$C$9,0,1)),0)+IF(AA$63=$C$17,0,IF(Z$63=$C$17,$B87*(Z$60),0)) -> 0 | AA87: =IF(AA$63<=$C$17,($C$34*AA$59*$B87/$C$63)*(IF(COUNTA($D87:Z87)*(12/$C$63)<=$C$9,0,1)),0)+IF(AB$63=$C$17,0,IF(AA$63=$C$17,$B87*(AA$60),0)) -> 0 | AB87: =IF(AB$63<=$C$17,($C$34*AB$59*$B87/$C$63)*(IF(COUNTA($D87:AA87)*(12/$C$63)<=$C$9,0,1)),0)+IF(AC$63=$C$17,0,IF(AB$63=$C$17,$B87*(AB$60),0)) -> 0 | AC87: =IF(AC$63<=$C$17,($C$34*AC$59*$B87/$C$63)*(IF(COUNTA($D87:AB87)*(12/$C$63)<=$C$9,0,1)),0)+IF(AD$63=$C$17,0,IF(AC$63=$C$17,$B87*(AC$60),0)) -> 0 | AD87: =IF(AD$63<=$C$17,($C$34*AD$59*$B87/$C$63)*(IF(COUNTA($D87:AC87)*(12/$C$63)<=$C$9,0,1)),0)+IF(AE$63=$C$17,0,IF(AD$63=$C$17,$B87*(AD$60),0)) -> 1.5890667 | AE87: =IF(AE$63<=$C$17,($C$34*AE$59*$B87/$C$63)*(IF(COUNTA($D87:AD87)*(12/$C$63)<=$C$9,0,1)),0)+IF(AF$63=$C$17,0,IF(AE$63=$C$17,$B87*(AE$60),0)) -> 1.5890667 | AF87: =IF(AF$63<=$C$17,($C$34*AF$59*$B87/$C$63)*(IF(COUNTA($D87:AE87)*(12/$C$63)<=$C$9,0,1)),0)+IF(AG$63=$C$17,0,IF(AF$63=$C$17,$B87*(AF$60),0)) -> 1.5890667 | AG87: =IF(AG$63<=$C$17,($C$34*AG$59*$B87/$C$63)*(IF(COUNTA($D87:AF87)*(12/$C$63)<=$C$9,0,1)),0)+IF(AH$63=$C$17,0,IF(AG$63=$C$17,$B87*(AG$60),0)) -> 1.5890667 | ... IW87: =IF(IW$63<=$C$17,($C$34*IW$59*$B87/$C$63)*(IF(COUNTA($D87:IV87)*(12/$C$63)<=$C$9,0,1)),0)+IF(IX$63=$C$17,0,IF(IW$63=$C$17,$B87*(IW$60),0)) -> 0
A88: Versement programmé | B88: =+OFFSET($D$52,0,COUNTA($B$66:B87),,) -> 2 | C88: =SUM(D88:XEG88) -> 138.99623 | Z88: =IF(AA$63>$C$17,0,-Z$53*(12/$C$63)) -> -408.04 | AA88: =IF(AA$63<=$C$17,($C$34*AA$59*$B88/$C$63)*(IF(COUNTA($D88:Z88)*(12/$C$63)<=$C$9,0,1)),0)+IF(AB$63=$C$17,0,IF(AA$63=$C$17,$B88*(AA$60),0)) -> 0 | AB88: =IF(AB$63<=$C$17,($C$34*AB$59*$B88/$C$63)*(IF(COUNTA($D88:AA88)*(12/$C$63)<=$C$9,0,1)),0)+IF(AC$63=$C$17,0,IF(AB$63=$C$17,$B88*(AB$60),0)) -> 0 | AC88: =IF(AC$63<=$C$17,($C$34*AC$59*$B88/$C$63)*(IF(COUNTA($D88:AB88)*(12/$C$63)<=$C$9,0,1)),0)+IF(AD$63=$C$17,0,IF(AC$63=$C$17,$B88*(AC$60),0)) -> 0 | AD88: =IF(AD$63<=$C$17,($C$34*AD$59*$B88/$C$63)*(IF(COUNTA($D88:AC88)*(12/$C$63)<=$C$9,0,1)),0)+IF(AE$63=$C$17,0,IF(AD$63=$C$17,$B88*(AD$60),0)) -> 0 | AE88: =IF(AE$63<=$C$17,($C$34*AE$59*$B88/$C$63)*(IF(COUNTA($D88:AD88)*(12/$C$63)<=$C$9,0,1)),0)+IF(AF$63=$C$17,0,IF(AE$63=$C$17,$B88*(AE$60),0)) -> 1.5890667 | AF88: =IF(AF$63<=$C$17,($C$34*AF$59*$B88/$C$63)*(IF(COUNTA($D88:AE88)*(12/$C$63)<=$C$9,0,1)),0)+IF(AG$63=$C$17,0,IF(AF$63=$C$17,$B88*(AF$60),0)) -> 1.5890667 | AG88: =IF(AG$63<=$C$17,($C$34*AG$59*$B88/$C$63)*(IF(COUNTA($D88:AF88)*(12/$C$63)<=$C$9,0,1)),0)+IF(AH$63=$C$17,0,IF(AG$63=$C$17,$B88*(AG$60),0)) -> 1.5890667 | AH88: =IF(AH$63<=$C$17,($C$34*AH$59*$B88/$C$63)*(IF(COUNTA($D88:AG88)*(12/$C$63)<=$C$9,0,1)),0)+IF(AI$63=$C$17,0,IF(AH$63=$C$17,$B88*(AH$60),0)) -> 1.5890667 | ... IW88: =IF(IW$63<=$C$17,($C$34*IW$59*$B88/$C$63)*(IF(COUNTA($D88:IV88)*(12/$C$63)<=$C$9,0,1)),0)+IF(IX$63=$C$17,0,IF(IW$63=$C$17,$B88*(IW$60),0)) -> 0
A89: Versement programmé | B89: =+OFFSET($D$52,0,COUNTA($B$66:B88),,) -> 3 | C89: =SUM(D89:XEG89) -> 206.11075 | AA89: =IF(AB$63>$C$17,0,-AA$53*(12/$C$63)) -> -612.06 | AB89: =IF(AB$63<=$C$17,($C$34*AB$59*$B89/$C$63)*(IF(COUNTA($D89:AA89)*(12/$C$63)<=$C$9,0,1)),0)+IF(AC$63=$C$17,0,IF(AB$63=$C$17,$B89*(AB$60),0)) -> 0 | AC89: =IF(AC$63<=$C$17,($C$34*AC$59*$B89/$C$63)*(IF(COUNTA($D89:AB89)*(12/$C$63)<=$C$9,0,1)),0)+IF(AD$63=$C$17,0,IF(AC$63=$C$17,$B89*(AC$60),0)) -> 0 | AD89: =IF(AD$63<=$C$17,($C$34*AD$59*$B89/$C$63)*(IF(COUNTA($D89:AC89)*(12/$C$63)<=$C$9,0,1)),0)+IF(AE$63=$C$17,0,IF(AD$63=$C$17,$B89*(AD$60),0)) -> 0 | AE89: =IF(AE$63<=$C$17,($C$34*AE$59*$B89/$C$63)*(IF(COUNTA($D89:AD89)*(12/$C$63)<=$C$9,0,1)),0)+IF(AF$63=$C$17,0,IF(AE$63=$C$17,$B89*(AE$60),0)) -> 0 | AF89: =IF(AF$63<=$C$17,($C$34*AF$59*$B89/$C$63)*(IF(COUNTA($D89:AE89)*(12/$C$63)<=$C$9,0,1)),0)+IF(AG$63=$C$17,0,IF(AF$63=$C$17,$B89*(AF$60),0)) -> 2.3836 | AG89: =IF(AG$63<=$C$17,($C$34*AG$59*$B89/$C$63)*(IF(COUNTA($D89:AF89)*(12/$C$63)<=$C$9,0,1)),0)+IF(AH$63=$C$17,0,IF(AG$63=$C$17,$B89*(AG$60),0)) -> 2.3836 | AH89: =IF(AH$63<=$C$17,($C$34*AH$59*$B89/$C$63)*(IF(COUNTA($D89:AG89)*(12/$C$63)<=$C$9,0,1)),0)+IF(AI$63=$C$17,0,IF(AH$63=$C$17,$B89*(AH$60),0)) -> 2.3836 | AI89: =IF(AI$63<=$C$17,($C$34*AI$59*$B89/$C$63)*(IF(COUNTA($D89:AH89)*(12/$C$63)<=$C$9,0,1)),0)+IF(AJ$63=$C$17,0,IF(AI$63=$C$17,$B89*(AI$60),0)) -> 2.3836 | ... IW89: =IF(IW$63<=$C$17,($C$34*IW$59*$B89/$C$63)*(IF(COUNTA($D89:IV89)*(12/$C$63)<=$C$9,0,1)),0)+IF(IX$63=$C$17,0,IF(IW$63=$C$17,$B89*(IW$60),0)) -> 0
A90: Versement programmé | B90: =+OFFSET($D$52,0,COUNTA($B$66:B89),,) -> 2 | C90: =SUM(D90:XEG90) -> 135.8181 | AB90: =IF(AC$63>$C$17,0,-AB$53*(12/$C$63)) -> -408.04 | AC90: =IF(AC$63<=$C$17,($C$34*AC$59*$B90/$C$63)*(IF(COUNTA($D90:AB90)*(12/$C$63)<=$C$9,0,1)),0)+IF(AD$63=$C$17,0,IF(AC$63=$C$17,$B90*(AC$60),0)) -> 0 | AD90: =IF(AD$63<=$C$17,($C$34*AD$59*$B90/$C$63)*(IF(COUNTA($D90:AC90)*(12/$C$63)<=$C$9,0,1)),0)+IF(AE$63=$C$17,0,IF(AD$63=$C$17,$B90*(AD$60),0)) -> 0 | AE90: =IF(AE$63<=$C$17,($C$34*AE$59*$B90/$C$63)*(IF(COUNTA($D90:AD90)*(12/$C$63)<=$C$9,0,1)),0)+IF(AF$63=$C$17,0,IF(AE$63=$C$17,$B90*(AE$60),0)) -> 0 | AF90: =IF(AF$63<=$C$17,($C$34*AF$59*$B90/$C$63)*(IF(COUNTA($D90:AE90)*(12/$C$63)<=$C$9,0,1)),0)+IF(AG$63=$C$17,0,IF(AF$63=$C$17,$B90*(AF$60),0)) -> 0 | AG90: =IF(AG$63<=$C$17,($C$34*AG$59*$B90/$C$63)*(IF(COUNTA($D90:AF90)*(12/$C$63)<=$C$9,0,1)),0)+IF(AH$63=$C$17,0,IF(AG$63=$C$17,$B90*(AG$60),0)) -> 1.5890667 | AH90: =IF(AH$63<=$C$17,($C$34*AH$59*$B90/$C$63)*(IF(COUNTA($D90:AG90)*(12/$C$63)<=$C$9,0,1)),0)+IF(AI$63=$C$17,0,IF(AH$63=$C$17,$B90*(AH$60),0)) -> 1.5890667 | AI90: =IF(AI$63<=$C$17,($C$34*AI$59*$B90/$C$63)*(IF(COUNTA($D90:AH90)*(12/$C$63)<=$C$9,0,1)),0)+IF(AJ$63=$C$17,0,IF(AI$63=$C$17,$B90*(AI$60),0)) -> 1.5890667 | AJ90: =IF(AJ$63<=$C$17,($C$34*AJ$59*$B90/$C$63)*(IF(COUNTA($D90:AI90)*(12/$C$63)<=$C$9,0,1)),0)+IF(AK$63=$C$17,0,IF(AJ$63=$C$17,$B90*(AJ$60),0)) -> 1.5890667 | ... IW90: =IF(IW$63<=$C$17,($C$34*IW$59*$B90/$C$63)*(IF(COUNTA($D90:IV90)*(12/$C$63)<=$C$9,0,1)),0)+IF(IX$63=$C$17,0,IF(IW$63=$C$17,$B90*(IW$60),0)) -> 0
A91: Versement programmé | B91: =+OFFSET($D$52,0,COUNTA($B$66:B90),,) -> 2 | C91: =SUM(D91:XEG91) -> 130.14863 | AC91: =IF(AD$63>$C$17,0,-AC$53*(12/$C$63)) -> -412.1204 | AD91: =IF(AD$63<=$C$17,($C$34*AD$59*$B91/$C$63)*(IF(COUNTA($D91:AC91)*(12/$C$63)<=$C$9,0,1)),0)+IF(AE$63=$C$17,0,IF(AD$63=$C$17,$B91*(AD$60),0)) -> 0 | AE91: =IF(AE$63<=$C$17,($C$34*AE$59*$B91/$C$63)*(IF(COUNTA($D91:AD91)*(12/$C$63)<=$C$9,0,1)),0)+IF(AF$63=$C$17,0,IF(AE$63=$C$17,$B91*(AE$60),0)) -> 0 | AF91: =IF(AF$63<=$C$17,($C$34*AF$59*$B91/$C$63)*(IF(COUNTA($D91:AE91)*(12/$C$63)<=$C$9,0,1)),0)+IF(AG$63=$C$17,0,IF(AF$63=$C$17,$B91*(AF$60),0)) -> 0 | AG91: =IF(AG$63<=$C$17,($C$34*AG$59*$B91/$C$63)*(IF(COUNTA($D91:AF91)*(12/$C$63)<=$C$9,0,1)),0)+IF(AH$63=$C$17,0,IF(AG$63=$C$17,$B91*(AG$60),0)) -> 0 | AH91: =IF(AH$63<=$C$17,($C$34*AH$59*$B91/$C$63)*(IF(COUNTA($D91:AG91)*(12/$C$63)<=$C$9,0,1)),0)+IF(AI$63=$C$17,0,IF(AH$63=$C$17,$B91*(AH$60),0)) -> 1.5890667 | AI91: =IF(AI$63<=$C$17,($C$34*AI$59*$B91/$C$63)*(IF(COUNTA($D91:AH91)*(12/$C$63)<=$C$9,0,1)),0)+IF(AJ$63=$C$17,0,IF(AI$63=$C$17,$B91*(AI$60),0)) -> 1.5890667 | AJ91: =IF(AJ$63<=$C$17,($C$34*AJ$59*$B91/$C$63)*(IF(COUNTA($D91:AI91)*(12/$C$63)<=$C$9,0,1)),0)+IF(AK$63=$C$17,0,IF(AJ$63=$C$17,$B91*(AJ$60),0)) -> 1.5890667 | AK91: =IF(AK$63<=$C$17,($C$34*AK$59*$B91/$C$63)*(IF(COUNTA($D91:AJ91)*(12/$C$63)<=$C$9,0,1)),0)+IF(AL$63=$C$17,0,IF(AK$63=$C$17,$B91*(AK$60),0)) -> 1.5890667 | ... IW91: =IF(IW$63<=$C$17,($C$34*IW$59*$B91/$C$63)*(IF(COUNTA($D91:IV91)*(12/$C$63)<=$C$9,0,1)),0)+IF(IX$63=$C$17,0,IF(IW$63=$C$17,$B91*(IW$60),0)) -> 0
A92: Versement programmé | B92: =+OFFSET($D$52,0,COUNTA($B$66:B91),,) -> 3 | C92: =SUM(D92:XEG92) -> 192.83935 | AD92: =IF(AE$63>$C$17,0,-AD$53*(12/$C$63)) -> -618.1806 | AE92: =IF(AE$63<=$C$17,($C$34*AE$59*$B92/$C$63)*(IF(COUNTA($D92:AD92)*(12/$C$63)<=$C$9,0,1)),0)+IF(AF$63=$C$17,0,IF(AE$63=$C$17,$B92*(AE$60),0)) -> 0 | AF92: =IF(AF$63<=$C$17,($C$34*AF$59*$B92/$C$63)*(IF(COUNTA($D92:AE92)*(12/$C$63)<=$C$9,0,1)),0)+IF(AG$63=$C$17,0,IF(AF$63=$C$17,$B92*(AF$60),0)) -> 0 | AG92: =IF(AG$63<=$C$17,($C$34*AG$59*$B92/$C$63)*(IF(COUNTA($D92:AF92)*(12/$C$63)<=$C$9,0,1)),0)+IF(AH$63=$C$17,0,IF(AG$63=$C$17,$B92*(AG$60),0)) -> 0 | AH92: =IF(AH$63<=$C$17,($C$34*AH$59*$B92/$C$63)*(IF(COUNTA($D92:AG92)*(12/$C$63)<=$C$9,0,1)),0)+IF(AI$63=$C$17,0,IF(AH$63=$C$17,$B92*(AH$60),0)) -> 0 | AI92: =IF(AI$63<=$C$17,($C$34*AI$59*$B92/$C$63)*(IF(COUNTA($D92:AH92)*(12/$C$63)<=$C$9,0,1)),0)+IF(AJ$63=$C$17,0,IF(AI$63=$C$17,$B92*(AI$60),0)) -> 2.3836 | AJ92: =IF(AJ$63<=$C$17,($C$34*AJ$59*$B92/$C$63)*(IF(COUNTA($D92:AI92)*(12/$C$63)<=$C$9,0,1)),0)+IF(AK$63=$C$17,0,IF(AJ$63=$C$17,$B92*(AJ$60),0)) -> 2.3836 | AK92: =IF(AK$63<=$C$17,($C$34*AK$59*$B92/$C$63)*(IF(COUNTA($D92:AJ92)*(12/$C$63)<=$C$9,0,1)),0)+IF(AL$63=$C$17,0,IF(AK$63=$C$17,$B92*(AK$60),0)) -> 2.3836 | AL92: =IF(AL$63<=$C$17,($C$34*AL$59*$B92/$C$63)*(IF(COUNTA($D92:AK92)*(12/$C$63)<=$C$9,0,1)),0)+IF(AM$63=$C$17,0,IF(AL$63=$C$17,$B92*(AL$60),0)) -> 2.3836 | ... IW92: =IF(IW$63<=$C$17,($C$34*IW$59*$B92/$C$63)*(IF(COUNTA($D92:IV92)*(12/$C$63)<=$C$9,0,1)),0)+IF(IX$63=$C$17,0,IF(IW$63=$C$17,$B92*(IW$60),0)) -> 0
A93: Versement programmé | B93: =+OFFSET($D$52,0,COUNTA($B$66:B92),,) -> 2 | C93: =SUM(D93:XEG93) -> 126.9705 | AE93: =IF(AF$63>$C$17,0,-AE$53*(12/$C$63)) -> -412.1204 | AF93: =IF(AF$63<=$C$17,($C$34*AF$59*$B93/$C$63)*(IF(COUNTA($D93:AE93)*(12/$C$63)<=$C$9,0,1)),0)+IF(AG$63=$C$17,0,IF(AF$63=$C$17,$B93*(AF$60),0)) -> 0 | AG93: =IF(AG$63<=$C$17,($C$34*AG$59*$B93/$C$63)*(IF(COUNTA($D93:AF93)*(12/$C$63)<=$C$9,0,1)),0)+IF(AH$63=$C$17,0,IF(AG$63=$C$17,$B93*(AG$60),0)) -> 0 | AH93: =IF(AH$63<=$C$17,($C$34*AH$59*$B93/$C$63)*(IF(COUNTA($D93:AG93)*(12/$C$63)<=$C$9,0,1)),0)+IF(AI$63=$C$17,0,IF(AH$63=$C$17,$B93*(AH$60),0)) -> 0 | AI93: =IF(AI$63<=$C$17,($C$34*AI$59*$B93/$C$63)*(IF(COUNTA($D93:AH93)*(12/$C$63)<=$C$9,0,1)),0)+IF(AJ$63=$C$17,0,IF(AI$63=$C$17,$B93*(AI$60),0)) -> 0 | AJ93: =IF(AJ$63<=$C$17,($C$34*AJ$59*$B93/$C$63)*(IF(COUNTA($D93:AI93)*(12/$C$63)<=$C$9,0,1)),0)+IF(AK$63=$C$17,0,IF(AJ$63=$C$17,$B93*(AJ$60),0)) -> 1.5890667 | AK93: =IF(AK$63<=$C$17,($C$34*AK$59*$B93/$C$63)*(IF(COUNTA($D93:AJ93)*(12/$C$63)<=$C$9,0,1)),0)+IF(AL$63=$C$17,0,IF(AK$63=$C$17,$B93*(AK$60),0)) -> 1.5890667 | AL93: =IF(AL$63<=$C$17,($C$34*AL$59*$B93/$C$63)*(IF(COUNTA($D93:AK93)*(12/$C$63)<=$C$9,0,1)),0)+IF(AM$63=$C$17,0,IF(AL$63=$C$17,$B93*(AL$60),0)) -> 1.5890667 | AM93: =IF(AM$63<=$C$17,($C$34*AM$59*$B93/$C$63)*(IF(COUNTA($D93:AL93)*(12/$C$63)<=$C$9,0,1)),0)+IF(AN$63=$C$17,0,IF(AM$63=$C$17,$B93*(AM$60),0)) -> 1.5890667 | ... IW93: =IF(IW$63<=$C$17,($C$34*IW$59*$B93/$C$63)*(IF(COUNTA($D93:IV93)*(12/$C$63)<=$C$9,0,1)),0)+IF(IX$63=$C$17,0,IF(IW$63=$C$17,$B93*(IW$60),0)) -> 0
A94: Versement programmé | B94: =+OFFSET($D$52,0,COUNTA($B$66:B93),,) -> 2 | C94: =SUM(D94:XEG94) -> 125.38143 | AF94: =IF(AG$63>$C$17,0,-AF$53*(12/$C$63)) -> -412.1204 | AG94: =IF(AG$63<=$C$17,($C$34*AG$59*$B94/$C$63)*(IF(COUNTA($D94:AF94)*(12/$C$63)<=$C$9,0,1)),0)+IF(AH$63=$C$17,0,IF(AG$63=$C$17,$B94*(AG$60),0)) -> 0 | AH94: =IF(AH$63<=$C$17,($C$34*AH$59*$B94/$C$63)*(IF(COUNTA($D94:AG94)*(12/$C$63)<=$C$9,0,1)),0)+IF(AI$63=$C$17,0,IF(AH$63=$C$17,$B94*(AH$60),0)) -> 0 | AI94: =IF(AI$63<=$C$17,($C$34*AI$59*$B94/$C$63)*(IF(COUNTA($D94:AH94)*(12/$C$63)<=$C$9,0,1)),0)+IF(AJ$63=$C$17,0,IF(AI$63=$C$17,$B94*(AI$60),0)) -> 0 | AJ94: =IF(AJ$63<=$C$17,($C$34*AJ$59*$B94/$C$63)*(IF(COUNTA($D94:AI94)*(12/$C$63)<=$C$9,0,1)),0)+IF(AK$63=$C$17,0,IF(AJ$63=$C$17,$B94*(AJ$60),0)) -> 0 | AK94: =IF(AK$63<=$C$17,($C$34*AK$59*$B94/$C$63)*(IF(COUNTA($D94:AJ94)*(12/$C$63)<=$C$9,0,1)),0)+IF(AL$63=$C$17,0,IF(AK$63=$C$17,$B94*(AK$60),0)) -> 1.5890667 | AL94: =IF(AL$63<=$C$17,($C$34*AL$59*$B94/$C$63)*(IF(COUNTA($D94:AK94)*(12/$C$63)<=$C$9,0,1)),0)+IF(AM$63=$C$17,0,IF(AL$63=$C$17,$B94*(AL$60),0)) -> 1.5890667 | AM94: =IF(AM$63<=$C$17,($C$34*AM$59*$B94/$C$63)*(IF(COUNTA($D94:AL94)*(12/$C$63)<=$C$9,0,1)),0)+IF(AN$63=$C$17,0,IF(AM$63=$C$17,$B94*(AM$60),0)) -> 1.5890667 | AN94: =IF(AN$63<=$C$17,($C$34*AN$59*$B94/$C$63)*(IF(COUNTA($D94:AM94)*(12/$C$63)<=$C$9,0,1)),0)+IF(AO$63=$C$17,0,IF(AN$63=$C$17,$B94*(AN$60),0)) -> 1.5890667 | ... IW94: =IF(IW$63<=$C$17,($C$34*IW$59*$B94/$C$63)*(IF(COUNTA($D94:IV94)*(12/$C$63)<=$C$9,0,1)),0)+IF(IX$63=$C$17,0,IF(IW$63=$C$17,$B94*(IW$60),0)) -> 0
A95: Versement programmé | B95: =+OFFSET($D$52,0,COUNTA($B$66:B94),,) -> 3 | C95: =SUM(D95:XEG95) -> 185.68855 | AG95: =IF(AH$63>$C$17,0,-AG$53*(12/$C$63)) -> -618.1806 | AH95: =IF(AH$63<=$C$17,($C$34*AH$59*$B95/$C$63)*(IF(COUNTA($D95:AG95)*(12/$C$63)<=$C$9,0,1)),0)+IF(AI$63=$C$17,0,IF(AH$63=$C$17,$B95*(AH$60),0)) -> 0 | AI95: =IF(AI$63<=$C$17,($C$34*AI$59*$B95/$C$63)*(IF(COUNTA($D95:AH95)*(12/$C$63)<=$C$9,0,1)),0)+IF(AJ$63=$C$17,0,IF(AI$63=$C$17,$B95*(AI$60),0)) -> 0 | AJ95: =IF(AJ$63<=$C$17,($C$34*AJ$59*$B95/$C$63)*(IF(COUNTA($D95:AI95)*(12/$C$63)<=$C$9,0,1)),0)+IF(AK$63=$C$17,0,IF(AJ$63=$C$17,$B95*(AJ$60),0)) -> 0 | AK95: =IF(AK$63<=$C$17,($C$34*AK$59*$B95/$C$63)*(IF(COUNTA($D95:AJ95)*(12/$C$63)<=$C$9,0,1)),0)+IF(AL$63=$C$17,0,IF(AK$63=$C$17,$B95*(AK$60),0)) -> 0 | AL95: =IF(AL$63<=$C$17,($C$34*AL$59*$B95/$C$63)*(IF(COUNTA($D95:AK95)*(12/$C$63)<=$C$9,0,1)),0)+IF(AM$63=$C$17,0,IF(AL$63=$C$17,$B95*(AL$60),0)) -> 2.3836 | AM95: =IF(AM$63<=$C$17,($C$34*AM$59*$B95/$C$63)*(IF(COUNTA($D95:AL95)*(12/$C$63)<=$C$9,0,1)),0)+IF(AN$63=$C$17,0,IF(AM$63=$C$17,$B95*(AM$60),0)) -> 2.3836 | AN95: =IF(AN$63<=$C$17,($C$34*AN$59*$B95/$C$63)*(IF(COUNTA($D95:AM95)*(12/$C$63)<=$C$9,0,1)),0)+IF(AO$63=$C$17,0,IF(AN$63=$C$17,$B95*(AN$60),0)) -> 2.3836 | AO95: =IF(AO$63<=$C$17,($C$34*AO$59*$B95/$C$63)*(IF(COUNTA($D95:AN95)*(12/$C$63)<=$C$9,0,1)),0)+IF(AP$63=$C$17,0,IF(AO$63=$C$17,$B95*(AO$60),0)) -> 2.3836 | ... IW95: =IF(IW$63<=$C$17,($C$34*IW$59*$B95/$C$63)*(IF(COUNTA($D95:IV95)*(12/$C$63)<=$C$9,0,1)),0)+IF(IX$63=$C$17,0,IF(IW$63=$C$17,$B95*(IW$60),0)) -> 0
A96: Versement programmé | B96: =+OFFSET($D$52,0,COUNTA($B$66:B95),,) -> 2 | C96: =SUM(D96:XEG96) -> 122.2033 | AH96: =IF(AI$63>$C$17,0,-AH$53*(12/$C$63)) -> -412.1204 | AI96: =IF(AI$63<=$C$17,($C$34*AI$59*$B96/$C$63)*(IF(COUNTA($D96:AH96)*(12/$C$63)<=$C$9,0,1)),0)+IF(AJ$63=$C$17,0,IF(AI$63=$C$17,$B96*(AI$60),0)) -> 0 | AJ96: =IF(AJ$63<=$C$17,($C$34*AJ$59*$B96/$C$63)*(IF(COUNTA($D96:AI96)*(12/$C$63)<=$C$9,0,1)),0)+IF(AK$63=$C$17,0,IF(AJ$63=$C$17,$B96*(AJ$60),0)) -> 0 | AK96: =IF(AK$63<=$C$17,($C$34*AK$59*$B96/$C$63)*(IF(COUNTA($D96:AJ96)*(12/$C$63)<=$C$9,0,1)),0)+IF(AL$63=$C$17,0,IF(AK$63=$C$17,$B96*(AK$60),0)) -> 0 | AL96: =IF(AL$63<=$C$17,($C$34*AL$59*$B96/$C$63)*(IF(COUNTA($D96:AK96)*(12/$C$63)<=$C$9,0,1)),0)+IF(AM$63=$C$17,0,IF(AL$63=$C$17,$B96*(AL$60),0)) -> 0 | AM96: =IF(AM$63<=$C$17,($C$34*AM$59*$B96/$C$63)*(IF(COUNTA($D96:AL96)*(12/$C$63)<=$C$9,0,1)),0)+IF(AN$63=$C$17,0,IF(AM$63=$C$17,$B96*(AM$60),0)) -> 1.5890667 | AN96: =IF(AN$63<=$C$17,($C$34*AN$59*$B96/$C$63)*(IF(COUNTA($D96:AM96)*(12/$C$63)<=$C$9,0,1)),0)+IF(AO$63=$C$17,0,IF(AN$63=$C$17,$B96*(AN$60),0)) -> 1.5890667 | AO96: =IF(AO$63<=$C$17,($C$34*AO$59*$B96/$C$63)*(IF(COUNTA($D96:AN96)*(12/$C$63)<=$C$9,0,1)),0)+IF(AP$63=$C$17,0,IF(AO$63=$C$17,$B96*(AO$60),0)) -> 1.5890667 | AP96: =IF(AP$63<=$C$17,($C$34*AP$59*$B96/$C$63)*(IF(COUNTA($D96:AO96)*(12/$C$63)<=$C$9,0,1)),0)+IF(AQ$63=$C$17,0,IF(AP$63=$C$17,$B96*(AP$60),0)) -> 1.5890667 | ... IW96: =IF(IW$63<=$C$17,($C$34*IW$59*$B96/$C$63)*(IF(COUNTA($D96:IV96)*(12/$C$63)<=$C$9,0,1)),0)+IF(IX$63=$C$17,0,IF(IW$63=$C$17,$B96*(IW$60),0)) -> 0
A97: Versement programmé | B97: =+OFFSET($D$52,0,COUNTA($B$66:B96),,) -> 3 | C97: =SUM(D97:XEG97) -> 180.92135 | AI97: =IF(AJ$63>$C$17,0,-AI$53*(12/$C$63)) -> -618.1806 | AJ97: =IF(AJ$63<=$C$17,($C$34*AJ$59*$B97/$C$63)*(IF(COUNTA($D97:AI97)*(12/$C$63)<=$C$9,0,1)),0)+IF(AK$63=$C$17,0,IF(AJ$63=$C$17,$B97*(AJ$60),0)) -> 0 | AK97: =IF(AK$63<=$C$17,($C$34*AK$59*$B97/$C$63)*(IF(COUNTA($D97:AJ97)*(12/$C$63)<=$C$9,0,1)),0)+IF(AL$63=$C$17,0,IF(AK$63=$C$17,$B97*(AK$60),0)) -> 0 | AL97: =IF(AL$63<=$C$17,($C$34*AL$59*$B97/$C$63)*(IF(COUNTA($D97:AK97)*(12/$C$63)<=$C$9,0,1)),0)+IF(AM$63=$C$17,0,IF(AL$63=$C$17,$B97*(AL$60),0)) -> 0 | AM97: =IF(AM$63<=$C$17,($C$34*AM$59*$B97/$C$63)*(IF(COUNTA($D97:AL97)*(12/$C$63)<=$C$9,0,1)),0)+IF(AN$63=$C$17,0,IF(AM$63=$C$17,$B97*(AM$60),0)) -> 0 | AN97: =IF(AN$63<=$C$17,($C$34*AN$59*$B97/$C$63)*(IF(COUNTA($D97:AM97)*(12/$C$63)<=$C$9,0,1)),0)+IF(AO$63=$C$17,0,IF(AN$63=$C$17,$B97*(AN$60),0)) -> 2.3836 | AO97: =IF(AO$63<=$C$17,($C$34*AO$59*$B97/$C$63)*(IF(COUNTA($D97:AN97)*(12/$C$63)<=$C$9,0,1)),0)+IF(AP$63=$C$17,0,IF(AO$63=$C$17,$B97*(AO$60),0)) -> 2.3836 | AP97: =IF(AP$63<=$C$17,($C$34*AP$59*$B97/$C$63)*(IF(COUNTA($D97:AO97)*(12/$C$63)<=$C$9,0,1)),0)+IF(AQ$63=$C$17,0,IF(AP$63=$C$17,$B97*(AP$60),0)) -> 2.3836 | AQ97: =IF(AQ$63<=$C$17,($C$34*AQ$59*$B97/$C$63)*(IF(COUNTA($D97:AP97)*(12/$C$63)<=$C$9,0,1)),0)+IF(AR$63=$C$17,0,IF(AQ$63=$C$17,$B97*(AQ$60),0)) -> 2.3836 | ... IW97: =IF(IW$63<=$C$17,($C$34*IW$59*$B97/$C$63)*(IF(COUNTA($D97:IV97)*(12/$C$63)<=$C$9,0,1)),0)+IF(IX$63=$C$17,0,IF(IW$63=$C$17,$B97*(IW$60),0)) -> 0
A98: Versement programmé | B98: =+OFFSET($D$52,0,COUNTA($B$66:B97),,) -> 2 | C98: =SUM(D98:XEG98) -> 119.02517 | AJ98: =IF(AK$63>$C$17,0,-AJ$53*(12/$C$63)) -> -412.1204 | AK98: =IF(AK$63<=$C$17,($C$34*AK$59*$B98/$C$63)*(IF(COUNTA($D98:AJ98)*(12/$C$63)<=$C$9,0,1)),0)+IF(AL$63=$C$17,0,IF(AK$63=$C$17,$B98*(AK$60),0)) -> 0 | AL98: =IF(AL$63<=$C$17,($C$34*AL$59*$B98/$C$63)*(IF(COUNTA($D98:AK98)*(12/$C$63)<=$C$9,0,1)),0)+IF(AM$63=$C$17,0,IF(AL$63=$C$17,$B98*(AL$60),0)) -> 0 | AM98: =IF(AM$63<=$C$17,($C$34*AM$59*$B98/$C$63)*(IF(COUNTA($D98:AL98)*(12/$C$63)<=$C$9,0,1)),0)+IF(AN$63=$C$17,0,IF(AM$63=$C$17,$B98*(AM$60),0)) -> 0 | AN98: =IF(AN$63<=$C$17,($C$34*AN$59*$B98/$C$63)*(IF(COUNTA($D98:AM98)*(12/$C$63)<=$C$9,0,1)),0)+IF(AO$63=$C$17,0,IF(AN$63=$C$17,$B98*(AN$60),0)) -> 0 | AO98: =IF(AO$63<=$C$17,($C$34*AO$59*$B98/$C$63)*(IF(COUNTA($D98:AN98)*(12/$C$63)<=$C$9,0,1)),0)+IF(AP$63=$C$17,0,IF(AO$63=$C$17,$B98*(AO$60),0)) -> 1.5890667 | AP98: =IF(AP$63<=$C$17,($C$34*AP$59*$B98/$C$63)*(IF(COUNTA($D98:AO98)*(12/$C$63)<=$C$9,0,1)),0)+IF(AQ$63=$C$17,0,IF(AP$63=$C$17,$B98*(AP$60),0)) -> 1.5890667 | AQ98: =IF(AQ$63<=$C$17,($C$34*AQ$59*$B98/$C$63)*(IF(COUNTA($D98:AP98)*(12/$C$63)<=$C$9,0,1)),0)+IF(AR$63=$C$17,0,IF(AQ$63=$C$17,$B98*(AQ$60),0)) -> 1.5890667 | AR98: =IF(AR$63<=$C$17,($C$34*AR$59*$B98/$C$63)*(IF(COUNTA($D98:AQ98)*(12/$C$63)<=$C$9,0,1)),0)+IF(AS$63=$C$17,0,IF(AR$63=$C$17,$B98*(AR$60),0)) -> 1.5890667 | ... IW98: =IF(IW$63<=$C$17,($C$34*IW$59*$B98/$C$63)*(IF(COUNTA($D98:IV98)*(12/$C$63)<=$C$9,0,1)),0)+IF(IX$63=$C$17,0,IF(IW$63=$C$17,$B98*(IW$60),0)) -> 0
A99: Versement programmé | B99: =+OFFSET($D$52,0,COUNTA($B$66:B98),,) -> 3 | C99: =SUM(D99:XEG99) -> 176.15415 | AK99: =IF(AL$63>$C$17,0,-AK$53*(12/$C$63)) -> -618.1806 | AL99: =IF(AL$63<=$C$17,($C$34*AL$59*$B99/$C$63)*(IF(COUNTA($D99:AK99)*(12/$C$63)<=$C$9,0,1)),0)+IF(AM$63=$C$17,0,IF(AL$63=$C$17,$B99*(AL$60),0)) -> 0 | AM99: =IF(AM$63<=$C$17,($C$34*AM$59*$B99/$C$63)*(IF(COUNTA($D99:AL99)*(12/$C$63)<=$C$9,0,1)),0)+IF(AN$63=$C$17,0,IF(AM$63=$C$17,$B99*(AM$60),0)) -> 0 | AN99: =IF(AN$63<=$C$17,($C$34*AN$59*$B99/$C$63)*(IF(COUNTA($D99:AM99)*(12/$C$63)<=$C$9,0,1)),0)+IF(AO$63=$C$17,0,IF(AN$63=$C$17,$B99*(AN$60),0)) -> 0 | AO99: =IF(AO$63<=$C$17,($C$34*AO$59*$B99/$C$63)*(IF(COUNTA($D99:AN99)*(12/$C$63)<=$C$9,0,1)),0)+IF(AP$63=$C$17,0,IF(AO$63=$C$17,$B99*(AO$60),0)) -> 0 | AP99: =IF(AP$63<=$C$17,($C$34*AP$59*$B99/$C$63)*(IF(COUNTA($D99:AO99)*(12/$C$63)<=$C$9,0,1)),0)+IF(AQ$63=$C$17,0,IF(AP$63=$C$17,$B99*(AP$60),0)) -> 2.3836 | AQ99: =IF(AQ$63<=$C$17,($C$34*AQ$59*$B99/$C$63)*(IF(COUNTA($D99:AP99)*(12/$C$63)<=$C$9,0,1)),0)+IF(AR$63=$C$17,0,IF(AQ$63=$C$17,$B99*(AQ$60),0)) -> 2.3836 | AR99: =IF(AR$63<=$C$17,($C$34*AR$59*$B99/$C$63)*(IF(COUNTA($D99:AQ99)*(12/$C$63)<=$C$9,0,1)),0)+IF(AS$63=$C$17,0,IF(AR$63=$C$17,$B99*(AR$60),0)) -> 2.3836 | AS99: =IF(AS$63<=$C$17,($C$34*AS$59*$B99/$C$63)*(IF(COUNTA($D99:AR99)*(12/$C$63)<=$C$9,0,1)),0)+IF(AT$63=$C$17,0,IF(AS$63=$C$17,$B99*(AS$60),0)) -> 2.3836 | ... IW99: =IF(IW$63<=$C$17,($C$34*IW$59*$B99/$C$63)*(IF(COUNTA($D99:IV99)*(12/$C$63)<=$C$9,0,1)),0)+IF(IX$63=$C$17,0,IF(IW$63=$C$17,$B99*(IW$60),0)) -> 0
A100: Versement programmé | B100: =+OFFSET($D$52,0,COUNTA($B$66:B99),,) -> 2 | C100: =SUM(D100:XEG100) -> 115.84703 | AL100: =IF(AM$63>$C$17,0,-AL$53*(12/$C$63)) -> -412.1204 | AM100: =IF(AM$63<=$C$17,($C$34*AM$59*$B100/$C$63)*(IF(COUNTA($D100:AL100)*(12/$C$63)<=$C$9,0,1)),0)+IF(AN$63=$C$17,0,IF(AM$63=$C$17,$B100*(AM$60),0)) -> 0 | AN100: =IF(AN$63<=$C$17,($C$34*AN$59*$B100/$C$63)*(IF(COUNTA($D100:AM100)*(12/$C$63)<=$C$9,0,1)),0)+IF(AO$63=$C$17,0,IF(AN$63=$C$17,$B100*(AN$60),0)) -> 0 | AO100: =IF(AO$63<=$C$17,($C$34*AO$59*$B100/$C$63)*(IF(COUNTA($D100:AN100)*(12/$C$63)<=$C$9,0,1)),0)+IF(AP$63=$C$17,0,IF(AO$63=$C$17,$B100*(AO$60),0)) -> 0 | AP100: =IF(AP$63<=$C$17,($C$34*AP$59*$B100/$C$63)*(IF(COUNTA($D100:AO100)*(12/$C$63)<=$C$9,0,1)),0)+IF(AQ$63=$C$17,0,IF(AP$63=$C$17,$B100*(AP$60),0)) -> 0 | AQ100: =IF(AQ$63<=$C$17,($C$34*AQ$59*$B100/$C$63)*(IF(COUNTA($D100:AP100)*(12/$C$63)<=$C$9,0,1)),0)+IF(AR$63=$C$17,0,IF(AQ$63=$C$17,$B100*(AQ$60),0)) -> 1.5890667 | AR100: =IF(AR$63<=$C$17,($C$34*AR$59*$B100/$C$63)*(IF(COUNTA($D100:AQ100)*(12/$C$63)<=$C$9,0,1)),0)+IF(AS$63=$C$17,0,IF(AR$63=$C$17,$B100*(AR$60),0)) -> 1.5890667 | AS100: =IF(AS$63<=$C$17,($C$34*AS$59*$B100/$C$63)*(IF(COUNTA($D100:AR100)*(12/$C$63)<=$C$9,0,1)),0)+IF(AT$63=$C$17,0,IF(AS$63=$C$17,$B100*(AS$60),0)) -> 1.5890667 | AT100: =IF(AT$63<=$C$17,($C$34*AT$59*$B100/$C$63)*(IF(COUNTA($D100:AS100)*(12/$C$63)<=$C$9,0,1)),0)+IF(AU$63=$C$17,0,IF(AT$63=$C$17,$B100*(AT$60),0)) -> 1.5890667 | ... IW100: =IF(IW$63<=$C$17,($C$34*IW$59*$B100/$C$63)*(IF(COUNTA($D100:IV100)*(12/$C$63)<=$C$9,0,1)),0)+IF(IX$63=$C$17,0,IF(IW$63=$C$17,$B100*(IW$60),0)) -> 0
A101: Versement programmé | B101: =+OFFSET($D$52,0,COUNTA($B$66:B100),,) -> 2 | C101: =SUM(D101:XEG101) -> 114.25797 | AM101: =IF(AN$63>$C$17,0,-AM$53*(12/$C$63)) -> -412.1204 | AN101: =IF(AN$63<=$C$17,($C$34*AN$59*$B101/$C$63)*(IF(COUNTA($D101:AM101)*(12/$C$63)<=$C$9,0,1)),0)+IF(AO$63=$C$17,0,IF(AN$63=$C$17,$B101*(AN$60),0)) -> 0 | AO101: =IF(AO$63<=$C$17,($C$34*AO$59*$B101/$C$63)*(IF(COUNTA($D101:AN101)*(12/$C$63)<=$C$9,0,1)),0)+IF(AP$63=$C$17,0,IF(AO$63=$C$17,$B101*(AO$60),0)) -> 0 | AP101: =IF(AP$63<=$C$17,($C$34*AP$59*$B101/$C$63)*(IF(COUNTA($D101:AO101)*(12/$C$63)<=$C$9,0,1)),0)+IF(AQ$63=$C$17,0,IF(AP$63=$C$17,$B101*(AP$60),0)) -> 0 | AQ101: =IF(AQ$63<=$C$17,($C$34*AQ$59*$B101/$C$63)*(IF(COUNTA($D101:AP101)*(12/$C$63)<=$C$9,0,1)),0)+IF(AR$63=$C$17,0,IF(AQ$63=$C$17,$B101*(AQ$60),0)) -> 0 | AR101: =IF(AR$63<=$C$17,($C$34*AR$59*$B101/$C$63)*(IF(COUNTA($D101:AQ101)*(12/$C$63)<=$C$9,0,1)),0)+IF(AS$63=$C$17,0,IF(AR$63=$C$17,$B101*(AR$60),0)) -> 1.5890667 | AS101: =IF(AS$63<=$C$17,($C$34*AS$59*$B101/$C$63)*(IF(COUNTA($D101:AR101)*(12/$C$63)<=$C$9,0,1)),0)+IF(AT$63=$C$17,0,IF(AS$63=$C$17,$B101*(AS$60),0)) -> 1.5890667 | AT101: =IF(AT$63<=$C$17,($C$34*AT$59*$B101/$C$63)*(IF(COUNTA($D101:AS101)*(12/$C$63)<=$C$9,0,1)),0)+IF(AU$63=$C$17,0,IF(AT$63=$C$17,$B101*(AT$60),0)) -> 1.5890667 | AU101: =IF(AU$63<=$C$17,($C$34*AU$59*$B101/$C$63)*(IF(COUNTA($D101:AT101)*(12/$C$63)<=$C$9,0,1)),0)+IF(AV$63=$C$17,0,IF(AU$63=$C$17,$B101*(AU$60),0)) -> 1.5890667 | ... IW101: =IF(IW$63<=$C$17,($C$34*IW$59*$B101/$C$63)*(IF(COUNTA($D101:IV101)*(12/$C$63)<=$C$9,0,1)),0)+IF(IX$63=$C$17,0,IF(IW$63=$C$17,$B101*(IW$60),0)) -> 0
A102: Versement programmé | B102: =+OFFSET($D$52,0,COUNTA($B$66:B101),,) -> 3 | C102: =SUM(D102:XEG102) -> 169.00335 | AN102: =IF(AO$63>$C$17,0,-AN$53*(12/$C$63)) -> -618.1806 | AO102: =IF(AO$63<=$C$17,($C$34*AO$59*$B102/$C$63)*(IF(COUNTA($D102:AN102)*(12/$C$63)<=$C$9,0,1)),0)+IF(AP$63=$C$17,0,IF(AO$63=$C$17,$B102*(AO$60),0)) -> 0 | AP102: =IF(AP$63<=$C$17,($C$34*AP$59*$B102/$C$63)*(IF(COUNTA($D102:AO102)*(12/$C$63)<=$C$9,0,1)),0)+IF(AQ$63=$C$17,0,IF(AP$63=$C$17,$B102*(AP$60),0)) -> 0 | AQ102: =IF(AQ$63<=$C$17,($C$34*AQ$59*$B102/$C$63)*(IF(COUNTA($D102:AP102)*(12/$C$63)<=$C$9,0,1)),0)+IF(AR$63=$C$17,0,IF(AQ$63=$C$17,$B102*(AQ$60),0)) -> 0 | AR102: =IF(AR$63<=$C$17,($C$34*AR$59*$B102/$C$63)*(IF(COUNTA($D102:AQ102)*(12/$C$63)<=$C$9,0,1)),0)+IF(AS$63=$C$17,0,IF(AR$63=$C$17,$B102*(AR$60),0)) -> 0 | AS102: =IF(AS$63<=$C$17,($C$34*AS$59*$B102/$C$63)*(IF(COUNTA($D102:AR102)*(12/$C$63)<=$C$9,0,1)),0)+IF(AT$63=$C$17,0,IF(AS$63=$C$17,$B102*(AS$60),0)) -> 2.3836 | AT102: =IF(AT$63<=$C$17,($C$34*AT$59*$B102/$C$63)*(IF(COUNTA($D102:AS102)*(12/$C$63)<=$C$9,0,1)),0)+IF(AU$63=$C$17,0,IF(AT$63=$C$17,$B102*(AT$60),0)) -> 2.3836 | AU102: =IF(AU$63<=$C$17,($C$34*AU$59*$B102/$C$63)*(IF(COUNTA($D102:AT102)*(12/$C$63)<=$C$9,0,1)),0)+IF(AV$63=$C$17,0,IF(AU$63=$C$17,$B102*(AU$60),0)) -> 2.3836 | AV102: =IF(AV$63<=$C$17,($C$34*AV$59*$B102/$C$63)*(IF(COUNTA($D102:AU102)*(12/$C$63)<=$C$9,0,1)),0)+IF(AW$63=$C$17,0,IF(AV$63=$C$17,$B102*(AV$60),0)) -> 2.3836 | ... IW102: =IF(IW$63<=$C$17,($C$34*IW$59*$B102/$C$63)*(IF(COUNTA($D102:IV102)*(12/$C$63)<=$C$9,0,1)),0)+IF(IX$63=$C$17,0,IF(IW$63=$C$17,$B102*(IW$60),0)) -> 0
A103: Versement programmé | B103: =+OFFSET($D$52,0,COUNTA($B$66:B102),,) -> 2 | C103: =SUM(D103:XEG103) -> 106.95863 | AO103: =IF(AP$63>$C$17,0,-AO$53*(12/$C$63)) -> -416.2416 | AP103: =IF(AP$63<=$C$17,($C$34*AP$59*$B103/$C$63)*(IF(COUNTA($D103:AO103)*(12/$C$63)<=$C$9,0,1)),0)+IF(AQ$63=$C$17,0,IF(AP$63=$C$17,$B103*(AP$60),0)) -> 0 | AQ103: =IF(AQ$63<=$C$17,($C$34*AQ$59*$B103/$C$63)*(IF(COUNTA($D103:AP103)*(12/$C$63)<=$C$9,0,1)),0)+IF(AR$63=$C$17,0,IF(AQ$63=$C$17,$B103*(AQ$60),0)) -> 0 | AR103: =IF(AR$63<=$C$17,($C$34*AR$59*$B103/$C$63)*(IF(COUNTA($D103:AQ103)*(12/$C$63)<=$C$9,0,1)),0)+IF(AS$63=$C$17,0,IF(AR$63=$C$17,$B103*(AR$60),0)) -> 0 | AS103: =IF(AS$63<=$C$17,($C$34*AS$59*$B103/$C$63)*(IF(COUNTA($D103:AR103)*(12/$C$63)<=$C$9,0,1)),0)+IF(AT$63=$C$17,0,IF(AS$63=$C$17,$B103*(AS$60),0)) -> 0 | AT103: =IF(AT$63<=$C$17,($C$34*AT$59*$B103/$C$63)*(IF(COUNTA($D103:AS103)*(12/$C$63)<=$C$9,0,1)),0)+IF(AU$63=$C$17,0,IF(AT$63=$C$17,$B103*(AT$60),0)) -> 1.5890667 | AU103: =IF(AU$63<=$C$17,($C$34*AU$59*$B103/$C$63)*(IF(COUNTA($D103:AT103)*(12/$C$63)<=$C$9,0,1)),0)+IF(AV$63=$C$17,0,IF(AU$63=$C$17,$B103*(AU$60),0)) -> 1.5890667 | AV103: =IF(AV$63<=$C$17,($C$34*AV$59*$B103/$C$63)*(IF(COUNTA($D103:AU103)*(12/$C$63)<=$C$9,0,1)),0)+IF(AW$63=$C$17,0,IF(AV$63=$C$17,$B103*(AV$60),0)) -> 1.5890667 | AW103: =IF(AW$63<=$C$17,($C$34*AW$59*$B103/$C$63)*(IF(COUNTA($D103:AV103)*(12/$C$63)<=$C$9,0,1)),0)+IF(AX$63=$C$17,0,IF(AW$63=$C$17,$B103*(AW$60),0)) -> 1.5890667 | ... IW103: =IF(IW$63<=$C$17,($C$34*IW$59*$B103/$C$63)*(IF(COUNTA($D103:IV103)*(12/$C$63)<=$C$9,0,1)),0)+IF(IX$63=$C$17,0,IF(IW$63=$C$17,$B103*(IW$60),0)) -> 0
A104: Versement programmé | B104: =+OFFSET($D$52,0,COUNTA($B$66:B103),,) -> 3 | C104: =SUM(D104:XEG104) -> 158.05434 | AP104: =IF(AQ$63>$C$17,0,-AP$53*(12/$C$63)) -> -624.36241 | AQ104: =IF(AQ$63<=$C$17,($C$34*AQ$59*$B104/$C$63)*(IF(COUNTA($D104:AP104)*(12/$C$63)<=$C$9,0,1)),0)+IF(AR$63=$C$17,0,IF(AQ$63=$C$17,$B104*(AQ$60),0)) -> 0 | AR104: =IF(AR$63<=$C$17,($C$34*AR$59*$B104/$C$63)*(IF(COUNTA($D104:AQ104)*(12/$C$63)<=$C$9,0,1)),0)+IF(AS$63=$C$17,0,IF(AR$63=$C$17,$B104*(AR$60),0)) -> 0 | AS104: =IF(AS$63<=$C$17,($C$34*AS$59*$B104/$C$63)*(IF(COUNTA($D104:AR104)*(12/$C$63)<=$C$9,0,1)),0)+IF(AT$63=$C$17,0,IF(AS$63=$C$17,$B104*(AS$60),0)) -> 0 | AT104: =IF(AT$63<=$C$17,($C$34*AT$59*$B104/$C$63)*(IF(COUNTA($D104:AS104)*(12/$C$63)<=$C$9,0,1)),0)+IF(AU$63=$C$17,0,IF(AT$63=$C$17,$B104*(AT$60),0)) -> 0 | AU104: =IF(AU$63<=$C$17,($C$34*AU$59*$B104/$C$63)*(IF(COUNTA($D104:AT104)*(12/$C$63)<=$C$9,0,1)),0)+IF(AV$63=$C$17,0,IF(AU$63=$C$17,$B104*(AU$60),0)) -> 2.3836 | AV104: =IF(AV$63<=$C$17,($C$34*AV$59*$B104/$C$63)*(IF(COUNTA($D104:AU104)*(12/$C$63)<=$C$9,0,1)),0)+IF(AW$63=$C$17,0,IF(AV$63=$C$17,$B104*(AV$60),0)) -> 2.3836 | AW104: =IF(AW$63<=$C$17,($C$34*AW$59*$B104/$C$63)*(IF(COUNTA($D104:AV104)*(12/$C$63)<=$C$9,0,1)),0)+IF(AX$63=$C$17,0,IF(AW$63=$C$17,$B104*(AW$60),0)) -> 2.3836 | AX104: =IF(AX$63<=$C$17,($C$34*AX$59*$B104/$C$63)*(IF(COUNTA($D104:AW104)*(12/$C$63)<=$C$9,0,1)),0)+IF(AY$63=$C$17,0,IF(AX$63=$C$17,$B104*(AX$60),0)) -> 2.3836 | ... IW104: =IF(IW$63<=$C$17,($C$34*IW$59*$B104/$C$63)*(IF(COUNTA($D104:IV104)*(12/$C$63)<=$C$9,0,1)),0)+IF(IX$63=$C$17,0,IF(IW$63=$C$17,$B104*(IW$60),0)) -> 0
A105: Versement programmé | B105: =+OFFSET($D$52,0,COUNTA($B$66:B104),,) -> 2 | C105: =SUM(D105:XEG105) -> 103.78049 | AQ105: =IF(AR$63>$C$17,0,-AQ$53*(12/$C$63)) -> -416.2416 | AR105: =IF(AR$63<=$C$17,($C$34*AR$59*$B105/$C$63)*(IF(COUNTA($D105:AQ105)*(12/$C$63)<=$C$9,0,1)),0)+IF(AS$63=$C$17,0,IF(AR$63=$C$17,$B105*(AR$60),0)) -> 0 | AS105: =IF(AS$63<=$C$17,($C$34*AS$59*$B105/$C$63)*(IF(COUNTA($D105:AR105)*(12/$C$63)<=$C$9,0,1)),0)+IF(AT$63=$C$17,0,IF(AS$63=$C$17,$B105*(AS$60),0)) -> 0 | AT105: =IF(AT$63<=$C$17,($C$34*AT$59*$B105/$C$63)*(IF(COUNTA($D105:AS105)*(12/$C$63)<=$C$9,0,1)),0)+IF(AU$63=$C$17,0,IF(AT$63=$C$17,$B105*(AT$60),0)) -> 0 | AU105: =IF(AU$63<=$C$17,($C$34*AU$59*$B105/$C$63)*(IF(COUNTA($D105:AT105)*(12/$C$63)<=$C$9,0,1)),0)+IF(AV$63=$C$17,0,IF(AU$63=$C$17,$B105*(AU$60),0)) -> 0 | AV105: =IF(AV$63<=$C$17,($C$34*AV$59*$B105/$C$63)*(IF(COUNTA($D105:AU105)*(12/$C$63)<=$C$9,0,1)),0)+IF(AW$63=$C$17,0,IF(AV$63=$C$17,$B105*(AV$60),0)) -> 1.5890667 | AW105: =IF(AW$63<=$C$17,($C$34*AW$59*$B105/$C$63)*(IF(COUNTA($D105:AV105)*(12/$C$63)<=$C$9,0,1)),0)+IF(AX$63=$C$17,0,IF(AW$63=$C$17,$B105*(AW$60),0)) -> 1.5890667 | AX105: =IF(AX$63<=$C$17,($C$34*AX$59*$B105/$C$63)*(IF(COUNTA($D105:AW105)*(12/$C$63)<=$C$9,0,1)),0)+IF(AY$63=$C$17,0,IF(AX$63=$C$17,$B105*(AX$60),0)) -> 1.5890667 | AY105: =IF(AY$63<=$C$17,($C$34*AY$59*$B105/$C$63)*(IF(COUNTA($D105:AX105)*(12/$C$63)<=$C$9,0,1)),0)+IF(AZ$63=$C$17,0,IF(AY$63=$C$17,$B105*(AY$60),0)) -> 1.5890667 | ... IW105: =IF(IW$63<=$C$17,($C$34*IW$59*$B105/$C$63)*(IF(COUNTA($D105:IV105)*(12/$C$63)<=$C$9,0,1)),0)+IF(IX$63=$C$17,0,IF(IW$63=$C$17,$B105*(IW$60),0)) -> 0
A106: Versement programmé | B106: =+OFFSET($D$52,0,COUNTA($B$66:B105),,) -> 3 | C106: =SUM(D106:XEG106) -> 153.28714 | AR106: =IF(AS$63>$C$17,0,-AR$53*(12/$C$63)) -> -624.36241 | AS106: =IF(AS$63<=$C$17,($C$34*AS$59*$B106/$C$63)*(IF(COUNTA($D106:AR106)*(12/$C$63)<=$C$9,0,1)),0)+IF(AT$63=$C$17,0,IF(AS$63=$C$17,$B106*(AS$60),0)) -> 0 | AT106: =IF(AT$63<=$C$17,($C$34*AT$59*$B106/$C$63)*(IF(COUNTA($D106:AS106)*(12/$C$63)<=$C$9,0,1)),0)+IF(AU$63=$C$17,0,IF(AT$63=$C$17,$B106*(AT$60),0)) -> 0 | AU106: =IF(AU$63<=$C$17,($C$34*AU$59*$B106/$C$63)*(IF(COUNTA($D106:AT106)*(12/$C$63)<=$C$9,0,1)),0)+IF(AV$63=$C$17,0,IF(AU$63=$C$17,$B106*(AU$60),0)) -> 0 | AV106: =IF(AV$63<=$C$17,($C$34*AV$59*$B106/$C$63)*(IF(COUNTA($D106:AU106)*(12/$C$63)<=$C$9,0,1)),0)+IF(AW$63=$C$17,0,IF(AV$63=$C$17,$B106*(AV$60),0)) -> 0 | AW106: =IF(AW$63<=$C$17,($C$34*AW$59*$B106/$C$63)*(IF(COUNTA($D106:AV106)*(12/$C$63)<=$C$9,0,1)),0)+IF(AX$63=$C$17,0,IF(AW$63=$C$17,$B106*(AW$60),0)) -> 2.3836 | AX106: =IF(AX$63<=$C$17,($C$34*AX$59*$B106/$C$63)*(IF(COUNTA($D106:AW106)*(12/$C$63)<=$C$9,0,1)),0)+IF(AY$63=$C$17,0,IF(AX$63=$C$17,$B106*(AX$60),0)) -> 2.3836 | AY106: =IF(AY$63<=$C$17,($C$34*AY$59*$B106/$C$63)*(IF(COUNTA($D106:AX106)*(12/$C$63)<=$C$9,0,1)),0)+IF(AZ$63=$C$17,0,IF(AY$63=$C$17,$B106*(AY$60),0)) -> 2.3836 | AZ106: =IF(AZ$63<=$C$17,($C$34*AZ$59*$B106/$C$63)*(IF(COUNTA($D106:AY106)*(12/$C$63)<=$C$9,0,1)),0)+IF(BA$63=$C$17,0,IF(AZ$63=$C$17,$B106*(AZ$60),0)) -> 2.3836 | ... IW106: =IF(IW$63<=$C$17,($C$34*IW$59*$B106/$C$63)*(IF(COUNTA($D106:IV106)*(12/$C$63)<=$C$9,0,1)),0)+IF(IX$63=$C$17,0,IF(IW$63=$C$17,$B106*(IW$60),0)) -> 0
A107: Versement programmé | B107: =+OFFSET($D$52,0,COUNTA($B$66:B106),,) -> 2 | C107: =SUM(D107:XEG107) -> 100.60236 | AS107: =IF(AT$63>$C$17,0,-AS$53*(12/$C$63)) -> -416.2416 | AT107: =IF(AT$63<=$C$17,($C$34*AT$59*$B107/$C$63)*(IF(COUNTA($D107:AS107)*(12/$C$63)<=$C$9,0,1)),0)+IF(AU$63=$C$17,0,IF(AT$63=$C$17,$B107*(AT$60),0)) -> 0 | AU107: =IF(AU$63<=$C$17,($C$34*AU$59*$B107/$C$63)*(IF(COUNTA($D107:AT107)*(12/$C$63)<=$C$9,0,1)),0)+IF(AV$63=$C$17,0,IF(AU$63=$C$17,$B107*(AU$60),0)) -> 0 | AV107: =IF(AV$63<=$C$17,($C$34*AV$59*$B107/$C$63)*(IF(COUNTA($D107:AU107)*(12/$C$63)<=$C$9,0,1)),0)+IF(AW$63=$C$17,0,IF(AV$63=$C$17,$B107*(AV$60),0)) -> 0 | AW107: =IF(AW$63<=$C$17,($C$34*AW$59*$B107/$C$63)*(IF(COUNTA($D107:AV107)*(12/$C$63)<=$C$9,0,1)),0)+IF(AX$63=$C$17,0,IF(AW$63=$C$17,$B107*(AW$60),0)) -> 0 | AX107: =IF(AX$63<=$C$17,($C$34*AX$59*$B107/$C$63)*(IF(COUNTA($D107:AW107)*(12/$C$63)<=$C$9,0,1)),0)+IF(AY$63=$C$17,0,IF(AX$63=$C$17,$B107*(AX$60),0)) -> 1.5890667 | AY107: =IF(AY$63<=$C$17,($C$34*AY$59*$B107/$C$63)*(IF(COUNTA($D107:AX107)*(12/$C$63)<=$C$9,0,1)),0)+IF(AZ$63=$C$17,0,IF(AY$63=$C$17,$B107*(AY$60),0)) -> 1.5890667 | AZ107: =IF(AZ$63<=$C$17,($C$34*AZ$59*$B107/$C$63)*(IF(COUNTA($D107:AY107)*(12/$C$63)<=$C$9,0,1)),0)+IF(BA$63=$C$17,0,IF(AZ$63=$C$17,$B107*(AZ$60),0)) -> 1.5890667 | BA107: =IF(BA$63<=$C$17,($C$34*BA$59*$B107/$C$63)*(IF(COUNTA($D107:AZ107)*(12/$C$63)<=$C$9,0,1)),0)+IF(BB$63=$C$17,0,IF(BA$63=$C$17,$B107*(BA$60),0)) -> 1.5890667 | ... IW107: =IF(IW$63<=$C$17,($C$34*IW$59*$B107/$C$63)*(IF(COUNTA($D107:IV107)*(12/$C$63)<=$C$9,0,1)),0)+IF(IX$63=$C$17,0,IF(IW$63=$C$17,$B107*(IW$60),0)) -> 0
A108: Versement programmé | B108: =+OFFSET($D$52,0,COUNTA($B$66:B107),,) -> 3 | C108: =SUM(D108:XEG108) -> 148.51994 | AT108: =IF(AU$63>$C$17,0,-AT$53*(12/$C$63)) -> -624.36241 | AU108: =IF(AU$63<=$C$17,($C$34*AU$59*$B108/$C$63)*(IF(COUNTA($D108:AT108)*(12/$C$63)<=$C$9,0,1)),0)+IF(AV$63=$C$17,0,IF(AU$63=$C$17,$B108*(AU$60),0)) -> 0 | AV108: =IF(AV$63<=$C$17,($C$34*AV$59*$B108/$C$63)*(IF(COUNTA($D108:AU108)*(12/$C$63)<=$C$9,0,1)),0)+IF(AW$63=$C$17,0,IF(AV$63=$C$17,$B108*(AV$60),0)) -> 0 | AW108: =IF(AW$63<=$C$17,($C$34*AW$59*$B108/$C$63)*(IF(COUNTA($D108:AV108)*(12/$C$63)<=$C$9,0,1)),0)+IF(AX$63=$C$17,0,IF(AW$63=$C$17,$B108*(AW$60),0)) -> 0 | AX108: =IF(AX$63<=$C$17,($C$34*AX$59*$B108/$C$63)*(IF(COUNTA($D108:AW108)*(12/$C$63)<=$C$9,0,1)),0)+IF(AY$63=$C$17,0,IF(AX$63=$C$17,$B108*(AX$60),0)) -> 0 | AY108: =IF(AY$63<=$C$17,($C$34*AY$59*$B108/$C$63)*(IF(COUNTA($D108:AX108)*(12/$C$63)<=$C$9,0,1)),0)+IF(AZ$63=$C$17,0,IF(AY$63=$C$17,$B108*(AY$60),0)) -> 2.3836 | AZ108: =IF(AZ$63<=$C$17,($C$34*AZ$59*$B108/$C$63)*(IF(COUNTA($D108:AY108)*(12/$C$63)<=$C$9,0,1)),0)+IF(BA$63=$C$17,0,IF(AZ$63=$C$17,$B108*(AZ$60),0)) -> 2.3836 | BA108: =IF(BA$63<=$C$17,($C$34*BA$59*$B108/$C$63)*(IF(COUNTA($D108:AZ108)*(12/$C$63)<=$C$9,0,1)),0)+IF(BB$63=$C$17,0,IF(BA$63=$C$17,$B108*(BA$60),0)) -> 2.3836 | BB108: =IF(BB$63<=$C$17,($C$34*BB$59*$B108/$C$63)*(IF(COUNTA($D108:BA108)*(12/$C$63)<=$C$9,0,1)),0)+IF(BC$63=$C$17,0,IF(BB$63=$C$17,$B108*(BB$60),0)) -> 2.3836 | ... IW108: =IF(IW$63<=$C$17,($C$34*IW$59*$B108/$C$63)*(IF(COUNTA($D108:IV108)*(12/$C$63)<=$C$9,0,1)),0)+IF(IX$63=$C$17,0,IF(IW$63=$C$17,$B108*(IW$60),0)) -> 0
A109: Versement programmé | B109: =+OFFSET($D$52,0,COUNTA($B$66:B108),,) -> 2 | C109: =SUM(D109:XEG109) -> 97.424228 | AU109: =IF(AV$63>$C$17,0,-AU$53*(12/$C$63)) -> -416.2416 | AV109: =IF(AV$63<=$C$17,($C$34*AV$59*$B109/$C$63)*(IF(COUNTA($D109:AU109)*(12/$C$63)<=$C$9,0,1)),0)+IF(AW$63=$C$17,0,IF(AV$63=$C$17,$B109*(AV$60),0)) -> 0 | AW109: =IF(AW$63<=$C$17,($C$34*AW$59*$B109/$C$63)*(IF(COUNTA($D109:AV109)*(12/$C$63)<=$C$9,0,1)),0)+IF(AX$63=$C$17,0,IF(AW$63=$C$17,$B109*(AW$60),0)) -> 0 | AX109: =IF(AX$63<=$C$17,($C$34*AX$59*$B109/$C$63)*(IF(COUNTA($D109:AW109)*(12/$C$63)<=$C$9,0,1)),0)+IF(AY$63=$C$17,0,IF(AX$63=$C$17,$B109*(AX$60),0)) -> 0 | AY109: =IF(AY$63<=$C$17,($C$34*AY$59*$B109/$C$63)*(IF(COUNTA($D109:AX109)*(12/$C$63)<=$C$9,0,1)),0)+IF(AZ$63=$C$17,0,IF(AY$63=$C$17,$B109*(AY$60),0)) -> 0 | AZ109: =IF(AZ$63<=$C$17,($C$34*AZ$59*$B109/$C$63)*(IF(COUNTA($D109:AY109)*(12/$C$63)<=$C$9,0,1)),0)+IF(BA$63=$C$17,0,IF(AZ$63=$C$17,$B109*(AZ$60),0)) -> 1.5890667 | BA109: =IF(BA$63<=$C$17,($C$34*BA$59*$B109/$C$63)*(IF(COUNTA($D109:AZ109)*(12/$C$63)<=$C$9,0,1)),0)+IF(BB$63=$C$17,0,IF(BA$63=$C$17,$B109*(BA$60),0)) -> 1.5890667 | BB109: =IF(BB$63<=$C$17,($C$34*BB$59*$B109/$C$63)*(IF(COUNTA($D109:BA109)*(12/$C$63)<=$C$9,0,1)),0)+IF(BC$63=$C$17,0,IF(BB$63=$C$17,$B109*(BB$60),0)) -> 1.5890667 | BC109: =IF(BC$63<=$C$17,($C$34*BC$59*$B109/$C$63)*(IF(COUNTA($D109:BB109)*(12/$C$63)<=$C$9,0,1)),0)+IF(BD$63=$C$17,0,IF(BC$63=$C$17,$B109*(BC$60),0)) -> 1.5890667 | ... IW109: =IF(IW$63<=$C$17,($C$34*IW$59*$B109/$C$63)*(IF(COUNTA($D109:IV109)*(12/$C$63)<=$C$9,0,1)),0)+IF(IX$63=$C$17,0,IF(IW$63=$C$17,$B109*(IW$60),0)) -> 0
A110: Versement programmé | B110: =+OFFSET($D$52,0,COUNTA($B$66:B109),,) -> 3 | C110: =SUM(D110:XEG110) -> 143.75274 | AV110: =IF(AW$63>$C$17,0,-AV$53*(12/$C$63)) -> -624.36241 | AW110: =IF(AW$63<=$C$17,($C$34*AW$59*$B110/$C$63)*(IF(COUNTA($D110:AV110)*(12/$C$63)<=$C$9,0,1)),0)+IF(AX$63=$C$17,0,IF(AW$63=$C$17,$B110*(AW$60),0)) -> 0 | AX110: =IF(AX$63<=$C$17,($C$34*AX$59*$B110/$C$63)*(IF(COUNTA($D110:AW110)*(12/$C$63)<=$C$9,0,1)),0)+IF(AY$63=$C$17,0,IF(AX$63=$C$17,$B110*(AX$60),0)) -> 0 | AY110: =IF(AY$63<=$C$17,($C$34*AY$59*$B110/$C$63)*(IF(COUNTA($D110:AX110)*(12/$C$63)<=$C$9,0,1)),0)+IF(AZ$63=$C$17,0,IF(AY$63=$C$17,$B110*(AY$60),0)) -> 0 | AZ110: =IF(AZ$63<=$C$17,($C$34*AZ$59*$B110/$C$63)*(IF(COUNTA($D110:AY110)*(12/$C$63)<=$C$9,0,1)),0)+IF(BA$63=$C$17,0,IF(AZ$63=$C$17,$B110*(AZ$60),0)) -> 0 | BA110: =IF(BA$63<=$C$17,($C$34*BA$59*$B110/$C$63)*(IF(COUNTA($D110:AZ110)*(12/$C$63)<=$C$9,0,1)),0)+IF(BB$63=$C$17,0,IF(BA$63=$C$17,$B110*(BA$60),0)) -> 2.3836 | BB110: =IF(BB$63<=$C$17,($C$34*BB$59*$B110/$C$63)*(IF(COUNTA($D110:BA110)*(12/$C$63)<=$C$9,0,1)),0)+IF(BC$63=$C$17,0,IF(BB$63=$C$17,$B110*(BB$60),0)) -> 2.3836 | BC110: =IF(BC$63<=$C$17,($C$34*BC$59*$B110/$C$63)*(IF(COUNTA($D110:BB110)*(12/$C$63)<=$C$9,0,1)),0)+IF(BD$63=$C$17,0,IF(BC$63=$C$17,$B110*(BC$60),0)) -> 2.3836 | BD110: =IF(BD$63<=$C$17,($C$34*BD$59*$B110/$C$63)*(IF(COUNTA($D110:BC110)*(12/$C$63)<=$C$9,0,1)),0)+IF(BE$63=$C$17,0,IF(BD$63=$C$17,$B110*(BD$60),0)) -> 2.3836 | ... IW110: =IF(IW$63<=$C$17,($C$34*IW$59*$B110/$C$63)*(IF(COUNTA($D110:IV110)*(12/$C$63)<=$C$9,0,1)),0)+IF(IX$63=$C$17,0,IF(IW$63=$C$17,$B110*(IW$60),0)) -> 0
A111: Versement programmé | B111: =+OFFSET($D$52,0,COUNTA($B$66:B110),,) -> 2 | C111: =SUM(D111:XEG111) -> 94.246094 | AW111: =IF(AX$63>$C$17,0,-AW$53*(12/$C$63)) -> -416.2416 | AX111: =IF(AX$63<=$C$17,($C$34*AX$59*$B111/$C$63)*(IF(COUNTA($D111:AW111)*(12/$C$63)<=$C$9,0,1)),0)+IF(AY$63=$C$17,0,IF(AX$63=$C$17,$B111*(AX$60),0)) -> 0 | AY111: =IF(AY$63<=$C$17,($C$34*AY$59*$B111/$C$63)*(IF(COUNTA($D111:AX111)*(12/$C$63)<=$C$9,0,1)),0)+IF(AZ$63=$C$17,0,IF(AY$63=$C$17,$B111*(AY$60),0)) -> 0 | AZ111: =IF(AZ$63<=$C$17,($C$34*AZ$59*$B111/$C$63)*(IF(COUNTA($D111:AY111)*(12/$C$63)<=$C$9,0,1)),0)+IF(BA$63=$C$17,0,IF(AZ$63=$C$17,$B111*(AZ$60),0)) -> 0 | BA111: =IF(BA$63<=$C$17,($C$34*BA$59*$B111/$C$63)*(IF(COUNTA($D111:AZ111)*(12/$C$63)<=$C$9,0,1)),0)+IF(BB$63=$C$17,0,IF(BA$63=$C$17,$B111*(BA$60),0)) -> 0 | BB111: =IF(BB$63<=$C$17,($C$34*BB$59*$B111/$C$63)*(IF(COUNTA($D111:BA111)*(12/$C$63)<=$C$9,0,1)),0)+IF(BC$63=$C$17,0,IF(BB$63=$C$17,$B111*(BB$60),0)) -> 1.5890667 | BC111: =IF(BC$63<=$C$17,($C$34*BC$59*$B111/$C$63)*(IF(COUNTA($D111:BB111)*(12/$C$63)<=$C$9,0,1)),0)+IF(BD$63=$C$17,0,IF(BC$63=$C$17,$B111*(BC$60),0)) -> 1.5890667 | BD111: =IF(BD$63<=$C$17,($C$34*BD$59*$B111/$C$63)*(IF(COUNTA($D111:BC111)*(12/$C$63)<=$C$9,0,1)),0)+IF(BE$63=$C$17,0,IF(BD$63=$C$17,$B111*(BD$60),0)) -> 1.5890667 | BE111: =IF(BE$63<=$C$17,($C$34*BE$59*$B111/$C$63)*(IF(COUNTA($D111:BD111)*(12/$C$63)<=$C$9,0,1)),0)+IF(BF$63=$C$17,0,IF(BE$63=$C$17,$B111*(BE$60),0)) -> 1.5890667 | ... IW111: =IF(IW$63<=$C$17,($C$34*IW$59*$B111/$C$63)*(IF(COUNTA($D111:IV111)*(12/$C$63)<=$C$9,0,1)),0)+IF(IX$63=$C$17,0,IF(IW$63=$C$17,$B111*(IW$60),0)) -> 0
A112: Versement programmé | B112: =+OFFSET($D$52,0,COUNTA($B$66:B111),,) -> 3 | C112: =SUM(D112:XEG112) -> 138.98554 | AX112: =IF(AY$63>$C$17,0,-AX$53*(12/$C$63)) -> -624.36241 | AY112: =IF(AY$63<=$C$17,($C$34*AY$59*$B112/$C$63)*(IF(COUNTA($D112:AX112)*(12/$C$63)<=$C$9,0,1)),0)+IF(AZ$63=$C$17,0,IF(AY$63=$C$17,$B112*(AY$60),0)) -> 0 | AZ112: =IF(AZ$63<=$C$17,($C$34*AZ$59*$B112/$C$63)*(IF(COUNTA($D112:AY112)*(12/$C$63)<=$C$9,0,1)),0)+IF(BA$63=$C$17,0,IF(AZ$63=$C$17,$B112*(AZ$60),0)) -> 0 | BA112: =IF(BA$63<=$C$17,($C$34*BA$59*$B112/$C$63)*(IF(COUNTA($D112:AZ112)*(12/$C$63)<=$C$9,0,1)),0)+IF(BB$63=$C$17,0,IF(BA$63=$C$17,$B112*(BA$60),0)) -> 0 | BB112: =IF(BB$63<=$C$17,($C$34*BB$59*$B112/$C$63)*(IF(COUNTA($D112:BA112)*(12/$C$63)<=$C$9,0,1)),0)+IF(BC$63=$C$17,0,IF(BB$63=$C$17,$B112*(BB$60),0)) -> 0 | BC112: =IF(BC$63<=$C$17,($C$34*BC$59*$B112/$C$63)*(IF(COUNTA($D112:BB112)*(12/$C$63)<=$C$9,0,1)),0)+IF(BD$63=$C$17,0,IF(BC$63=$C$17,$B112*(BC$60),0)) -> 2.3836 | BD112: =IF(BD$63<=$C$17,($C$34*BD$59*$B112/$C$63)*(IF(COUNTA($D112:BC112)*(12/$C$63)<=$C$9,0,1)),0)+IF(BE$63=$C$17,0,IF(BD$63=$C$17,$B112*(BD$60),0)) -> 2.3836 | BE112: =IF(BE$63<=$C$17,($C$34*BE$59*$B112/$C$63)*(IF(COUNTA($D112:BD112)*(12/$C$63)<=$C$9,0,1)),0)+IF(BF$63=$C$17,0,IF(BE$63=$C$17,$B112*(BE$60),0)) -> 2.3836 | BF112: =IF(BF$63<=$C$17,($C$34*BF$59*$B112/$C$63)*(IF(COUNTA($D112:BE112)*(12/$C$63)<=$C$9,0,1)),0)+IF(BG$63=$C$17,0,IF(BF$63=$C$17,$B112*(BF$60),0)) -> 2.3836 | ... IW112: =IF(IW$63<=$C$17,($C$34*IW$59*$B112/$C$63)*(IF(COUNTA($D112:IV112)*(12/$C$63)<=$C$9,0,1)),0)+IF(IX$63=$C$17,0,IF(IW$63=$C$17,$B112*(IW$60),0)) -> 0
A113: Versement programmé | B113: =+OFFSET($D$52,0,COUNTA($B$66:B112),,) -> 3 | C113: =SUM(D113:XEG113) -> 136.60194 | AY113: =IF(AZ$63>$C$17,0,-AY$53*(12/$C$63)) -> -624.36241 | AZ113: =IF(AZ$63<=$C$17,($C$34*AZ$59*$B113/$C$63)*(IF(COUNTA($D113:AY113)*(12/$C$63)<=$C$9,0,1)),0)+IF(BA$63=$C$17,0,IF(AZ$63=$C$17,$B113*(AZ$60),0)) -> 0 | BA113: =IF(BA$63<=$C$17,($C$34*BA$59*$B113/$C$63)*(IF(COUNTA($D113:AZ113)*(12/$C$63)<=$C$9,0,1)),0)+IF(BB$63=$C$17,0,IF(BA$63=$C$17,$B113*(BA$60),0)) -> 0 | BB113: =IF(BB$63<=$C$17,($C$34*BB$59*$B113/$C$63)*(IF(COUNTA($D113:BA113)*(12/$C$63)<=$C$9,0,1)),0)+IF(BC$63=$C$17,0,IF(BB$63=$C$17,$B113*(BB$60),0)) -> 0 | BC113: =IF(BC$63<=$C$17,($C$34*BC$59*$B113/$C$63)*(IF(COUNTA($D113:BB113)*(12/$C$63)<=$C$9,0,1)),0)+IF(BD$63=$C$17,0,IF(BC$63=$C$17,$B113*(BC$60),0)) -> 0 | BD113: =IF(BD$63<=$C$17,($C$34*BD$59*$B113/$C$63)*(IF(COUNTA($D113:BC113)*(12/$C$63)<=$C$9,0,1)),0)+IF(BE$63=$C$17,0,IF(BD$63=$C$17,$B113*(BD$60),0)) -> 2.3836 | BE113: =IF(BE$63<=$C$17,($C$34*BE$59*$B113/$C$63)*(IF(COUNTA($D113:BD113)*(12/$C$63)<=$C$9,0,1)),0)+IF(BF$63=$C$17,0,IF(BE$63=$C$17,$B113*(BE$60),0)) -> 2.3836 | BF113: =IF(BF$63<=$C$17,($C$34*BF$59*$B113/$C$63)*(IF(COUNTA($D113:BE113)*(12/$C$63)<=$C$9,0,1)),0)+IF(BG$63=$C$17,0,IF(BF$63=$C$17,$B113*(BF$60),0)) -> 2.3836 | BG113: =IF(BG$63<=$C$17,($C$34*BG$59*$B113/$C$63)*(IF(COUNTA($D113:BF113)*(12/$C$63)<=$C$9,0,1)),0)+IF(BH$63=$C$17,0,IF(BG$63=$C$17,$B113*(BG$60),0)) -> 2.3836 | ... IW113: =IF(IW$63<=$C$17,($C$34*IW$59*$B113/$C$63)*(IF(COUNTA($D113:IV113)*(12/$C$63)<=$C$9,0,1)),0)+IF(IX$63=$C$17,0,IF(IW$63=$C$17,$B113*(IW$60),0)) -> 0
A114: Versement programmé | B114: =+OFFSET($D$52,0,COUNTA($B$66:B113),,) -> 2 | C114: =SUM(D114:XEG114) -> 89.478894 | AZ114: =IF(BA$63>$C$17,0,-AZ$53*(12/$C$63)) -> -416.2416 | BA114: =IF(BA$63<=$C$17,($C$34*BA$59*$B114/$C$63)*(IF(COUNTA($D114:AZ114)*(12/$C$63)<=$C$9,0,1)),0)+IF(BB$63=$C$17,0,IF(BA$63=$C$17,$B114*(BA$60),0)) -> 0 | BB114: =IF(BB$63<=$C$17,($C$34*BB$59*$B114/$C$63)*(IF(COUNTA($D114:BA114)*(12/$C$63)<=$C$9,0,1)),0)+IF(BC$63=$C$17,0,IF(BB$63=$C$17,$B114*(BB$60),0)) -> 0 | BC114: =IF(BC$63<=$C$17,($C$34*BC$59*$B114/$C$63)*(IF(COUNTA($D114:BB114)*(12/$C$63)<=$C$9,0,1)),0)+IF(BD$63=$C$17,0,IF(BC$63=$C$17,$B114*(BC$60),0)) -> 0 | BD114: =IF(BD$63<=$C$17,($C$34*BD$59*$B114/$C$63)*(IF(COUNTA($D114:BC114)*(12/$C$63)<=$C$9,0,1)),0)+IF(BE$63=$C$17,0,IF(BD$63=$C$17,$B114*(BD$60),0)) -> 0 | BE114: =IF(BE$63<=$C$17,($C$34*BE$59*$B114/$C$63)*(IF(COUNTA($D114:BD114)*(12/$C$63)<=$C$9,0,1)),0)+IF(BF$63=$C$17,0,IF(BE$63=$C$17,$B114*(BE$60),0)) -> 1.5890667 | BF114: =IF(BF$63<=$C$17,($C$34*BF$59*$B114/$C$63)*(IF(COUNTA($D114:BE114)*(12/$C$63)<=$C$9,0,1)),0)+IF(BG$63=$C$17,0,IF(BF$63=$C$17,$B114*(BF$60),0)) -> 1.5890667 | BG114: =IF(BG$63<=$C$17,($C$34*BG$59*$B114/$C$63)*(IF(COUNTA($D114:BF114)*(12/$C$63)<=$C$9,0,1)),0)+IF(BH$63=$C$17,0,IF(BG$63=$C$17,$B114*(BG$60),0)) -> 1.5890667 | BH114: =IF(BH$63<=$C$17,($C$34*BH$59*$B114/$C$63)*(IF(COUNTA($D114:BG114)*(12/$C$63)<=$C$9,0,1)),0)+IF(BI$63=$C$17,0,IF(BH$63=$C$17,$B114*(BH$60),0)) -> 1.5890667 | ... IW114: =IF(IW$63<=$C$17,($C$34*IW$59*$B114/$C$63)*(IF(COUNTA($D114:IV114)*(12/$C$63)<=$C$9,0,1)),0)+IF(IX$63=$C$17,0,IF(IW$63=$C$17,$B114*(IW$60),0)) -> 0
A115: Versement programmé | B115: =+OFFSET($D$52,0,COUNTA($B$66:B114),,) -> 3 | C115: =SUM(D115:XEG115) -> 125.59112 | BA115: =IF(BB$63>$C$17,0,-BA$53*(12/$C$63)) -> -630.60603 | BB115: =IF(BB$63<=$C$17,($C$34*BB$59*$B115/$C$63)*(IF(COUNTA($D115:BA115)*(12/$C$63)<=$C$9,0,1)),0)+IF(BC$63=$C$17,0,IF(BB$63=$C$17,$B115*(BB$60),0)) -> 0 | BC115: =IF(BC$63<=$C$17,($C$34*BC$59*$B115/$C$63)*(IF(COUNTA($D115:BB115)*(12/$C$63)<=$C$9,0,1)),0)+IF(BD$63=$C$17,0,IF(BC$63=$C$17,$B115*(BC$60),0)) -> 0 | BD115: =IF(BD$63<=$C$17,($C$34*BD$59*$B115/$C$63)*(IF(COUNTA($D115:BC115)*(12/$C$63)<=$C$9,0,1)),0)+IF(BE$63=$C$17,0,IF(BD$63=$C$17,$B115*(BD$60),0)) -> 0 | BE115: =IF(BE$63<=$C$17,($C$34*BE$59*$B115/$C$63)*(IF(COUNTA($D115:BD115)*(12/$C$63)<=$C$9,0,1)),0)+IF(BF$63=$C$17,0,IF(BE$63=$C$17,$B115*(BE$60),0)) -> 0 | BF115: =IF(BF$63<=$C$17,($C$34*BF$59*$B115/$C$63)*(IF(COUNTA($D115:BE115)*(12/$C$63)<=$C$9,0,1)),0)+IF(BG$63=$C$17,0,IF(BF$63=$C$17,$B115*(BF$60),0)) -> 2.3836 | BG115: =IF(BG$63<=$C$17,($C$34*BG$59*$B115/$C$63)*(IF(COUNTA($D115:BF115)*(12/$C$63)<=$C$9,0,1)),0)+IF(BH$63=$C$17,0,IF(BG$63=$C$17,$B115*(BG$60),0)) -> 2.3836 | BH115: =IF(BH$63<=$C$17,($C$34*BH$59*$B115/$C$63)*(IF(COUNTA($D115:BG115)*(12/$C$63)<=$C$9,0,1)),0)+IF(BI$63=$C$17,0,IF(BH$63=$C$17,$B115*(BH$60),0)) -> 2.3836 | BI115: =IF(BI$63<=$C$17,($C$34*BI$59*$B115/$C$63)*(IF(COUNTA($D115:BH115)*(12/$C$63)<=$C$9,0,1)),0)+IF(BJ$63=$C$17,0,IF(BI$63=$C$17,$B115*(BI$60),0)) -> 2.3836 | ... IW115: =IF(IW$63<=$C$17,($C$34*IW$59*$B115/$C$63)*(IF(COUNTA($D115:IV115)*(12/$C$63)<=$C$9,0,1)),0)+IF(IX$63=$C$17,0,IF(IW$63=$C$17,$B115*(IW$60),0)) -> 0
A116: Versement programmé | B116: =+OFFSET($D$52,0,COUNTA($B$66:B115),,) -> 2 | C116: =SUM(D116:XEG116) -> 82.138345 | BB116: =IF(BC$63>$C$17,0,-BB$53*(12/$C$63)) -> -420.40402 | BC116: =IF(BC$63<=$C$17,($C$34*BC$59*$B116/$C$63)*(IF(COUNTA($D116:BB116)*(12/$C$63)<=$C$9,0,1)),0)+IF(BD$63=$C$17,0,IF(BC$63=$C$17,$B116*(BC$60),0)) -> 0 | BD116: =IF(BD$63<=$C$17,($C$34*BD$59*$B116/$C$63)*(IF(COUNTA($D116:BC116)*(12/$C$63)<=$C$9,0,1)),0)+IF(BE$63=$C$17,0,IF(BD$63=$C$17,$B116*(BD$60),0)) -> 0 | BE116: =IF(BE$63<=$C$17,($C$34*BE$59*$B116/$C$63)*(IF(COUNTA($D116:BD116)*(12/$C$63)<=$C$9,0,1)),0)+IF(BF$63=$C$17,0,IF(BE$63=$C$17,$B116*(BE$60),0)) -> 0 | BF116: =IF(BF$63<=$C$17,($C$34*BF$59*$B116/$C$63)*(IF(COUNTA($D116:BE116)*(12/$C$63)<=$C$9,0,1)),0)+IF(BG$63=$C$17,0,IF(BF$63=$C$17,$B116*(BF$60),0)) -> 0 | BG116: =IF(BG$63<=$C$17,($C$34*BG$59*$B116/$C$63)*(IF(COUNTA($D116:BF116)*(12/$C$63)<=$C$9,0,1)),0)+IF(BH$63=$C$17,0,IF(BG$63=$C$17,$B116*(BG$60),0)) -> 1.5890667 | BH116: =IF(BH$63<=$C$17,($C$34*BH$59*$B116/$C$63)*(IF(COUNTA($D116:BG116)*(12/$C$63)<=$C$9,0,1)),0)+IF(BI$63=$C$17,0,IF(BH$63=$C$17,$B116*(BH$60),0)) -> 1.5890667 | BI116: =IF(BI$63<=$C$17,($C$34*BI$59*$B116/$C$63)*(IF(COUNTA($D116:BH116)*(12/$C$63)<=$C$9,0,1)),0)+IF(BJ$63=$C$17,0,IF(BI$63=$C$17,$B116*(BI$60),0)) -> 1.5890667 | BJ116: =IF(BJ$63<=$C$17,($C$34*BJ$59*$B116/$C$63)*(IF(COUNTA($D116:BI116)*(12/$C$63)<=$C$9,0,1)),0)+IF(BK$63=$C$17,0,IF(BJ$63=$C$17,$B116*(BJ$60),0)) -> 1.5890667 | ... IW116: =IF(IW$63<=$C$17,($C$34*IW$59*$B116/$C$63)*(IF(COUNTA($D116:IV116)*(12/$C$63)<=$C$9,0,1)),0)+IF(IX$63=$C$17,0,IF(IW$63=$C$17,$B116*(IW$60),0)) -> 0
A117: Versement programmé | B117: =+OFFSET($D$52,0,COUNTA($B$66:B116),,) -> 3 | C117: =SUM(D117:XEG117) -> 120.82392 | BC117: =IF(BD$63>$C$17,0,-BC$53*(12/$C$63)) -> -630.60603 | BD117: =IF(BD$63<=$C$17,($C$34*BD$59*$B117/$C$63)*(IF(COUNTA($D117:BC117)*(12/$C$63)<=$C$9,0,1)),0)+IF(BE$63=$C$17,0,IF(BD$63=$C$17,$B117*(BD$60),0)) -> 0 | BE117: =IF(BE$63<=$C$17,($C$34*BE$59*$B117/$C$63)*(IF(COUNTA($D117:BD117)*(12/$C$63)<=$C$9,0,1)),0)+IF(BF$63=$C$17,0,IF(BE$63=$C$17,$B117*(BE$60),0)) -> 0 | BF117: =IF(BF$63<=$C$17,($C$34*BF$59*$B117/$C$63)*(IF(COUNTA($D117:BE117)*(12/$C$63)<=$C$9,0,1)),0)+IF(BG$63=$C$17,0,IF(BF$63=$C$17,$B117*(BF$60),0)) -> 0 | BG117: =IF(BG$63<=$C$17,($C$34*BG$59*$B117/$C$63)*(IF(COUNTA($D117:BF117)*(12/$C$63)<=$C$9,0,1)),0)+IF(BH$63=$C$17,0,IF(BG$63=$C$17,$B117*(BG$60),0)) -> 0 | BH117: =IF(BH$63<=$C$17,($C$34*BH$59*$B117/$C$63)*(IF(COUNTA($D117:BG117)*(12/$C$63)<=$C$9,0,1)),0)+IF(BI$63=$C$17,0,IF(BH$63=$C$17,$B117*(BH$60),0)) -> 2.3836 | BI117: =IF(BI$63<=$C$17,($C$34*BI$59*$B117/$C$63)*(IF(COUNTA($D117:BH117)*(12/$C$63)<=$C$9,0,1)),0)+IF(BJ$63=$C$17,0,IF(BI$63=$C$17,$B117*(BI$60),0)) -> 2.3836 | BJ117: =IF(BJ$63<=$C$17,($C$34*BJ$59*$B117/$C$63)*(IF(COUNTA($D117:BI117)*(12/$C$63)<=$C$9,0,1)),0)+IF(BK$63=$C$17,0,IF(BJ$63=$C$17,$B117*(BJ$60),0)) -> 2.3836 | BK117: =IF(BK$63<=$C$17,($C$34*BK$59*$B117/$C$63)*(IF(COUNTA($D117:BJ117)*(12/$C$63)<=$C$9,0,1)),0)+IF(BL$63=$C$17,0,IF(BK$63=$C$17,$B117*(BK$60),0)) -> 2.3836 | ... IW117: =IF(IW$63<=$C$17,($C$34*IW$59*$B117/$C$63)*(IF(COUNTA($D117:IV117)*(12/$C$63)<=$C$9,0,1)),0)+IF(IX$63=$C$17,0,IF(IW$63=$C$17,$B117*(IW$60),0)) -> 0
A118: Versement programmé | B118: =+OFFSET($D$52,0,COUNTA($B$66:B117),,) -> 2 | C118: =SUM(D118:XEG118) -> 78.960212 | BD118: =IF(BE$63>$C$17,0,-BD$53*(12/$C$63)) -> -420.40402 | BE118: =IF(BE$63<=$C$17,($C$34*BE$59*$B118/$C$63)*(IF(COUNTA($D118:BD118)*(12/$C$63)<=$C$9,0,1)),0)+IF(BF$63=$C$17,0,IF(BE$63=$C$17,$B118*(BE$60),0)) -> 0 | BF118: =IF(BF$63<=$C$17,($C$34*BF$59*$B118/$C$63)*(IF(COUNTA($D118:BE118)*(12/$C$63)<=$C$9,0,1)),0)+IF(BG$63=$C$17,0,IF(BF$63=$C$17,$B118*(BF$60),0)) -> 0 | BG118: =IF(BG$63<=$C$17,($C$34*BG$59*$B118/$C$63)*(IF(COUNTA($D118:BF118)*(12/$C$63)<=$C$9,0,1)),0)+IF(BH$63=$C$17,0,IF(BG$63=$C$17,$B118*(BG$60),0)) -> 0 | BH118: =IF(BH$63<=$C$17,($C$34*BH$59*$B118/$C$63)*(IF(COUNTA($D118:BG118)*(12/$C$63)<=$C$9,0,1)),0)+IF(BI$63=$C$17,0,IF(BH$63=$C$17,$B118*(BH$60),0)) -> 0 | BI118: =IF(BI$63<=$C$17,($C$34*BI$59*$B118/$C$63)*(IF(COUNTA($D118:BH118)*(12/$C$63)<=$C$9,0,1)),0)+IF(BJ$63=$C$17,0,IF(BI$63=$C$17,$B118*(BI$60),0)) -> 1.5890667 | BJ118: =IF(BJ$63<=$C$17,($C$34*BJ$59*$B118/$C$63)*(IF(COUNTA($D118:BI118)*(12/$C$63)<=$C$9,0,1)),0)+IF(BK$63=$C$17,0,IF(BJ$63=$C$17,$B118*(BJ$60),0)) -> 1.5890667 | BK118: =IF(BK$63<=$C$17,($C$34*BK$59*$B118/$C$63)*(IF(COUNTA($D118:BJ118)*(12/$C$63)<=$C$9,0,1)),0)+IF(BL$63=$C$17,0,IF(BK$63=$C$17,$B118*(BK$60),0)) -> 1.5890667 | BL118: =IF(BL$63<=$C$17,($C$34*BL$59*$B118/$C$63)*(IF(COUNTA($D118:BK118)*(12/$C$63)<=$C$9,0,1)),0)+IF(BM$63=$C$17,0,IF(BL$63=$C$17,$B118*(BL$60),0)) -> 1.5890667 | ... IW118: =IF(IW$63<=$C$17,($C$34*IW$59*$B118/$C$63)*(IF(COUNTA($D118:IV118)*(12/$C$63)<=$C$9,0,1)),0)+IF(IX$63=$C$17,0,IF(IW$63=$C$17,$B118*(IW$60),0)) -> 0
...

Sheet Détails (2)
A1: SCPI Fair Invest
A3: Données d'une part
A5: Prix part | C5: 181.5 | D5: 200
A6: dont droits et frais | C6: 14 | D6: 14
A7: dont frais collecte | C7: 5.5 | D7: 24
A9: Délai de jouissance | C9: 4 | D9: mois
C10: 6 | D10: mois
A13: Données souscription
A15: Profil | C15: =+Résumé!F2 -> Non Fondateur
A16: Catégorie | C16: Pleine Propriété
A17: Durée de souscription | C17: =+Résumé!F3 -> 10
A18: Montant de souscription | C18: =+C26*Résumé!F4 -> 10000
A19: Recurring | C19: =C26*Résumé!F5 -> 400
A23: Résumé de souscription
A25: Montant de souscription | C25: =C18 -> 10000 | I25: Investissement | J25: Gains | K25: TRI
A26: Prix d'une part | C26: =+IF($C$15="fondateur",C5,D5) -> 200
A27: dont droits et frais | C27: =+IF($C$15="fondateur",C6,D6) -> 14 | H27: =+C16 -> Pleine Propriété | I27: =+C49 -> 59781.146 | J27: =+C65 -> 11606.533 | K27: =+XIRR(D65:IW65,D64:IW64) -> 0.030468085
A28: dont frais collecte | C28: =+IF($C$15="fondateur",C7,D7) -> 24
A29: Nombre de parts | C29: =+C18/C26 -> 50
A31: Profil | C31: =+C15 -> Non Fondateur
A32: Durée de souscription | C32: =+C17 -> 10
A33: Catégorie | C33: =+C16 -> Pleine Propriété
A34: DVM | C34: =+Résumé!F7 -> 0.0472
A35: Valeur de la part pour calcul du rendement | C35: =+D5 -> 200
A36: Valeur de la part pour calcul de sortie | C36: =+C26-C28 -> 176
A37: Revalorisation d'une part | C37: =+Résumé!F8 -> 0.01 | CV37: =200*(1+1%)^(8-1) -> 214.42707
A39: CF
A41: Disponible dans le wallet client début du mois | C41: =SUM(D41:XEG41) -> 12347.399 | E41: =+IF(E$63>$C$17,0,D46) -> 0 | F41: =+IF(F$63>$C$17,0,E46) -> 0 | G41: =+IF(G$63>$C$17,0,F46) -> 0 | H41: =+IF(H$63>$C$17,0,G46) -> 0 | I41: =+IF(I$63>$C$17,0,H46) -> 0 | J41: =+IF(J$63>$C$17,0,I46) -> 39.333333 | K41: =+IF(K$63>$C$17,0,J46) -> 80.24 | L41: =+IF(L$63>$C$17,0,K46) -> 122.72 | ... IV41: =+IF(IV$63>$C$17,0,IU46) -> 0
A42: Profit périodique | C42: =SUM(D42:XEG42) -> 88566.243 | E42: =+SUM(OFFSET(E66,0,0,COUNTA($D$42:D42)+1)) -> 0 | F42: =+SUM(OFFSET(F66,0,0,COUNTA($D$42:E42)+1)) -> 0 | G42: =+SUM(OFFSET(G66,0,0,COUNTA($D$42:F42)+1)) -> 0 | H42: =+SUM(OFFSET(H66,0,0,COUNTA($D$42:G42)+1)) -> 0 | I42: =+SUM(OFFSET(I66,0,0,COUNTA($D$42:H42)+1)) -> 39.333333 | J42: =+SUM(OFFSET(J66,0,0,COUNTA($D$42:I42)+1)) -> 40.906667 | K42: =+SUM(OFFSET(K66,0,0,COUNTA($D$42:J42)+1)) -> 42.48 | L42: =+SUM(OFFSET(L66,0,0,COUNTA($D$42:K42)+1)) -> 44.053333 | ... IV42: =+SUM(OFFSET(IV66,0,0,COUNTA($D$42:IU42)+1)) -> 0
A43: Disponible dans le wallet client fin du mois (avant souscription du mois) | C43: =+MAX(E43:IV43) -> 71387.679 | E43: =+IF(E$63>$C$17,0,E42+D43-D44) -> 0 | F43: =+IF(F$63>$C$17,0,F42+E43-E44) -> 0 | G43: =+IF(G$63>$C$17,0,G42+F43-F44) -> 0 | H43: =+IF(H$63>$C$17,0,H42+G43-G44) -> 0 | I43: =+IF(I$63>$C$17,0,I42+H43-H44) -> 39.333333 | J43: =+IF(J$63>$C$17,0,J42+I43-I44) -> 80.24 | K43: =+IF(K$63>$C$17,0,K42+J43-J44) -> 122.72 | L43: =+IF(L$63>$C$17,0,L42+K43-K44) -> 166.77333 | ... IV43: =+IF(IV$63>$C$17,0,IV42+IU43-IU44) -> 0
A44: Nouvelles souscriptions (montant payé) | C44: =SUM(D44:XEG44) -> 17178.564 | E44: =+E45*E58 -> 0 | F44: =+F45*F58 -> 0 | G44: =+G45*G58 -> 0 | H44: =+H45*H58 -> 0 | I44: =+I45*I58 -> 0 | J44: =+J45*J58 -> 0 | K44: =+K45*K58 -> 0 | L44: =+L45*L58 -> 0 | ... IV44: =+IV45*IV58 -> 0
A45: Nouvelles souscriptions (nb de parts) | C45: =SUM(D45:XEG45) -> 81 | E45: =+IF(Résumé!$F$6="oui",IF(OFFSET(F$63,,$A$63)>$C$17,0,IF(F$63>$C$17,0,ROUNDDOWN(E43/E58,0))),0) -> 0 | F45: =+IF(Résumé!$F$6="oui",IF(OFFSET(G$63,,$A$63)>$C$17,0,IF(G$63>$C$17,0,ROUNDDOWN(F43/F58,0))),0) -> 0 | G45: =+IF(Résumé!$F$6="oui",IF(OFFSET(H$63,,$A$63)>$C$17,0,IF(H$63>$C$17,0,ROUNDDOWN(G43/G58,0))),0) -> 0 | H45: =+IF(Résumé!$F$6="oui",IF(OFFSET(I$63,,$A$63)>$C$17,0,IF(I$63>$C$17,0,ROUNDDOWN(H43/H58,0))),0) -> 0 | I45: =+IF(Résumé!$F$6="oui",IF(OFFSET(J$63,,$A$63)>$C$17,0,IF(J$63>$C$17,0,ROUNDDOWN(I43/I58,0))),0) -> 0 | J45: =+IF(Résumé!$F$6="oui",IF(OFFSET(K$63,,$A$63)>$C$17,0,IF(K$63>$C$17,0,ROUNDDOWN(J43/J58,0))),0) -> 0 | K45: =+IF(Résumé!$F$6="oui",IF(OFFSET(L$63,,$A$63)>$C$17,0,IF(L$63>$C$17,0,ROUNDDOWN(K43/K58,0))),0) -> 0 | L45: =+IF(Résumé!$F$6="oui",IF(OFFSET(M$63,,$A$63)>$C$17,0,IF(M$63>$C$17,0,ROUNDDOWN(L43/L58,0))),0) -> 0 | ... IV45: =+IF(Résumé!$F$6="oui",IF(OFFSET(IW$63,,$A$63)>$C$17,0,IF(IW$63>$C$17,0,ROUNDDOWN(IV43/IV58,0))),0) -> 0
A46: Disponible dans le wallet client fin du mois (après souscription du mois) | C46: =+IV46 -> 0 | E46: =+E43-E44 -> 0 | F46: =+F43-F44 -> 0 | G46: =+G43-G44 -> 0 | H46: =+H43-H44 -> 0 | I46: =+I43-I44 -> 39.333333 | J46: =+J43-J44 -> 80.24 | K46: =+K43-K44 -> 122.72 | L46: =+L43-L44 -> 166.77333 | ... IV46: =+IV43-IV44 -> 0
A47: Check | C47: {=+E47:IV47=TRUE} -> TRUE | E47: =+AND(ROUND(E41+E42-E44,2)=ROUND(E46,2),ROUND(E41+E42,2)=ROUND(E43,2)) -> TRUE | F47: =+AND(ROUND(F41+F42-F44,2)=ROUND(F46,2),ROUND(F41+F42,2)=ROUND(F43,2)) -> TRUE | G47: =+AND(ROUND(G41+G42-G44,2)=ROUND(G46,2),ROUND(G41+G42,2)=ROUND(G43,2)) -> TRUE | H47: =+AND(ROUND(H41+H42-H44,2)=ROUND(H46,2),ROUND(H41+H42,2)=ROUND(H43,2)) -> TRUE | I47: =+AND(ROUND(I41+I42-I44,2)=ROUND(I46,2),ROUND(I41+I42,2)=ROUND(I43,2)) -> TRUE | J47: =+AND(ROUND(J41+J42-J44,2)=ROUND(J46,2),ROUND(J41+J42,2)=ROUND(J43,2)) -> TRUE | K47: =+AND(ROUND(K41+K42-K44,2)=ROUND(K46,2),ROUND(K41+K42,2)=ROUND(K43,2)) -> TRUE | L47: =+AND(ROUND(L41+L42-L44,2)=ROUND(L46,2),ROUND(L41+L42,2)=ROUND(L43,2)) -> TRUE | ... IV47: =+AND(ROUND(IV41+IV42-IV44,2)=ROUND(IV46,2),ROUND(IV41+IV42,2)=ROUND(IV43,2)) -> TRUE
A49: Souscription Initiale + récurrente (montant payé) | C49: =SUM(D49:XEG49) -> 59781.146 | D49: =+D50*'Détails (2)'!$D$58 -> 10000 | E49: =IF(F$63>$C$17,0,E50*E$58) -> 400 | F49: =IF(G$63>$C$17,0,F50*F$58) -> 400 | G49: =IF(H$63>$C$17,0,G50*G$58) -> 400 | H49: =IF(I$63>$C$17,0,H50*H$58) -> 400 | I49: =IF(J$63>$C$17,0,I50*I$58) -> 400 | J49: =IF(K$63>$C$17,0,J50*J$58) -> 400 | K49: =IF(L$63>$C$17,0,K50*K$58) -> 400 | L49: =IF(M$63>$C$17,0,L50*L$58) -> 400 | ... IV49: =IF(IW$63>$C$17,0,IV50*IV$58) -> 0
A50: Souscription Initiale + récurrente (nb de parts) | C50: =SUM(D50:XEG50) -> 288 | D50: =+Résumé!$F$4 -> 50 | E50: =IF(OR(OFFSET(F$63,,$A$63)>$C$17,F$63>$C$17),0,Résumé!$F$5) -> 2 | F50: =IF(OR(OFFSET(G$63,,$A$63)>$C$17,G$63>$C$17),0,Résumé!$F$5) -> 2 | G50: =IF(OR(OFFSET(H$63,,$A$63)>$C$17,H$63>$C$17),0,Résumé!$F$5) -> 2 | H50: =IF(OR(OFFSET(I$63,,$A$63)>$C$17,I$63>$C$17),0,Résumé!$F$5) -> 2 | I50: =IF(OR(OFFSET(J$63,,$A$63)>$C$17,J$63>$C$17),0,Résumé!$F$5) -> 2 | J50: =IF(OR(OFFSET(K$63,,$A$63)>$C$17,K$63>$C$17),0,Résumé!$F$5) -> 2 | K50: =IF(OR(OFFSET(L$63,,$A$63)>$C$17,L$63>$C$17),0,Résumé!$F$5) -> 2 | L50: =IF(OR(OFFSET(M$63,,$A$63)>$C$17,M$63>$C$17),0,Résumé!$F$5) -> 2 | ... IV50: =IF(OR(OFFSET(IW$63,,$A$63)>$C$17,IW$63>$C$17),0,Résumé!$F$5) -> 0
A52: Souscription totale (nb de parts) | C52: =SUM(D52:XEG52) -> 369 | D52: =+D50+D45 -> 50 | E52: =+E50+E45 -> 2 | F52: =+F50+F45 -> 2 | G52: =+G50+G45 -> 2 | H52: =+H50+H45 -> 2 | I52: =+I50+I45 -> 2 | J52: =+J50+J45 -> 2 | K52: =+K50+K45 -> 2 | ... IV52: =+IV50+IV45 -> 0
A53: Souscription totale (montant payé) | C53: =SUM(D53:XEG53) -> 76959.71 | D53: =+D49+D44 -> 10000 | E53: =+E49+E44 -> 400 | F53: =+F49+F44 -> 400 | G53: =+G49+G44 -> 400 | H53: =+H49+H44 -> 400 | I53: =+I49+I44 -> 400 | J53: =+J49+J44 -> 400 | K53: =+K49+K44 -> 400 | ... IV53: =+IV49+IV44 -> 0
A55: zakat | B55: 0.02579 | C55: =SUM(D55:XEG55) -> 8794.1815 | P55: =IF((OFFSET(Q$63,,$A$63)-1)>$C$17,0,$B$55*P56) -> 381.692 | AB55: =IF((OFFSET(AC$63,,$A$63)-1)>$C$17,0,$B$55*AB56) -> 496.87808 | AN55: =IF((OFFSET(AO$63,,$A$63)-1)>$C$17,0,$B$55*AN56) -> 610.34382 | AZ55: =IF((OFFSET(BA$63,,$A$63)-1)>$C$17,0,$B$55*AZ56) -> 722.14607 | BL55: =IF((OFFSET(BM$63,,$A$63)-1)>$C$17,0,$B$55*BL56) -> 832.34038 | BX55: =IF((OFFSET(BY$63,,$A$63)-1)>$C$17,0,$B$55*BX56) -> 940.98095 | CJ55: =IF((OFFSET(CK$63,,$A$63)-1)>$C$17,0,$B$55*CJ56) -> 1048.1208 | CV55: =IF((OFFSET(CW$63,,$A$63)-1)>$C$17,0,$B$55*CV56) -> 1153.8115 | DH55: =IF((OFFSET(DI$63,,$A$63)-1)>$C$17,0,$B$55*DH56) -> 1258.1037 | DT55: =IF((OFFSET(DU$63,,$A$63)-1)>$C$17,0,$B$55*DT56) -> 1349.7642 | EF55: =IF((OFFSET(EG$63,,$A$63)-1)>$C$17,0,$B$55*EF56) -> 0 | ER55: =IF((OFFSET(ES$63,,$A$63)-1)>$C$17,0,$B$55*ER56) -> 0 | FD55: =IF((OFFSET(FE$63,,$A$63)-1)>$C$17,0,$B$55*FD56) -> 0 | FP55: =IF((OFFSET(FQ$63,,$A$63)-1)>$C$17,0,$B$55*FP56) -> 0 | GB55: =IF((OFFSET(GC$63,,$A$63)-1)>$C$17,0,$B$55*GB56) -> 0 | GN55: =IF((OFFSET(GO$63,,$A$63)-1)>$C$17,0,$B$55*GN56) -> 0 | GZ55: =IF((OFFSET(HA$63,,$A$63)-1)>$C$17,0,$B$55*GZ56) -> 0 | HL55: =IF((OFFSET(HM$63,,$A$63)-1)>$C$17,0,$B$55*HL56) -> 0 | HX55: =IF((OFFSET(HY$63,,$A$63)-1)>$C$17,0,$B$55*HX56) -> 0 | IJ55: =IF((OFFSET(IK$63,,$A$63)-1)>$C$17,0,$B$55*IJ56) -> 0 | IV55: =IF((OFFSET(IW$63,,$A$63)-1)>$C$17,0,$B$55*IV56) -> 0
D56: =+D49 -> 10000 | E56: =+E49+D56 -> 10400 | F56: =+F49+E56 -> 10800 | G56: =+G49+F56 -> 11200 | H56: =+H49+G56 -> 11600 | I56: =+I49+H56 -> 12000 | J56: =+J49+I56 -> 12400 | K56: =+K49+J56 -> 12800 | L56: =+L49+K56 -> 13200 | ... P56: =+P49+O56 -> 14800 | Q56: =+Q49+P56-P55 -> 14822.308 | R56: =+R49+Q56-Q55 -> 15226.308 | S56: =+S49+R56-R55 -> 15630.308 | T56: =+T49+S56-S55 -> 16034.308 | U56: =+U49+T56-T55 -> 16438.308 | V56: =+V49+U56-U55 -> 16842.308 | W56: =+W49+V56-V55 -> 17246.308 | X56: =+X49+W56-W55 -> 17650.308 | ... IV56: =+IV49+IU56-IU55 -> 50986.965
A58: Prix d'une part | D58: =+$C$26 -> 200 | E58: =+D58 -> 200 | F58: =+IF(F63=E63,E58,E58*(1+$C$37)) -> 200 | G58: =+IF(G63=F63,F58,F58*(1+$C$37)) -> 200 | H58: =+IF(H63=G63,G58,G58*(1+$C$37)) -> 200 | I58: =+IF(I63=H63,H58,H58*(1+$C$37)) -> 200 | J58: =+IF(J63=I63,I58,I58*(1+$C$37)) -> 200 | K58: =+IF(K63=J63,J58,J58*(1+$C$37)) -> 200 | L58: =+IF(L63=K63,K58,K58*(1+$C$37)) -> 200 | M58: =+IF(M63=L63,L58,L58*(1+$C$37)) -> 200 | ... IV58: =+IF(IV63=IU63,IU58,IU58*(1+$C$37)) -> 244.03801
A59: Valeur de la part pour calcul du rendement | D59: =+$C$35 -> 200 | E59: =+$C$35 -> 200 | F59: =+$C$35 -> 200 | G59: =+$C$35 -> 200 | H59: =+$C$35 -> 200 | I59: =+$C$35 -> 200 | J59: =+$C$35 -> 200 | K59: =+$C$35 -> 200 | ... IV59: =+$C$35 -> 200
A60: Valeur de la part pour calcul de sortie | D60: =+$C$36 -> 176 | E60: =+E58*(1-IF($C$15="fondateur",3.0303%,12%)) -> 176 | F60: =+F58*(1-IF($C$15="fondateur",3.0303%,12%)) -> 176 | G60: =+G58*(1-IF($C$15="fondateur",3.0303%,12%)) -> 176 | H60: =+H58*(1-IF($C$15="fondateur",3.0303%,12%)) -> 176 | I60: =+I58*(1-IF($C$15="fondateur",3.0303%,12%)) -> 176 | J60: =+J58*(1-IF($C$15="fondateur",3.0303%,12%)) -> 176 | K60: =+K58*(1-IF($C$15="fondateur",3.0303%,12%)) -> 176 | L60: =+L58*(1-IF($C$15="fondateur",3.0303%,12%)) -> 176 | ... IV60: =+IV58*(1-IF($C$15="fondateur",3.0303%,12%)) -> 214.75345
A62: =COUNTIF(E62:LV62,">0") -> 88 | E62: =+OFFSET($C$66,COUNTA($E$64:E64),0,,) -> 165.91055 | F62: =+OFFSET($C$66,COUNTA($E$64:F64),0,,) -> 164.33722 | G62: =+OFFSET($C$66,COUNTA($E$64:G64),0,,) -> 162.76388 | H62: =+OFFSET($C$66,COUNTA($E$64:H64),0,,) -> 161.19055 | I62: =+OFFSET($C$66,COUNTA($E$64:I64),0,,) -> 159.61722 | J62: =+OFFSET($C$66,COUNTA($E$64:J64),0,,) -> 158.04388 | K62: =+OFFSET($C$66,COUNTA($E$64:K64),0,,) -> 156.47055 | L62: =+OFFSET($C$66,COUNTA($E$64:L64),0,,) -> 154.89722 | ... LV62: =+OFFSET($C$66,COUNTA($E$64:LV64),0,,) -> 0
B63: =+IF(C32-(A63/C63)<0,0,C32-(A63/C63)) -> 10 | C63: =+IF($A$64="Monthly",12,4) -> 12 | E63: =+ROUNDUP(COUNTA($E$64:E64)/$C$63,0) -> 1 | F63: =+ROUNDUP(COUNTA($E$64:F64)/$C$63,0) -> 1 | G63: =+ROUNDUP(COUNTA($E$64:G64)/$C$63,0) -> 1 | H63: =+ROUNDUP(COUNTA($E$64:H64)/$C$63,0) -> 1 | I63: =+ROUNDUP(COUNTA($E$64:I64)/$C$63,0) -> 1 | J63: =+ROUNDUP(COUNTA($E$64:J64)/$C$63,0) -> 1 | K63: =+ROUNDUP(COUNTA($E$64:K64)/$C$63,0) -> 1 | L63: =+ROUNDUP(COUNTA($E$64:L64)/$C$63,0) -> 1 | ... LV63: =+ROUNDUP(COUNTA($E$64:LV64)/$C$63,0) -> 28
A64: Monthly | C64: Total | D64: 43191 | E64: =EOMONTH(D64-1,1) -> 43220 | F64: =EOMONTH(E64,12/$C$63) -> 43251 | G64: =EOMONTH(F64,12/$C$63) -> 43281 | H64: =EOMONTH(G64,12/$C$63) -> 43312 | I64: =EOMONTH(H64,12/$C$63) -> 43343 | J64: =EOMONTH(I64,12/$C$63) -> 43373 | K64: =EOMONTH(J64,12/$C$63) -> 43404 | L64: =EOMONTH(K64,12/$C$63) -> 43434 | M64: =EOMONTH(L64,12/$C$63) -> 43465 | ... LV64: =EOMONTH(LU64,12/$C$63) -> 53235
C65: =SUM(C66:C1258) -> 11606.533 | D65: =SUM(D66:D1258) -> -10000 | E65: =SUM(E66:E1258) -> -400 | F65: =SUM(F66:F1258) -> -400 | G65: =SUM(G66:G1258) -> -400 | H65: =SUM(H66:H1258) -> -400 | I65: =SUM(I66:I1258) -> -360.66667 | J65: =SUM(J66:J1258) -> -359.09333 | ... IW65: =SUM(IW66:IW1258) -> 0
A66: Versement initial | B66: =+D52 -> 50 | C66: =SUM(D66:XEG66) -> 4187.0971 | D66: =-$C$25 -> -10000 | E66: =IF(E$63<=$C$17,($C$34*E$59*($C$25/E$59)/$C$63)*IF(D66>0,1,(IF(COUNTA($E$63:E63)*(12/$C$63)<=IF($C$15="Fondateur",$C$10,$C$9),0,(COUNTA($E$63:E63)*(12/$C$63)-IF($C$15="Fondateur",$C$10,$C$9))/(12/$C$63)))),0)+IF(F63=$C$17,0,IF(E63=$C$17,$B66*E$60,0)) -> 0 | F66: =IF(F$63<=$C$17,($C$34*F$59*($C$25/F$59)/$C$63)*IF(E66>0,1,(IF(COUNTA($E$63:F63)*(12/$C$63)<=IF($C$15="Fondateur",$C$10,$C$9),0,(COUNTA($E$63:F63)*(12/$C$63)-IF($C$15="Fondateur",$C$10,$C$9))/(12/$C$63)))),0)+IF(G63=$C$17,0,IF(F63=$C$17,$B66*F$60,0)) -> 0 | G66: =IF(G$63<=$C$17,($C$34*G$59*($C$25/G$59)/$C$63)*IF(F66>0,1,(IF(COUNTA($E$63:G63)*(12/$C$63)<=IF($C$15="Fondateur",$C$10,$C$9),0,(COUNTA($E$63:G63)*(12/$C$63)-IF($C$15="Fondateur",$C$10,$C$9))/(12/$C$63)))),0)+IF(H63=$C$17,0,IF(G63=$C$17,$B66*G$60,0)) -> 0 | H66: =IF(H$63<=$C$17,($C$34*H$59*($C$25/H$59)/$C$63)*IF(G66>0,1,(IF(COUNTA($E$63:H63)*(12/$C$63)<=IF($C$15="Fondateur",$C$10,$C$9),0,(COUNTA($E$63:H63)*(12/$C$63)-IF($C$15="Fondateur",$C$10,$C$9))/(12/$C$63)))),0)+IF(I63=$C$17,0,IF(H63=$C$17,$B66*H$60,0)) -> 0 | I66: =IF(I$63<=$C$17,($C$34*I$59*($C$25/I$59)/$C$63)*IF(H66>0,1,(IF(COUNTA($E$63:I63)*(12/$C$63)<=IF($C$15="Fondateur",$C$10,$C$9),0,(COUNTA($E$63:I63)*(12/$C$63)-IF($C$15="Fondateur",$C$10,$C$9))/(12/$C$63)))),0)+IF(J63=$C$17,0,IF(I63=$C$17,$B66*I$60,0)) -> 39.333333 | J66: =IF(J$63<=$C$17,($C$34*J$59*($C$25/J$59)/$C$63)*IF(I66>0,1,(IF(COUNTA($E$63:J63)*(12/$C$63)<=IF($C$15="Fondateur",$C$10,$C$9),0,(COUNTA($E$63:J63)*(12/$C$63)-IF($C$15="Fondateur",$C$10,$C$9))/(12/$C$63)))),0)+IF(K63=$C$17,0,IF(J63=$C$17,$B66*J$60,0)) -> 39.333333 | K66: =IF(K$63<=$C$17,($C$34*K$59*($C$25/K$59)/$C$63)*IF(J66>0,1,(IF(COUNTA($E$63:K63)*(12/$C$63)<=IF($C$15="Fondateur",$C$10,$C$9),0,(COUNTA($E$63:K63)*(12/$C$63)-IF($C$15="Fondateur",$C$10,$C$9))/(12/$C$63)))),0)+IF(L63=$C$17,0,IF(K63=$C$17,$B66*K$60,0)) -> 39.333333 | L66: =IF(L$63<=$C$17,($C$34*L$59*($C$25/L$59)/$C$63)*IF(K66>0,1,(IF(COUNTA($E$63:L63)*(12/$C$63)<=IF($C$15="Fondateur",$C$10,$C$9),0,(COUNTA($E$63:L63)*(12/$C$63)-IF($C$15="Fondateur",$C$10,$C$9))/(12/$C$63)))),0)+IF(M63=$C$17,0,IF(L63=$C$17,$B66*L$60,0)) -> 39.333333 | ... IW66: =IF(IW$63<=$C$17,($C$34*IW$59*($C$25/IW$59)/$C$63)*IF(IV66>0,1,(IF(COUNTA($E$63:IW63)*(12/$C$63)<=IF($C$15="Fondateur",$C$10,$C$9),0,(COUNTA($E$63:IW63)*(12/$C$63)-IF($C$15="Fondateur",$C$10,$C$9))/(12/$C$63)))),0)+IF(IX63=$C$17,0,IF(IW63=$C$17,$B66*IW$60,0)) -> 0
A67: Versement programmé | B67: =+OFFSET($D$52,0,COUNTA($B$66:B66),,) -> 2 | C67: =SUM(D67:XEG67) -> 165.91055 | E67: =IF(F$63>$C$17,0,-E$53*(12/$C$63)) -> -400 | F67: =IF(F$63<=$C$17,($C$34*F$59*$B67/$C$63)*(IF(COUNTA($D67:E67)*(12/$C$63)<=$C$9,0,1)),0)+IF(G$63=$C$17,0,IF(F$63=$C$17,$B67*(F$60),0)) -> 0 | G67: =IF(G$63<=$C$17,($C$34*G$59*$B67/$C$63)*(IF(COUNTA($D67:F67)*(12/$C$63)<=$C$9,0,1)),0)+IF(H$63=$C$17,0,IF(G$63=$C$17,$B67*(G$60),0)) -> 0 | H67: =IF(H$63<=$C$17,($C$34*H$59*$B67/$C$63)*(IF(COUNTA($D67:G67)*(12/$C$63)<=$C$9,0,1)),0)+IF(I$63=$C$17,0,IF(H$63=$C$17,$B67*(H$60),0)) -> 0 | I67: =IF(I$63<=$C$17,($C$34*I$59*$B67/$C$63)*(IF(COUNTA($D67:H67)*(12/$C$63)<=$C$9,0,1)),0)+IF(J$63=$C$17,0,IF(I$63=$C$17,$B67*(I$60),0)) -> 0 | J67: =IF(J$63<=$C$17,($C$34*J$59*$B67/$C$63)*(IF(COUNTA($D67:I67)*(12/$C$63)<=$C$9,0,1)),0)+IF(K$63=$C$17,0,IF(J$63=$C$17,$B67*(J$60),0)) -> 1.5733333 | K67: =IF(K$63<=$C$17,($C$34*K$59*$B67/$C$63)*(IF(COUNTA($D67:J67)*(12/$C$63)<=$C$9,0,1)),0)+IF(L$63=$C$17,0,IF(K$63=$C$17,$B67*(K$60),0)) -> 1.5733333 | L67: =IF(L$63<=$C$17,($C$34*L$59*$B67/$C$63)*(IF(COUNTA($D67:K67)*(12/$C$63)<=$C$9,0,1)),0)+IF(M$63=$C$17,0,IF(L$63=$C$17,$B67*(L$60),0)) -> 1.5733333 | M67: =IF(M$63<=$C$17,($C$34*M$59*$B67/$C$63)*(IF(COUNTA($D67:L67)*(12/$C$63)<=$C$9,0,1)),0)+IF(N$63=$C$17,0,IF(M$63=$C$17,$B67*(M$60),0)) -> 1.5733333 | ... IW67: =IF(IW$63<=$C$17,($C$34*IW$59*$B67/$C$63)*(IF(COUNTA($D67:IV67)*(12/$C$63)<=$C$9,0,1)),0)+IF(IX$63=$C$17,0,IF(IW$63=$C$17,$B67*(IW$60),0)) -> 0
A68: Versement programmé | B68: =+OFFSET($D$52,0,COUNTA($B$66:B67),,) -> 2 | C68: =SUM(D68:XEG68) -> 164.33722 | F68: =IF(G$63>$C$17,0,-F$53*(12/$C$63)) -> -400 | G68: =IF(G$63<=$C$17,($C$34*G$59*$B68/$C$63)*(IF(COUNTA($D68:F68)*(12/$C$63)<=$C$9,0,1)),0)+IF(H$63=$C$17,0,IF(G$63=$C$17,$B68*(G$60),0)) -> 0 | H68: =IF(H$63<=$C$17,($C$34*H$59*$B68/$C$63)*(IF(COUNTA($D68:G68)*(12/$C$63)<=$C$9,0,1)),0)+IF(I$63=$C$17,0,IF(H$63=$C$17,$B68*(H$60),0)) -> 0 | I68: =IF(I$63<=$C$17,($C$34*I$59*$B68/$C$63)*(IF(COUNTA($D68:H68)*(12/$C$63)<=$C$9,0,1)),0)+IF(J$63=$C$17,0,IF(I$63=$C$17,$B68*(I$60),0)) -> 0 | J68: =IF(J$63<=$C$17,($C$34*J$59*$B68/$C$63)*(IF(COUNTA($D68:I68)*(12/$C$63)<=$C$9,0,1)),0)+IF(K$63=$C$17,0,IF(J$63=$C$17,$B68*(J$60),0)) -> 0 | K68: =IF(K$63<=$C$17,($C$34*K$59*$B68/$C$63)*(IF(COUNTA($D68:J68)*(12/$C$63)<=$C$9,0,1)),0)+IF(L$63=$C$17,0,IF(K$63=$C$17,$B68*(K$60),0)) -> 1.5733333 | L68: =IF(L$63<=$C$17,($C$34*L$59*$B68/$C$63)*(IF(COUNTA($D68:K68)*(12/$C$63)<=$C$9,0,1)),0)+IF(M$63=$C$17,0,IF(L$63=$C$17,$B68*(L$60),0)) -> 1.5733333 | M68: =IF(M$63<=$C$17,($C$34*M$59*$B68/$C$63)*(IF(COUNTA($D68:L68)*(12/$C$63)<=$C$9,0,1)),0)+IF(N$63=$C$17,0,IF(M$63=$C$17,$B68*(M$60),0)) -> 1.5733333 | N68: =IF(N$63<=$C$17,($C$34*N$59*$B68/$C$63)*(IF(COUNTA($D68:M68)*(12/$C$63)<=$C$9,0,1)),0)+IF(O$63=$C$17,0,IF(N$63=$C$17,$B68*(N$60),0)) -> 1.5733333 | ... IW68: =IF(IW$63<=$C$17,($C$34*IW$59*$B68/$C$63)*(IF(COUNTA($D68:IV68)*(12/$C$63)<=$C$9,0,1)),0)+IF(IX$63=$C$17,0,IF(IW$63=$C$17,$B68*(IW$60),0)) -> 0
A69: Versement programmé | B69: =+OFFSET($D$52,0,COUNTA($B$66:B68),,) -> 2 | C69: =SUM(D69:XEG69) -> 162.76388 | G69: =IF(H$63>$C$17,0,-G$53*(12/$C$63)) -> -400 | H69: =IF(H$63<=$C$17,($C$34*H$59*$B69/$C$63)*(IF(COUNTA($D69:G69)*(12/$C$63)<=$C$9,0,1)),0)+IF(I$63=$C$17,0,IF(H$63=$C$17,$B69*(H$60),0)) -> 0 | I69: =IF(I$63<=$C$17,($C$34*I$59*$B69/$C$63)*(IF(COUNTA($D69:H69)*(12/$C$63)<=$C$9,0,1)),0)+IF(J$63=$C$17,0,IF(I$63=$C$17,$B69*(I$60),0)) -> 0 | J69: =IF(J$63<=$C$17,($C$34*J$59*$B69/$C$63)*(IF(COUNTA($D69:I69)*(12/$C$63)<=$C$9,0,1)),0)+IF(K$63=$C$17,0,IF(J$63=$C$17,$B69*(J$60),0)) -> 0 | K69: =IF(K$63<=$C$17,($C$34*K$59*$B69/$C$63)*(IF(COUNTA($D69:J69)*(12/$C$63)<=$C$9,0,1)),0)+IF(L$63=$C$17,0,IF(K$63=$C$17,$B69*(K$60),0)) -> 0 | L69: =IF(L$63<=$C$17,($C$34*L$59*$B69/$C$63)*(IF(COUNTA($D69:K69)*(12/$C$63)<=$C$9,0,1)),0)+IF(M$63=$C$17,0,IF(L$63=$C$17,$B69*(L$60),0)) -> 1.5733333 | M69: =IF(M$63<=$C$17,($C$34*M$59*$B69/$C$63)*(IF(COUNTA($D69:L69)*(12/$C$63)<=$C$9,0,1)),0)+IF(N$63=$C$17,0,IF(M$63=$C$17,$B69*(M$60),0)) -> 1.5733333 | N69: =IF(N$63<=$C$17,($C$34*N$59*$B69/$C$63)*(IF(COUNTA($D69:M69)*(12/$C$63)<=$C$9,0,1)),0)+IF(O$63=$C$17,0,IF(N$63=$C$17,$B69*(N$60),0)) -> 1.5733333 | O69: =IF(O$63<=$C$17,($C$34*O$59*$B69/$C$63)*(IF(COUNTA($D69:N69)*(12/$C$63)<=$C$9,0,1)),0)+IF(P$63=$C$17,0,IF(O$63=$C$17,$B69*(O$60),0)) -> 1.5733333 | ... IW69: =IF(IW$63<=$C$17,($C$34*IW$59*$B69/$C$63)*(IF(COUNTA($D69:IV69)*(12/$C$63)<=$C$9,0,1)),0)+IF(IX$63=$C$17,0,IF(IW$63=$C$17,$B69*(IW$60),0)) -> 0
A70: Versement programmé | B70: =+OFFSET($D$52,0,COUNTA($B$66:B69),,) -> 2 | C70: =SUM(D70:XEG70) -> 161.19055 | H70: =IF(I$63>$C$17,0,-H$53*(12/$C$63)) -> -400 | I70: =IF(I$63<=$C$17,($C$34*I$59*$B70/$C$63)*(IF(COUNTA($D70:H70)*(12/$C$63)<=$C$9,0,1)),0)+IF(J$63=$C$17,0,IF(I$63=$C$17,$B70*(I$60),0)) -> 0 | J70: =IF(J$63<=$C$17,($C$34*J$59*$B70/$C$63)*(IF(COUNTA($D70:I70)*(12/$C$63)<=$C$9,0,1)),0)+IF(K$63=$C$17,0,IF(J$63=$C$17,$B70*(J$60),0)) -> 0 | K70: =IF(K$63<=$C$17,($C$34*K$59*$B70/$C$63)*(IF(COUNTA($D70:J70)*(12/$C$63)<=$C$9,0,1)),0)+IF(L$63=$C$17,0,IF(K$63=$C$17,$B70*(K$60),0)) -> 0 | L70: =IF(L$63<=$C$17,($C$34*L$59*$B70/$C$63)*(IF(COUNTA($D70:K70)*(12/$C$63)<=$C$9,0,1)),0)+IF(M$63=$C$17,0,IF(L$63=$C$17,$B70*(L$60),0)) -> 0 | M70: =IF(M$63<=$C$17,($C$34*M$59*$B70/$C$63)*(IF(COUNTA($D70:L70)*(12/$C$63)<=$C$9,0,1)),0)+IF(N$63=$C$17,0,IF(M$63=$C$17,$B70*(M$60),0)) -> 1.5733333 | N70: =IF(N$63<=$C$17,($C$34*N$59*$B70/$C$63)*(IF(COUNTA($D70:M70)*(12/$C$63)<=$C$9,0,1)),0)+IF(O$63=$C$17,0,IF(N$63=$C$17,$B70*(N$60),0)) -> 1.5733333 | O70: =IF(O$63<=$C$17,($C$34*O$59*$B70/$C$63)*(IF(COUNTA($D70:N70)*(12/$C$63)<=$C$9,0,1)),0)+IF(P$63=$C$17,0,IF(O$63=$C$17,$B70*(O$60),0)) -> 1.5733333 | P70: =IF(P$63<=$C$17,($C$34*P$59*$B70/$C$63)*(IF(COUNTA($D70:O70)*(12/$C$63)<=$C$9,0,1)),0)+IF(Q$63=$C$17,0,IF(P$63=$C$17,$B70*(P$60),0)) -> 1.5733333 | ... IW70: =IF(IW$63<=$C$17,($C$34*IW$59*$B70/$C$63)*(IF(COUNTA($D70:IV70)*(12/$C$63)<=$C$9,0,1)),0)+IF(IX$63=$C$17,0,IF(IW$63=$C$17,$B70*(IW$60),0)) -> 0
A71: Versement programmé | B71: =+OFFSET($D$52,0,COUNTA($B$66:B70),,) -> 2 | C71: =SUM(D71:XEG71) -> 159.61722 | I71: =IF(J$63>$C$17,0,-I$53*(12/$C$63)) -> -400 | J71: =IF(J$63<=$C$17,($C$34*J$59*$B71/$C$63)*(IF(COUNTA($D71:I71)*(12/$C$63)<=$C$9,0,1)),0)+IF(K$63=$C$17,0,IF(J$63=$C$17,$B71*(J$60),0)) -> 0 | K71: =IF(K$63<=$C$17,($C$34*K$59*$B71/$C$63)*(IF(COUNTA($D71:J71)*(12/$C$63)<=$C$9,0,1)),0)+IF(L$63=$C$17,0,IF(K$63=$C$17,$B71*(K$60),0)) -> 0 | L71: =IF(L$63<=$C$17,($C$34*L$59*$B71/$C$63)*(IF(COUNTA($D71:K71)*(12/$C$63)<=$C$9,0,1)),0)+IF(M$63=$C$17,0,IF(L$63=$C$17,$B71*(L$60),0)) -> 0 | M71: =IF(M$63<=$C$17,($C$34*M$59*$B71/$C$63)*(IF(COUNTA($D71:L71)*(12/$C$63)<=$C$9,0,1)),0)+IF(N$63=$C$17,0,IF(M$63=$C$17,$B71*(M$60),0)) -> 0 | N71: =IF(N$63<=$C$17,($C$34*N$59*$B71/$C$63)*(IF(COUNTA($D71:M71)*(12/$C$63)<=$C$9,0,1)),0)+IF(O$63=$C$17,0,IF(N$63=$C$17,$B71*(N$60),0)) -> 1.5733333 | O71: =IF(O$63<=$C$17,($C$34*O$59*$B71/$C$63)*(IF(COUNTA($D71:N71)*(12/$C$63)<=$C$9,0,1)),0)+IF(P$63=$C$17,0,IF(O$63=$C$17,$B71*(O$60),0)) -> 1.5733333 | P71: =IF(P$63<=$C$17,($C$34*P$59*$B71/$C$63)*(IF(COUNTA($D71:O71)*(12/$C$63)<=$C$9,0,1)),0)+IF(Q$63=$C$17,0,IF(P$63=$C$17,$B71*(P$60),0)) -> 1.5733333 | Q71: =IF(Q$63<=$C$17,($C$34*Q$59*$B71/$C$63)*(IF(COUNTA($D71:P71)*(12/$C$63)<=$C$9,0,1)),0)+IF(R$63=$C$17,0,IF(Q$63=$C$17,$B71*(Q$60),0)) -> 1.5733333 | ... IW71: =IF(IW$63<=$C$17,($C$34*IW$59*$B71/$C$63)*(IF(COUNTA($D71:IV71)*(12/$C$63)<=$C$9,0,1)),0)+IF(IX$63=$C$17,0,IF(IW$63=$C$17,$B71*(IW$60),0)) -> 0
A72: Versement programmé | B72: =+OFFSET($D$52,0,COUNTA($B$66:B71),,) -> 2 | C72: =SUM(D72:XEG72) -> 158.04388 | J72: =IF(K$63>$C$17,0,-J$53*(12/$C$63)) -> -400 | K72: =IF(K$63<=$C$17,($C$34*K$59*$B72/$C$63)*(IF(COUNTA($D72:J72)*(12/$C$63)<=$C$9,0,1)),0)+IF(L$63=$C$17,0,IF(K$63=$C$17,$B72*(K$60),0)) -> 0 | L72: =IF(L$63<=$C$17,($C$34*L$59*$B72/$C$63)*(IF(COUNTA($D72:K72)*(12/$C$63)<=$C$9,0,1)),0)+IF(M$63=$C$17,0,IF(L$63=$C$17,$B72*(L$60),0)) -> 0 | M72: =IF(M$63<=$C$17,($C$34*M$59*$B72/$C$63)*(IF(COUNTA($D72:L72)*(12/$C$63)<=$C$9,0,1)),0)+IF(N$63=$C$17,0,IF(M$63=$C$17,$B72*(M$60),0)) -> 0 | N72: =IF(N$63<=$C$17,($C$34*N$59*$B72/$C$63)*(IF(COUNTA($D72:M72)*(12/$C$63)<=$C$9,0,1)),0)+IF(O$63=$C$17,0,IF(N$63=$C$17,$B72*(N$60),0)) -> 0 | O72: =IF(O$63<=$C$17,($C$34*O$59*$B72/$C$63)*(IF(COUNTA($D72:N72)*(12/$C$63)<=$C$9,0,1)),0)+IF(P$63=$C$17,0,IF(O$63=$C$17,$B72*(O$60),0)) -> 1.5733333 | P72: =IF(P$63<=$C$17,($C$34*P$59*$B72/$C$63)*(IF(COUNTA($D72:O72)*(12/$C$63)<=$C$9,0,1)),0)+IF(Q$63=$C$17,0,IF(P$63=$C$17,$B72*(P$60),0)) -> 1.5733333 | Q72: =IF(Q$63<=$C$17,($C$34*Q$59*$B72/$C$63)*(IF(COUNTA($D72:P72)*(12/$C$63)<=$C$9,0,1)),0)+IF(R$63=$C$17,0,IF(Q$63=$C$17,$B72*(Q$60),0)) -> 1.5733333 | R72: =IF(R$63<=$C$17,($C$34*R$59*$B72/$C$63)*(IF(COUNTA($D72:Q72)*(12/$C$63)<=$C$9,0,1)),0)+IF(S$63=$C$17,0,IF(R$63=$C$17,$B72*(R$60),0)) -> 1.5733333 | ... IW72: =IF(IW$63<=$C$17,($C$34*IW$59*$B72/$C$63)*(IF(COUNTA($D72:IV72)*(12/$C$63)<=$C$9,0,1)),0)+IF(IX$63=$C$17,0,IF(IW$63=$C$17,$B72*(IW$60),0)) -> 0
A73: Versement programmé | B73: =+OFFSET($D$52,0,COUNTA($B$66:B72),,) -> 2 | C73: =SUM(D73:XEG73) -> 156.47055 | K73: =IF(L$63>$C$17,0,-K$53*(12/$C$63)) -> -400 | L73: =IF(L$63<=$C$17,($C$34*L$59*$B73/$C$63)*(IF(COUNTA($D73:K73)*(12/$C$63)<=$C$9,0,1)),0)+IF(M$63=$C$17,0,IF(L$63=$C$17,$B73*(L$60),0)) -> 0 | M73: =IF(M$63<=$C$17,($C$34*M$59*$B73/$C$63)*(IF(COUNTA($D73:L73)*(12/$C$63)<=$C$9,0,1)),0)+IF(N$63=$C$17,0,IF(M$63=$C$17,$B73*(M$60),0)) -> 0 | N73: =IF(N$63<=$C$17,($C$34*N$59*$B73/$C$63)*(IF(COUNTA($D73:M73)*(12/$C$63)<=$C$9,0,1)),0)+IF(O$63=$C$17,0,IF(N$63=$C$17,$B73*(N$60),0)) -> 0 | O73: =IF(O$63<=$C$17,($C$34*O$59*$B73/$C$63)*(IF(COUNTA($D73:N73)*(12/$C$63)<=$C$9,0,1)),0)+IF(P$63=$C$17,0,IF(O$63=$C$17,$B73*(O$60),0)) -> 0 | P73: =IF(P$63<=$C$17,($C$34*P$59*$B73/$C$63)*(IF(COUNTA($D73:O73)*(12/$C$63)<=$C$9,0,1)),0)+IF(Q$63=$C$17,0,IF(P$63=$C$17,$B73*(P$60),0)) -> 1.5733333 | Q73: =IF(Q$63<=$C$17,($C$34*Q$59*$B73/$C$63)*(IF(COUNTA($D73:P73)*(12/$C$63)<=$C$9,0,1)),0)+IF(R$63=$C$17,0,IF(Q$63=$C$17,$B73*(Q$60),0)) -> 1.5733333 | R73: =IF(R$63<=$C$17,($C$34*R$59*$B73/$C$63)*(IF(COUNTA($D73:Q73)*(12/$C$63)<=$C$9,0,1)),0)+IF(S$63=$C$17,0,IF(R$63=$C$17,$B73*(R$60),0)) -> 1.5733333 | S73: =IF(S$63<=$C$17,($C$34*S$59*$B73/$C$63)*(IF(COUNTA($D73:R73)*(12/$C$63)<=$C$9,0,1)),0)+IF(T$63=$C$17,0,IF(S$63=$C$17,$B73*(S$60),0)) -> 1.5733333 | ... IW73: =IF(IW$63<=$C$17,($C$34*IW$59*$B73/$C$63)*(IF(COUNTA($D73:IV73)*(12/$C$63)<=$C$9,0,1)),0)+IF(IX$63=$C$17,0,IF(IW$63=$C$17,$B73*(IW$60),0)) -> 0
A74: Versement programmé | B74: =+OFFSET($D$52,0,COUNTA($B$66:B73),,) -> 2 | C74: =SUM(D74:XEG74) -> 154.89722 | L74: =IF(M$63>$C$17,0,-L$53*(12/$C$63)) -> -400 | M74: =IF(M$63<=$C$17,($C$34*M$59*$B74/$C$63)*(IF(COUNTA($D74:L74)*(12/$C$63)<=$C$9,0,1)),0)+IF(N$63=$C$17,0,IF(M$63=$C$17,$B74*(M$60),0)) -> 0 | N74: =IF(N$63<=$C$17,($C$34*N$59*$B74/$C$63)*(IF(COUNTA($D74:M74)*(12/$C$63)<=$C$9,0,1)),0)+IF(O$63=$C$17,0,IF(N$63=$C$17,$B74*(N$60),0)) -> 0 | O74: =IF(O$63<=$C$17,($C$34*O$59*$B74/$C$63)*(IF(COUNTA($D74:N74)*(12/$C$63)<=$C$9,0,1)),0)+IF(P$63=$C$17,0,IF(O$63=$C$17,$B74*(O$60),0)) -> 0 | P74: =IF(P$63<=$C$17,($C$34*P$59*$B74/$C$63)*(IF(COUNTA($D74:O74)*(12/$C$63)<=$C$9,0,1)),0)+IF(Q$63=$C$17,0,IF(P$63=$C$17,$B74*(P$60),0)) -> 0 | Q74: =IF(Q$63<=$C$17,($C$34*Q$59*$B74/$C$63)*(IF(COUNTA($D74:P74)*(12/$C$63)<=$C$9,0,1)),0)+IF(R$63=$C$17,0,IF(Q$63=$C$17,$B74*(Q$60),0)) -> 1.5733333 | R74: =IF(R$63<=$C$17,($C$34*R$59*$B74/$C$63)*(IF(COUNTA($D74:Q74)*(12/$C$63)<=$C$9,0,1)),0)+IF(S$63=$C$17,0,IF(R$63=$C$17,$B74*(R$60),0)) -> 1.5733333 | S74: =IF(S$63<=$C$17,($C$34*S$59*$B74/$C$63)*(IF(COUNTA($D74:R74)*(12/$C$63)<=$C$9,0,1)),0)+IF(T$63=$C$17,0,IF(S$63=$C$17,$B74*(S$60),0)) -> 1.5733333 | T74: =IF(T$63<=$C$17,($C$34*T$59*$B74/$C$63)*(IF(COUNTA($D74:S74)*(12/$C$63)<=$C$9,0,1)),0)+IF(U$63=$C$17,0,IF(T$63=$C$17,$B74*(T$60),0)) -> 1.5733333 | ... IW74: =IF(IW$63<=$C$17,($C$34*IW$59*$B74/$C$63)*(IF(COUNTA($D74:IV74)*(12/$C$63)<=$C$9,0,1)),0)+IF(IX$63=$C$17,0,IF(IW$63=$C$17,$B74*(IW$60),0)) -> 0
A75: Versement programmé | B75: =+OFFSET($D$52,0,COUNTA($B$66:B74),,) -> 3 | C75: =SUM(D75:XEG75) -> 229.98582 | M75: =IF(N$63>$C$17,0,-M$53*(12/$C$63)) -> -600 | N75: =IF(N$63<=$C$17,($C$34*N$59*$B75/$C$63)*(IF(COUNTA($D75:M75)*(12/$C$63)<=$C$9,0,1)),0)+IF(O$63=$C$17,0,IF(N$63=$C$17,$B75*(N$60),0)) -> 0 | O75: =IF(O$63<=$C$17,($C$34*O$59*$B75/$C$63)*(IF(COUNTA($D75:N75)*(12/$C$63)<=$C$9,0,1)),0)+IF(P$63=$C$17,0,IF(O$63=$C$17,$B75*(O$60),0)) -> 0 | P75: =IF(P$63<=$C$17,($C$34*P$59*$B75/$C$63)*(IF(COUNTA($D75:O75)*(12/$C$63)<=$C$9,0,1)),0)+IF(Q$63=$C$17,0,IF(P$63=$C$17,$B75*(P$60),0)) -> 0 | Q75: =IF(Q$63<=$C$17,($C$34*Q$59*$B75/$C$63)*(IF(COUNTA($D75:P75)*(12/$C$63)<=$C$9,0,1)),0)+IF(R$63=$C$17,0,IF(Q$63=$C$17,$B75*(Q$60),0)) -> 0 | R75: =IF(R$63<=$C$17,($C$34*R$59*$B75/$C$63)*(IF(COUNTA($D75:Q75)*(12/$C$63)<=$C$9,0,1)),0)+IF(S$63=$C$17,0,IF(R$63=$C$17,$B75*(R$60),0)) -> 2.36 | S75: =IF(S$63<=$C$17,($C$34*S$59*$B75/$C$63)*(IF(COUNTA($D75:R75)*(12/$C$63)<=$C$9,0,1)),0)+IF(T$63=$C$17,0,IF(S$63=$C$17,$B75*(S$60),0)) -> 2.36 | T75: =IF(T$63<=$C$17,($C$34*T$59*$B75/$C$63)*(IF(COUNTA($D75:S75)*(12/$C$63)<=$C$9,0,1)),0)+IF(U$63=$C$17,0,IF(T$63=$C$17,$B75*(T$60),0)) -> 2.36 | U75: =IF(U$63<=$C$17,($C$34*U$59*$B75/$C$63)*(IF(COUNTA($D75:T75)*(12/$C$63)<=$C$9,0,1)),0)+IF(V$63=$C$17,0,IF(U$63=$C$17,$B75*(U$60),0)) -> 2.36 | ... IW75: =IF(IW$63<=$C$17,($C$34*IW$59*$B75/$C$63)*(IF(COUNTA($D75:IV75)*(12/$C$63)<=$C$9,0,1)),0)+IF(IX$63=$C$17,0,IF(IW$63=$C$17,$B75*(IW$60),0)) -> 0
A76: Versement programmé | B76: =+OFFSET($D$52,0,COUNTA($B$66:B75),,) -> 2 | C76: =SUM(D76:XEG76) -> 151.75055 | N76: =IF(O$63>$C$17,0,-N$53*(12/$C$63)) -> -400 | O76: =IF(O$63<=$C$17,($C$34*O$59*$B76/$C$63)*(IF(COUNTA($D76:N76)*(12/$C$63)<=$C$9,0,1)),0)+IF(P$63=$C$17,0,IF(O$63=$C$17,$B76*(O$60),0)) -> 0 | P76: =IF(P$63<=$C$17,($C$34*P$59*$B76/$C$63)*(IF(COUNTA($D76:O76)*(12/$C$63)<=$C$9,0,1)),0)+IF(Q$63=$C$17,0,IF(P$63=$C$17,$B76*(P$60),0)) -> 0 | Q76: =IF(Q$63<=$C$17,($C$34*Q$59*$B76/$C$63)*(IF(COUNTA($D76:P76)*(12/$C$63)<=$C$9,0,1)),0)+IF(R$63=$C$17,0,IF(Q$63=$C$17,$B76*(Q$60),0)) -> 0 | R76: =IF(R$63<=$C$17,($C$34*R$59*$B76/$C$63)*(IF(COUNTA($D76:Q76)*(12/$C$63)<=$C$9,0,1)),0)+IF(S$63=$C$17,0,IF(R$63=$C$17,$B76*(R$60),0)) -> 0 | S76: =IF(S$63<=$C$17,($C$34*S$59*$B76/$C$63)*(IF(COUNTA($D76:R76)*(12/$C$63)<=$C$9,0,1)),0)+IF(T$63=$C$17,0,IF(S$63=$C$17,$B76*(S$60),0)) -> 1.5733333 | T76: =IF(T$63<=$C$17,($C$34*T$59*$B76/$C$63)*(IF(COUNTA($D76:S76)*(12/$C$63)<=$C$9,0,1)),0)+IF(U$63=$C$17,0,IF(T$63=$C$17,$B76*(T$60),0)) -> 1.5733333 | U76: =IF(U$63<=$C$17,($C$34*U$59*$B76/$C$63)*(IF(COUNTA($D76:T76)*(12/$C$63)<=$C$9,0,1)),0)+IF(V$63=$C$17,0,IF(U$63=$C$17,$B76*(U$60),0)) -> 1.5733333 | V76: =IF(V$63<=$C$17,($C$34*V$59*$B76/$C$63)*(IF(COUNTA($D76:U76)*(12/$C$63)<=$C$9,0,1)),0)+IF(W$63=$C$17,0,IF(V$63=$C$17,$B76*(V$60),0)) -> 1.5733333 | ... IW76: =IF(IW$63<=$C$17,($C$34*IW$59*$B76/$C$63)*(IF(COUNTA($D76:IV76)*(12/$C$63)<=$C$9,0,1)),0)+IF(IX$63=$C$17,0,IF(IW$63=$C$17,$B76*(IW$60),0)) -> 0
A77: Versement programmé | B77: =+OFFSET($D$52,0,COUNTA($B$66:B76),,) -> 2 | C77: =SUM(D77:XEG77) -> 150.17722 | O77: =IF(P$63>$C$17,0,-O$53*(12/$C$63)) -> -400 | P77: =IF(P$63<=$C$17,($C$34*P$59*$B77/$C$63)*(IF(COUNTA($D77:O77)*(12/$C$63)<=$C$9,0,1)),0)+IF(Q$63=$C$17,0,IF(P$63=$C$17,$B77*(P$60),0)) -> 0 | Q77: =IF(Q$63<=$C$17,($C$34*Q$59*$B77/$C$63)*(IF(COUNTA($D77:P77)*(12/$C$63)<=$C$9,0,1)),0)+IF(R$63=$C$17,0,IF(Q$63=$C$17,$B77*(Q$60),0)) -> 0 | R77: =IF(R$63<=$C$17,($C$34*R$59*$B77/$C$63)*(IF(COUNTA($D77:Q77)*(12/$C$63)<=$C$9,0,1)),0)+IF(S$63=$C$17,0,IF(R$63=$C$17,$B77*(R$60),0)) -> 0 | S77: =IF(S$63<=$C$17,($C$34*S$59*$B77/$C$63)*(IF(COUNTA($D77:R77)*(12/$C$63)<=$C$9,0,1)),0)+IF(T$63=$C$17,0,IF(S$63=$C$17,$B77*(S$60),0)) -> 0 | T77: =IF(T$63<=$C$17,($C$34*T$59*$B77/$C$63)*(IF(COUNTA($D77:S77)*(12/$C$63)<=$C$9,0,1)),0)+IF(U$63=$C$17,0,IF(T$63=$C$17,$B77*(T$60),0)) -> 1.5733333 | U77: =IF(U$63<=$C$17,($C$34*U$59*$B77/$C$63)*(IF(COUNTA($D77:T77)*(12/$C$63)<=$C$9,0,1)),0)+IF(V$63=$C$17,0,IF(U$63=$C$17,$B77*(U$60),0)) -> 1.5733333 | V77: =IF(V$63<=$C$17,($C$34*V$59*$B77/$C$63)*(IF(COUNTA($D77:U77)*(12/$C$63)<=$C$9,0,1)),0)+IF(W$63=$C$17,0,IF(V$63=$C$17,$B77*(V$60),0)) -> 1.5733333 | W77: =IF(W$63<=$C$17,($C$34*W$59*$B77/$C$63)*(IF(COUNTA($D77:V77)*(12/$C$63)<=$C$9,0,1)),0)+IF(X$63=$C$17,0,IF(W$63=$C$17,$B77*(W$60),0)) -> 1.5733333 | ... IW77: =IF(IW$63<=$C$17,($C$34*IW$59*$B77/$C$63)*(IF(COUNTA($D77:IV77)*(12/$C$63)<=$C$9,0,1)),0)+IF(IX$63=$C$17,0,IF(IW$63=$C$17,$B77*(IW$60),0)) -> 0
A78: Versement programmé | B78: =+OFFSET($D$52,0,COUNTA($B$66:B77),,) -> 2 | C78: =SUM(D78:XEG78) -> 148.60388 | P78: =IF(Q$63>$C$17,0,-P$53*(12/$C$63)) -> -400 | Q78: =IF(Q$63<=$C$17,($C$34*Q$59*$B78/$C$63)*(IF(COUNTA($D78:P78)*(12/$C$63)<=$C$9,0,1)),0)+IF(R$63=$C$17,0,IF(Q$63=$C$17,$B78*(Q$60),0)) -> 0 | R78: =IF(R$63<=$C$17,($C$34*R$59*$B78/$C$63)*(IF(COUNTA($D78:Q78)*(12/$C$63)<=$C$9,0,1)),0)+IF(S$63=$C$17,0,IF(R$63=$C$17,$B78*(R$60),0)) -> 0 | S78: =IF(S$63<=$C$17,($C$34*S$59*$B78/$C$63)*(IF(COUNTA($D78:R78)*(12/$C$63)<=$C$9,0,1)),0)+IF(T$63=$C$17,0,IF(S$63=$C$17,$B78*(S$60),0)) -> 0 | T78: =IF(T$63<=$C$17,($C$34*T$59*$B78/$C$63)*(IF(COUNTA($D78:S78)*(12/$C$63)<=$C$9,0,1)),0)+IF(U$63=$C$17,0,IF(T$63=$C$17,$B78*(T$60),0)) -> 0 | U78: =IF(U$63<=$C$17,($C$34*U$59*$B78/$C$63)*(IF(COUNTA($D78:T78)*(12/$C$63)<=$C$9,0,1)),0)+IF(V$63=$C$17,0,IF(U$63=$C$17,$B78*(U$60),0)) -> 1.5733333 | V78: =IF(V$63<=$C$17,($C$34*V$59*$B78/$C$63)*(IF(COUNTA($D78:U78)*(12/$C$63)<=$C$9,0,1)),0)+IF(W$63=$C$17,0,IF(V$63=$C$17,$B78*(V$60),0)) -> 1.5733333 | W78: =IF(W$63<=$C$17,($C$34*W$59*$B78/$C$63)*(IF(COUNTA($D78:V78)*(12/$C$63)<=$C$9,0,1)),0)+IF(X$63=$C$17,0,IF(W$63=$C$17,$B78*(W$60),0)) -> 1.5733333 | X78: =IF(X$63<=$C$17,($C$34*X$59*$B78/$C$63)*(IF(COUNTA($D78:W78)*(12/$C$63)<=$C$9,0,1)),0)+IF(Y$63=$C$17,0,IF(X$63=$C$17,$B78*(X$60),0)) -> 1.5733333 | ... IW78: =IF(IW$63<=$C$17,($C$34*IW$59*$B78/$C$63)*(IF(COUNTA($D78:IV78)*(12/$C$63)<=$C$9,0,1)),0)+IF(IX$63=$C$17,0,IF(IW$63=$C$17,$B78*(IW$60),0)) -> 0
A79: Versement programmé | B79: =+OFFSET($D$52,0,COUNTA($B$66:B78),,) -> 3 | C79: =SUM(D79:XEG79) -> 214.54582 | Q79: =IF(R$63>$C$17,0,-Q$53*(12/$C$63)) -> -606 | R79: =IF(R$63<=$C$17,($C$34*R$59*$B79/$C$63)*(IF(COUNTA($D79:Q79)*(12/$C$63)<=$C$9,0,1)),0)+IF(S$63=$C$17,0,IF(R$63=$C$17,$B79*(R$60),0)) -> 0 | S79: =IF(S$63<=$C$17,($C$34*S$59*$B79/$C$63)*(IF(COUNTA($D79:R79)*(12/$C$63)<=$C$9,0,1)),0)+IF(T$63=$C$17,0,IF(S$63=$C$17,$B79*(S$60),0)) -> 0 | T79: =IF(T$63<=$C$17,($C$34*T$59*$B79/$C$63)*(IF(COUNTA($D79:S79)*(12/$C$63)<=$C$9,0,1)),0)+IF(U$63=$C$17,0,IF(T$63=$C$17,$B79*(T$60),0)) -> 0 | U79: =IF(U$63<=$C$17,($C$34*U$59*$B79/$C$63)*(IF(COUNTA($D79:T79)*(12/$C$63)<=$C$9,0,1)),0)+IF(V$63=$C$17,0,IF(U$63=$C$17,$B79*(U$60),0)) -> 0 | V79: =IF(V$63<=$C$17,($C$34*V$59*$B79/$C$63)*(IF(COUNTA($D79:U79)*(12/$C$63)<=$C$9,0,1)),0)+IF(W$63=$C$17,0,IF(V$63=$C$17,$B79*(V$60),0)) -> 2.36 | W79: =IF(W$63<=$C$17,($C$34*W$59*$B79/$C$63)*(IF(COUNTA($D79:V79)*(12/$C$63)<=$C$9,0,1)),0)+IF(X$63=$C$17,0,IF(W$63=$C$17,$B79*(W$60),0)) -> 2.36 | X79: =IF(X$63<=$C$17,($C$34*X$59*$B79/$C$63)*(IF(COUNTA($D79:W79)*(12/$C$63)<=$C$9,0,1)),0)+IF(Y$63=$C$17,0,IF(X$63=$C$17,$B79*(X$60),0)) -> 2.36 | Y79: =IF(Y$63<=$C$17,($C$34*Y$59*$B79/$C$63)*(IF(COUNTA($D79:X79)*(12/$C$63)<=$C$9,0,1)),0)+IF(Z$63=$C$17,0,IF(Y$63=$C$17,$B79*(Y$60),0)) -> 2.36 | ... IW79: =IF(IW$63<=$C$17,($C$34*IW$59*$B79/$C$63)*(IF(COUNTA($D79:IV79)*(12/$C$63)<=$C$9,0,1)),0)+IF(IX$63=$C$17,0,IF(IW$63=$C$17,$B79*(IW$60),0)) -> 0
A80: Versement programmé | B80: =+OFFSET($D$52,0,COUNTA($B$66:B79),,) -> 2 | C80: =SUM(D80:XEG80) -> 141.45722 | R80: =IF(S$63>$C$17,0,-R$53*(12/$C$63)) -> -404 | S80: =IF(S$63<=$C$17,($C$34*S$59*$B80/$C$63)*(IF(COUNTA($D80:R80)*(12/$C$63)<=$C$9,0,1)),0)+IF(T$63=$C$17,0,IF(S$63=$C$17,$B80*(S$60),0)) -> 0 | T80: =IF(T$63<=$C$17,($C$34*T$59*$B80/$C$63)*(IF(COUNTA($D80:S80)*(12/$C$63)<=$C$9,0,1)),0)+IF(U$63=$C$17,0,IF(T$63=$C$17,$B80*(T$60),0)) -> 0 | U80: =IF(U$63<=$C$17,($C$34*U$59*$B80/$C$63)*(IF(COUNTA($D80:T80)*(12/$C$63)<=$C$9,0,1)),0)+IF(V$63=$C$17,0,IF(U$63=$C$17,$B80*(U$60),0)) -> 0 | V80: =IF(V$63<=$C$17,($C$34*V$59*$B80/$C$63)*(IF(COUNTA($D80:U80)*(12/$C$63)<=$C$9,0,1)),0)+IF(W$63=$C$17,0,IF(V$63=$C$17,$B80*(V$60),0)) -> 0 | W80: =IF(W$63<=$C$17,($C$34*W$59*$B80/$C$63)*(IF(COUNTA($D80:V80)*(12/$C$63)<=$C$9,0,1)),0)+IF(X$63=$C$17,0,IF(W$63=$C$17,$B80*(W$60),0)) -> 1.5733333 | X80: =IF(X$63<=$C$17,($C$34*X$59*$B80/$C$63)*(IF(COUNTA($D80:W80)*(12/$C$63)<=$C$9,0,1)),0)+IF(Y$63=$C$17,0,IF(X$63=$C$17,$B80*(X$60),0)) -> 1.5733333 | Y80: =IF(Y$63<=$C$17,($C$34*Y$59*$B80/$C$63)*(IF(COUNTA($D80:X80)*(12/$C$63)<=$C$9,0,1)),0)+IF(Z$63=$C$17,0,IF(Y$63=$C$17,$B80*(Y$60),0)) -> 1.5733333 | Z80: =IF(Z$63<=$C$17,($C$34*Z$59*$B80/$C$63)*(IF(COUNTA($D80:Y80)*(12/$C$63)<=$C$9,0,1)),0)+IF(AA$63=$C$17,0,IF(Z$63=$C$17,$B80*(Z$60),0)) -> 1.5733333 | ... IW80: =IF(IW$63<=$C$17,($C$34*IW$59*$B80/$C$63)*(IF(COUNTA($D80:IV80)*(12/$C$63)<=$C$9,0,1)),0)+IF(IX$63=$C$17,0,IF(IW$63=$C$17,$B80*(IW$60),0)) -> 0
A81: Versement programmé | B81: =+OFFSET($D$52,0,COUNTA($B$66:B80),,) -> 2 | C81: =SUM(D81:XEG81) -> 139.88388 | S81: =IF(T$63>$C$17,0,-S$53*(12/$C$63)) -> -404 | T81: =IF(T$63<=$C$17,($C$34*T$59*$B81/$C$63)*(IF(COUNTA($D81:S81)*(12/$C$63)<=$C$9,0,1)),0)+IF(U$63=$C$17,0,IF(T$63=$C$17,$B81*(T$60),0)) -> 0 | U81: =IF(U$63<=$C$17,($C$34*U$59*$B81/$C$63)*(IF(COUNTA($D81:T81)*(12/$C$63)<=$C$9,0,1)),0)+IF(V$63=$C$17,0,IF(U$63=$C$17,$B81*(U$60),0)) -> 0 | V81: =IF(V$63<=$C$17,($C$34*V$59*$B81/$C$63)*(IF(COUNTA($D81:U81)*(12/$C$63)<=$C$9,0,1)),0)+IF(W$63=$C$17,0,IF(V$63=$C$17,$B81*(V$60),0)) -> 0 | W81: =IF(W$63<=$C$17,($C$34*W$59*$B81/$C$63)*(IF(COUNTA($D81:V81)*(12/$C$63)<=$C$9,0,1)),0)+IF(X$63=$C$17,0,IF(W$63=$C$17,$B81*(W$60),0)) -> 0 | X81: =IF(X$63<=$C$17,($C$34*X$59*$B81/$C$63)*(IF(COUNTA($D81:W81)*(12/$C$63)<=$C$9,0,1)),0)+IF(Y$63=$C$17,0,IF(X$63=$C$17,$B81*(X$60),0)) -> 1.5733333 | Y81: =IF(Y$63<=$C$17,($C$34*Y$59*$B81/$C$63)*(IF(COUNTA($D81:X81)*(12/$C$63)<=$C$9,0,1)),0)+IF(Z$63=$C$17,0,IF(Y$63=$C$17,$B81*(Y$60),0)) -> 1.5733333 | Z81: =IF(Z$63<=$C$17,($C$34*Z$59*$B81/$C$63)*(IF(COUNTA($D81:Y81)*(12/$C$63)<=$C$9,0,1)),0)+IF(AA$63=$C$17,0,IF(Z$63=$C$17,$B81*(Z$60),0)) -> 1.5733333 | AA81: =IF(AA$63<=$C$17,($C$34*AA$59*$B81/$C$63)*(IF(COUNTA($D81:Z81)*(12/$C$63)<=$C$9,0,1)),0)+IF(AB$63=$C$17,0,IF(AA$63=$C$17,$B81*(AA$60),0)) -> 1.5733333 | ... IW81: =IF(IW$63<=$C$17,($C$34*IW$59*$B81/$C$63)*(IF(COUNTA($D81:IV81)*(12/$C$63)<=$C$9,0,1)),0)+IF(IX$63=$C$17,0,IF(IW$63=$C$17,$B81*(IW$60),0)) -> 0
A82: Versement programmé | B82: =+OFFSET($D$52,0,COUNTA($B$66:B81),,) -> 2 | C82: =SUM(D82:XEG82) -> 138.31055 | T82: =IF(U$63>$C$17,0,-T$53*(12/$C$63)) -> -404 | U82: =IF(U$63<=$C$17,($C$34*U$59*$B82/$C$63)*(IF(COUNTA($D82:T82)*(12/$C$63)<=$C$9,0,1)),0)+IF(V$63=$C$17,0,IF(U$63=$C$17,$B82*(U$60),0)) -> 0 | V82: =IF(V$63<=$C$17,($C$34*V$59*$B82/$C$63)*(IF(COUNTA($D82:U82)*(12/$C$63)<=$C$9,0,1)),0)+IF(W$63=$C$17,0,IF(V$63=$C$17,$B82*(V$60),0)) -> 0 | W82: =IF(W$63<=$C$17,($C$34*W$59*$B82/$C$63)*(IF(COUNTA($D82:V82)*(12/$C$63)<=$C$9,0,1)),0)+IF(X$63=$C$17,0,IF(W$63=$C$17,$B82*(W$60),0)) -> 0 | X82: =IF(X$63<=$C$17,($C$34*X$59*$B82/$C$63)*(IF(COUNTA($D82:W82)*(12/$C$63)<=$C$9,0,1)),0)+IF(Y$63=$C$17,0,IF(X$63=$C$17,$B82*(X$60),0)) -> 0 | Y82: =IF(Y$63<=$C$17,($C$34*Y$59*$B82/$C$63)*(IF(COUNTA($D82:X82)*(12/$C$63)<=$C$9,0,1)),0)+IF(Z$63=$C$17,0,IF(Y$63=$C$17,$B82*(Y$60),0)) -> 1.5733333 | Z82: =IF(Z$63<=$C$17,($C$34*Z$59*$B82/$C$63)*(IF(COUNTA($D82:Y82)*(12/$C$63)<=$C$9,0,1)),0)+IF(AA$63=$C$17,0,IF(Z$63=$C$17,$B82*(Z$60),0)) -> 1.5733333 | AA82: =IF(AA$63<=$C$17,($C$34*AA$59*$B82/$C$63)*(IF(COUNTA($D82:Z82)*(12/$C$63)<=$C$9,0,1)),0)+IF(AB$63=$C$17,0,IF(AA$63=$C$17,$B82*(AA$60),0)) -> 1.5733333 | AB82: =IF(AB$63<=$C$17,($C$34*AB$59*$B82/$C$63)*(IF(COUNTA($D82:AA82)*(12/$C$63)<=$C$9,0,1)),0)+IF(AC$63=$C$17,0,IF(AB$63=$C$17,$B82*(AB$60),0)) -> 1.5733333 | ... IW82: =IF(IW$63<=$C$17,($C$34*IW$59*$B82/$C$63)*(IF(COUNTA($D82:IV82)*(12/$C$63)<=$C$9,0,1)),0)+IF(IX$63=$C$17,0,IF(IW$63=$C$17,$B82*(IW$60),0)) -> 0
A83: Versement programmé | B83: =+OFFSET($D$52,0,COUNTA($B$66:B82),,) -> 3 | C83: =SUM(D83:XEG83) -> 205.10582 | U83: =IF(V$63>$C$17,0,-U$53*(12/$C$63)) -> -606 | V83: =IF(V$63<=$C$17,($C$34*V$59*$B83/$C$63)*(IF(COUNTA($D83:U83)*(12/$C$63)<=$C$9,0,1)),0)+IF(W$63=$C$17,0,IF(V$63=$C$17,$B83*(V$60),0)) -> 0 | W83: =IF(W$63<=$C$17,($C$34*W$59*$B83/$C$63)*(IF(COUNTA($D83:V83)*(12/$C$63)<=$C$9,0,1)),0)+IF(X$63=$C$17,0,IF(W$63=$C$17,$B83*(W$60),0)) -> 0 | X83: =IF(X$63<=$C$17,($C$34*X$59*$B83/$C$63)*(IF(COUNTA($D83:W83)*(12/$C$63)<=$C$9,0,1)),0)+IF(Y$63=$C$17,0,IF(X$63=$C$17,$B83*(X$60),0)) -> 0 | Y83: =IF(Y$63<=$C$17,($C$34*Y$59*$B83/$C$63)*(IF(COUNTA($D83:X83)*(12/$C$63)<=$C$9,0,1)),0)+IF(Z$63=$C$17,0,IF(Y$63=$C$17,$B83*(Y$60),0)) -> 0 | Z83: =IF(Z$63<=$C$17,($C$34*Z$59*$B83/$C$63)*(IF(COUNTA($D83:Y83)*(12/$C$63)<=$C$9,0,1)),0)+IF(AA$63=$C$17,0,IF(Z$63=$C$17,$B83*(Z$60),0)) -> 2.36 | AA83: =IF(AA$63<=$C$17,($C$34*AA$59*$B83/$C$63)*(IF(COUNTA($D83:Z83)*(12/$C$63)<=$C$9,0,1)),0)+IF(AB$63=$C$17,0,IF(AA$63=$C$17,$B83*(AA$60),0)) -> 2.36 | AB83: =IF(AB$63<=$C$17,($C$34*AB$59*$B83/$C$63)*(IF(COUNTA($D83:AA83)*(12/$C$63)<=$C$9,0,1)),0)+IF(AC$63=$C$17,0,IF(AB$63=$C$17,$B83*(AB$60),0)) -> 2.36 | AC83: =IF(AC$63<=$C$17,($C$34*AC$59*$B83/$C$63)*(IF(COUNTA($D83:AB83)*(12/$C$63)<=$C$9,0,1)),0)+IF(AD$63=$C$17,0,IF(AC$63=$C$17,$B83*(AC$60),0)) -> 2.36 | ... IW83: =IF(IW$63<=$C$17,($C$34*IW$59*$B83/$C$63)*(IF(COUNTA($D83:IV83)*(12/$C$63)<=$C$9,0,1)),0)+IF(IX$63=$C$17,0,IF(IW$63=$C$17,$B83*(IW$60),0)) -> 0
A84: Versement programmé | B84: =+OFFSET($D$52,0,COUNTA($B$66:B83),,) -> 2 | C84: =SUM(D84:XEG84) -> 135.16388 | V84: =IF(W$63>$C$17,0,-V$53*(12/$C$63)) -> -404 | W84: =IF(W$63<=$C$17,($C$34*W$59*$B84/$C$63)*(IF(COUNTA($D84:V84)*(12/$C$63)<=$C$9,0,1)),0)+IF(X$63=$C$17,0,IF(W$63=$C$17,$B84*(W$60),0)) -> 0 | X84: =IF(X$63<=$C$17,($C$34*X$59*$B84/$C$63)*(IF(COUNTA($D84:W84)*(12/$C$63)<=$C$9,0,1)),0)+IF(Y$63=$C$17,0,IF(X$63=$C$17,$B84*(X$60),0)) -> 0 | Y84: =IF(Y$63<=$C$17,($C$34*Y$59*$B84/$C$63)*(IF(COUNTA($D84:X84)*(12/$C$63)<=$C$9,0,1)),0)+IF(Z$63=$C$17,0,IF(Y$63=$C$17,$B84*(Y$60),0)) -> 0 | Z84: =IF(Z$63<=$C$17,($C$34*Z$59*$B84/$C$63)*(IF(COUNTA($D84:Y84)*(12/$C$63)<=$C$9,0,1)),0)+IF(AA$63=$C$17,0,IF(Z$63=$C$17,$B84*(Z$60),0)) -> 0 | AA84: =IF(AA$63<=$C$17,($C$34*AA$59*$B84/$C$63)*(IF(COUNTA($D84:Z84)*(12/$C$63)<=$C$9,0,1)),0)+IF(AB$63=$C$17,0,IF(AA$63=$C$17,$B84*(AA$60),0)) -> 1.5733333 | AB84: =IF(AB$63<=$C$17,($C$34*AB$59*$B84/$C$63)*(IF(COUNTA($D84:AA84)*(12/$C$63)<=$C$9,0,1)),0)+IF(AC$63=$C$17,0,IF(AB$63=$C$17,$B84*(AB$60),0)) -> 1.5733333 | AC84: =IF(AC$63<=$C$17,($C$34*AC$59*$B84/$C$63)*(IF(COUNTA($D84:AB84)*(12/$C$63)<=$C$9,0,1)),0)+IF(AD$63=$C$17,0,IF(AC$63=$C$17,$B84*(AC$60),0)) -> 1.5733333 | AD84: =IF(AD$63<=$C$17,($C$34*AD$59*$B84/$C$63)*(IF(COUNTA($D84:AC84)*(12/$C$63)<=$C$9,0,1)),0)+IF(AE$63=$C$17,0,IF(AD$63=$C$17,$B84*(AD$60),0)) -> 1.5733333 | ... IW84: =IF(IW$63<=$C$17,($C$34*IW$59*$B84/$C$63)*(IF(COUNTA($D84:IV84)*(12/$C$63)<=$C$9,0,1)),0)+IF(IX$63=$C$17,0,IF(IW$63=$C$17,$B84*(IW$60),0)) -> 0
A85: Versement programmé | B85: =+OFFSET($D$52,0,COUNTA($B$66:B84),,) -> 2 | C85: =SUM(D85:XEG85) -> 133.59055 | W85: =IF(X$63>$C$17,0,-W$53*(12/$C$63)) -> -404 | X85: =IF(X$63<=$C$17,($C$34*X$59*$B85/$C$63)*(IF(COUNTA($D85:W85)*(12/$C$63)<=$C$9,0,1)),0)+IF(Y$63=$C$17,0,IF(X$63=$C$17,$B85*(X$60),0)) -> 0 | Y85: =IF(Y$63<=$C$17,($C$34*Y$59*$B85/$C$63)*(IF(COUNTA($D85:X85)*(12/$C$63)<=$C$9,0,1)),0)+IF(Z$63=$C$17,0,IF(Y$63=$C$17,$B85*(Y$60),0)) -> 0 | Z85: =IF(Z$63<=$C$17,($C$34*Z$59*$B85/$C$63)*(IF(COUNTA($D85:Y85)*(12/$C$63)<=$C$9,0,1)),0)+IF(AA$63=$C$17,0,IF(Z$63=$C$17,$B85*(Z$60),0)) -> 0 | AA85: =IF(AA$63<=$C$17,($C$34*AA$59*$B85/$C$63)*(IF(COUNTA($D85:Z85)*(12/$C$63)<=$C$9,0,1)),0)+IF(AB$63=$C$17,0,IF(AA$63=$C$17,$B85*(AA$60),0)) -> 0 | AB85: =IF(AB$63<=$C$17,($C$34*AB$59*$B85/$C$63)*(IF(COUNTA($D85:AA85)*(12/$C$63)<=$C$9,0,1)),0)+IF(AC$63=$C$17,0,IF(AB$63=$C$17,$B85*(AB$60),0)) -> 1.5733333 | AC85: =IF(AC$63<=$C$17,($C$34*AC$59*$B85/$C$63)*(IF(COUNTA($D85:AB85)*(12/$C$63)<=$C$9,0,1)),0)+IF(AD$63=$C$17,0,IF(AC$63=$C$17,$B85*(AC$60),0)) -> 1.5733333 | AD85: =IF(AD$63<=$C$17,($C$34*AD$59*$B85/$C$63)*(IF(COUNTA($D85:AC85)*(12/$C$63)<=$C$9,0,1)),0)+IF(AE$63=$C$17,0,IF(AD$63=$C$17,$B85*(AD$60),0)) -> 1.5733333 | AE85: =IF(AE$63<=$C$17,($C$34*AE$59*$B85/$C$63)*(IF(COUNTA($D85:AD85)*(12/$C$63)<=$C$9,0,1)),0)+IF(AF$63=$C$17,0,IF(AE$63=$C$17,$B85*(AE$60),0)) -> 1.5733333 | ... IW85: =IF(IW$63<=$C$17,($C$34*IW$59*$B85/$C$63)*(IF(COUNTA($D85:IV85)*(12/$C$63)<=$C$9,0,1)),0)+IF(IX$63=$C$17,0,IF(IW$63=$C$17,$B85*(IW$60),0)) -> 0
A86: Versement programmé | B86: =+OFFSET($D$52,0,COUNTA($B$66:B85),,) -> 3 | C86: =SUM(D86:XEG86) -> 198.02582 | X86: =IF(Y$63>$C$17,0,-X$53*(12/$C$63)) -> -606 | Y86: =IF(Y$63<=$C$17,($C$34*Y$59*$B86/$C$63)*(IF(COUNTA($D86:X86)*(12/$C$63)<=$C$9,0,1)),0)+IF(Z$63=$C$17,0,IF(Y$63=$C$17,$B86*(Y$60),0)) -> 0 | Z86: =IF(Z$63<=$C$17,($C$34*Z$59*$B86/$C$63)*(IF(COUNTA($D86:Y86)*(12/$C$63)<=$C$9,0,1)),0)+IF(AA$63=$C$17,0,IF(Z$63=$C$17,$B86*(Z$60),0)) -> 0 | AA86: =IF(AA$63<=$C$17,($C$34*AA$59*$B86/$C$63)*(IF(COUNTA($D86:Z86)*(12/$C$63)<=$C$9,0,1)),0)+IF(AB$63=$C$17,0,IF(AA$63=$C$17,$B86*(AA$60),0)) -> 0 | AB86: =IF(AB$63<=$C$17,($C$34*AB$59*$B86/$C$63)*(IF(COUNTA($D86:AA86)*(12/$C$63)<=$C$9,0,1)),0)+IF(AC$63=$C$17,0,IF(AB$63=$C$17,$B86*(AB$60),0)) -> 0 | AC86: =IF(AC$63<=$C$17,($C$34*AC$59*$B86/$C$63)*(IF(COUNTA($D86:AB86)*(12/$C$63)<=$C$9,0,1)),0)+IF(AD$63=$C$17,0,IF(AC$63=$C$17,$B86*(AC$60),0)) -> 2.36 | AD86: =IF(AD$63<=$C$17,($C$34*AD$59*$B86/$C$63)*(IF(COUNTA($D86:AC86)*(12/$C$63)<=$C$9,0,1)),0)+IF(AE$63=$C$17,0,IF(AD$63=$C$17,$B86*(AD$60),0)) -> 2.36 | AE86: =IF(AE$63<=$C$17,($C$34*AE$59*$B86/$C$63)*(IF(COUNTA($D86:AD86)*(12/$C$63)<=$C$9,0,1)),0)+IF(AF$63=$C$17,0,IF(AE$63=$C$17,$B86*(AE$60),0)) -> 2.36 | AF86: =IF(AF$63<=$C$17,($C$34*AF$59*$B86/$C$63)*(IF(COUNTA($D86:AE86)*(12/$C$63)<=$C$9,0,1)),0)+IF(AG$63=$C$17,0,IF(AF$63=$C$17,$B86*(AF$60),0)) -> 2.36 | ... IW86: =IF(IW$63<=$C$17,($C$34*IW$59*$B86/$C$63)*(IF(COUNTA($D86:IV86)*(12/$C$63)<=$C$9,0,1)),0)+IF(IX$63=$C$17,0,IF(IW$63=$C$17,$B86*(IW$60),0)) -> 0
A87: Versement programmé | B87: =+OFFSET($D$52,0,COUNTA($B$66:B86),,) -> 2 | C87: =SUM(D87:XEG87) -> 130.44388 | Y87: =IF(Z$63>$C$17,0,-Y$53*(12/$C$63)) -> -404 | Z87: =IF(Z$63<=$C$17,($C$34*Z$59*$B87/$C$63)*(IF(COUNTA($D87:Y87)*(12/$C$63)<=$C$9,0,1)),0)+IF(AA$63=$C$17,0,IF(Z$63=$C$17,$B87*(Z$60),0)) -> 0 | AA87: =IF(AA$63<=$C$17,($C$34*AA$59*$B87/$C$63)*(IF(COUNTA($D87:Z87)*(12/$C$63)<=$C$9,0,1)),0)+IF(AB$63=$C$17,0,IF(AA$63=$C$17,$B87*(AA$60),0)) -> 0 | AB87: =IF(AB$63<=$C$17,($C$34*AB$59*$B87/$C$63)*(IF(COUNTA($D87:AA87)*(12/$C$63)<=$C$9,0,1)),0)+IF(AC$63=$C$17,0,IF(AB$63=$C$17,$B87*(AB$60),0)) -> 0 | AC87: =IF(AC$63<=$C$17,($C$34*AC$59*$B87/$C$63)*(IF(COUNTA($D87:AB87)*(12/$C$63)<=$C$9,0,1)),0)+IF(AD$63=$C$17,0,IF(AC$63=$C$17,$B87*(AC$60),0)) -> 0 | AD87: =IF(AD$63<=$C$17,($C$34*AD$59*$B87/$C$63)*(IF(COUNTA($D87:AC87)*(12/$C$63)<=$C$9,0,1)),0)+IF(AE$63=$C$17,0,IF(AD$63=$C$17,$B87*(AD$60),0)) -> 1.5733333 | AE87: =IF(AE$63<=$C$17,($C$34*AE$59*$B87/$C$63)*(IF(COUNTA($D87:AD87)*(12/$C$63)<=$C$9,0,1)),0)+IF(AF$63=$C$17,0,IF(AE$63=$C$17,$B87*(AE$60),0)) -> 1.5733333 | AF87: =IF(AF$63<=$C$17,($C$34*AF$59*$B87/$C$63)*(IF(COUNTA($D87:AE87)*(12/$C$63)<=$C$9,0,1)),0)+IF(AG$63=$C$17,0,IF(AF$63=$C$17,$B87*(AF$60),0)) -> 1.5733333 | AG87: =IF(AG$63<=$C$17,($C$34*AG$59*$B87/$C$63)*(IF(COUNTA($D87:AF87)*(12/$C$63)<=$C$9,0,1)),0)+IF(AH$63=$C$17,0,IF(AG$63=$C$17,$B87*(AG$60),0)) -> 1.5733333 | ... IW87: =IF(IW$63<=$C$17,($C$34*IW$59*$B87/$C$63)*(IF(COUNTA($D87:IV87)*(12/$C$63)<=$C$9,0,1)),0)+IF(IX$63=$C$17,0,IF(IW$63=$C$17,$B87*(IW$60),0)) -> 0
A88: Versement programmé | B88: =+OFFSET($D$52,0,COUNTA($B$66:B87),,) -> 2 | C88: =SUM(D88:XEG88) -> 128.87055 | Z88: =IF(AA$63>$C$17,0,-Z$53*(12/$C$63)) -> -404 | AA88: =IF(AA$63<=$C$17,($C$34*AA$59*$B88/$C$63)*(IF(COUNTA($D88:Z88)*(12/$C$63)<=$C$9,0,1)),0)+IF(AB$63=$C$17,0,IF(AA$63=$C$17,$B88*(AA$60),0)) -> 0 | AB88: =IF(AB$63<=$C$17,($C$34*AB$59*$B88/$C$63)*(IF(COUNTA($D88:AA88)*(12/$C$63)<=$C$9,0,1)),0)+IF(AC$63=$C$17,0,IF(AB$63=$C$17,$B88*(AB$60),0)) -> 0 | AC88: =IF(AC$63<=$C$17,($C$34*AC$59*$B88/$C$63)*(IF(COUNTA($D88:AB88)*(12/$C$63)<=$C$9,0,1)),0)+IF(AD$63=$C$17,0,IF(AC$63=$C$17,$B88*(AC$60),0)) -> 0 | AD88: =IF(AD$63<=$C$17,($C$34*AD$59*$B88/$C$63)*(IF(COUNTA($D88:AC88)*(12/$C$63)<=$C$9,0,1)),0)+IF(AE$63=$C$17,0,IF(AD$63=$C$17,$B88*(AD$60),0)) -> 0 | AE88: =IF(AE$63<=$C$17,($C$34*AE$59*$B88/$C$63)*(IF(COUNTA($D88:AD88)*(12/$C$63)<=$C$9,0,1)),0)+IF(AF$63=$C$17,0,IF(AE$63=$C$17,$B88*(AE$60),0)) -> 1.5733333 | AF88: =IF(AF$63<=$C$17,($C$34*AF$59*$B88/$C$63)*(IF(COUNTA($D88:AE88)*(12/$C$63)<=$C$9,0,1)),0)+IF(AG$63=$C$17,0,IF(AF$63=$C$17,$B88*(AF$60),0)) -> 1.5733333 | AG88: =IF(AG$63<=$C$17,($C$34*AG$59*$B88/$C$63)*(IF(COUNTA($D88:AF88)*(12/$C$63)<=$C$9,0,1)),0)+IF(AH$63=$C$17,0,IF(AG$63=$C$17,$B88*(AG$60),0)) -> 1.5733333 | AH88: =IF(AH$63<=$C$17,($C$34*AH$59*$B88/$C$63)*(IF(COUNTA($D88:AG88)*(12/$C$63)<=$C$9,0,1)),0)+IF(AI$63=$C$17,0,IF(AH$63=$C$17,$B88*(AH$60),0)) -> 1.5733333 | ... IW88: =IF(IW$63<=$C$17,($C$34*IW$59*$B88/$C$63)*(IF(COUNTA($D88:IV88)*(12/$C$63)<=$C$9,0,1)),0)+IF(IX$63=$C$17,0,IF(IW$63=$C$17,$B88*(IW$60),0)) -> 0
A89: Versement programmé | B89: =+OFFSET($D$52,0,COUNTA($B$66:B88),,) -> 3 | C89: =SUM(D89:XEG89) -> 190.94582 | AA89: =IF(AB$63>$C$17,0,-AA$53*(12/$C$63)) -> -606 | AB89: =IF(AB$63<=$C$17,($C$34*AB$59*$B89/$C$63)*(IF(COUNTA($D89:AA89)*(12/$C$63)<=$C$9,0,1)),0)+IF(AC$63=$C$17,0,IF(AB$63=$C$17,$B89*(AB$60),0)) -> 0 | AC89: =IF(AC$63<=$C$17,($C$34*AC$59*$B89/$C$63)*(IF(COUNTA($D89:AB89)*(12/$C$63)<=$C$9,0,1)),0)+IF(AD$63=$C$17,0,IF(AC$63=$C$17,$B89*(AC$60),0)) -> 0 | AD89: =IF(AD$63<=$C$17,($C$34*AD$59*$B89/$C$63)*(IF(COUNTA($D89:AC89)*(12/$C$63)<=$C$9,0,1)),0)+IF(AE$63=$C$17,0,IF(AD$63=$C$17,$B89*(AD$60),0)) -> 0 | AE89: =IF(AE$63<=$C$17,($C$34*AE$59*$B89/$C$63)*(IF(COUNTA($D89:AD89)*(12/$C$63)<=$C$9,0,1)),0)+IF(AF$63=$C$17,0,IF(AE$63=$C$17,$B89*(AE$60),0)) -> 0 | AF89: =IF(AF$63<=$C$17,($C$34*AF$59*$B89/$C$63)*(IF(COUNTA($D89:AE89)*(12/$C$63)<=$C$9,0,1)),0)+IF(AG$63=$C$17,0,IF(AF$63=$C$17,$B89*(AF$60),0)) -> 2.36 | AG89: =IF(AG$63<=$C$17,($C$34*AG$59*$B89/$C$63)*(IF(COUNTA($D89:AF89)*(12/$C$63)<=$C$9,0,1)),0)+IF(AH$63=$C$17,0,IF(AG$63=$C$17,$B89*(AG$60),0)) -> 2.36 | AH89: =IF(AH$63<=$C$17,($C$34*AH$59*$B89/$C$63)*(IF(COUNTA($D89:AG89)*(12/$C$63)<=$C$9,0,1)),0)+IF(AI$63=$C$17,0,IF(AH$63=$C$17,$B89*(AH$60),0)) -> 2.36 | AI89: =IF(AI$63<=$C$17,($C$34*AI$59*$B89/$C$63)*(IF(COUNTA($D89:AH89)*(12/$C$63)<=$C$9,0,1)),0)+IF(AJ$63=$C$17,0,IF(AI$63=$C$17,$B89*(AI$60),0)) -> 2.36 | ... IW89: =IF(IW$63<=$C$17,($C$34*IW$59*$B89/$C$63)*(IF(COUNTA($D89:IV89)*(12/$C$63)<=$C$9,0,1)),0)+IF(IX$63=$C$17,0,IF(IW$63=$C$17,$B89*(IW$60),0)) -> 0
A90: Versement programmé | B90: =+OFFSET($D$52,0,COUNTA($B$66:B89),,) -> 2 | C90: =SUM(D90:XEG90) -> 125.72388 | AB90: =IF(AC$63>$C$17,0,-AB$53*(12/$C$63)) -> -404 | AC90: =IF(AC$63<=$C$17,($C$34*AC$59*$B90/$C$63)*(IF(COUNTA($D90:AB90)*(12/$C$63)<=$C$9,0,1)),0)+IF(AD$63=$C$17,0,IF(AC$63=$C$17,$B90*(AC$60),0)) -> 0 | AD90: =IF(AD$63<=$C$17,($C$34*AD$59*$B90/$C$63)*(IF(COUNTA($D90:AC90)*(12/$C$63)<=$C$9,0,1)),0)+IF(AE$63=$C$17,0,IF(AD$63=$C$17,$B90*(AD$60),0)) -> 0 | AE90: =IF(AE$63<=$C$17,($C$34*AE$59*$B90/$C$63)*(IF(COUNTA($D90:AD90)*(12/$C$63)<=$C$9,0,1)),0)+IF(AF$63=$C$17,0,IF(AE$63=$C$17,$B90*(AE$60),0)) -> 0 | AF90: =IF(AF$63<=$C$17,($C$34*AF$59*$B90/$C$63)*(IF(COUNTA($D90:AE90)*(12/$C$63)<=$C$9,0,1)),0)+IF(AG$63=$C$17,0,IF(AF$63=$C$17,$B90*(AF$60),0)) -> 0 | AG90: =IF(AG$63<=$C$17,($C$34*AG$59*$B90/$C$63)*(IF(COUNTA($D90:AF90)*(12/$C$63)<=$C$9,0,1)),0)+IF(AH$63=$C$17,0,IF(AG$63=$C$17,$B90*(AG$60),0)) -> 1.5733333 | AH90: =IF(AH$63<=$C$17,($C$34*AH$59*$B90/$C$63)*(IF(COUNTA($D90:AG90)*(12/$C$63)<=$C$9,0,1)),0)+IF(AI$63=$C$17,0,IF(AH$63=$C$17,$B90*(AH$60),0)) -> 1.5733333 | AI90: =IF(AI$63<=$C$17,($C$34*AI$59*$B90/$C$63)*(IF(COUNTA($D90:AH90)*(12/$C$63)<=$C$9,0,1)),0)+IF(AJ$63=$C$17,0,IF(AI$63=$C$17,$B90*(AI$60),0)) -> 1.5733333 | AJ90: =IF(AJ$63<=$C$17,($C$34*AJ$59*$B90/$C$63)*(IF(COUNTA($D90:AI90)*(12/$C$63)<=$C$9,0,1)),0)+IF(AK$63=$C$17,0,IF(AJ$63=$C$17,$B90*(AJ$60),0)) -> 1.5733333 | ... IW90: =IF(IW$63<=$C$17,($C$34*IW$59*$B90/$C$63)*(IF(COUNTA($D90:IV90)*(12/$C$63)<=$C$9,0,1)),0)+IF(IX$63=$C$17,0,IF(IW$63=$C$17,$B90*(IW$60),0)) -> 0
A91: Versement programmé | B91: =+OFFSET($D$52,0,COUNTA($B$66:B90),,) -> 2 | C91: =SUM(D91:XEG91) -> 120.11055 | AC91: =IF(AD$63>$C$17,0,-AC$53*(12/$C$63)) -> -408.04 | AD91: =IF(AD$63<=$C$17,($C$34*AD$59*$B91/$C$63)*(IF(COUNTA($D91:AC91)*(12/$C$63)<=$C$9,0,1)),0)+IF(AE$63=$C$17,0,IF(AD$63=$C$17,$B91*(AD$60),0)) -> 0 | AE91: =IF(AE$63<=$C$17,($C$34*AE$59*$B91/$C$63)*(IF(COUNTA($D91:AD91)*(12/$C$63)<=$C$9,0,1)),0)+IF(AF$63=$C$17,0,IF(AE$63=$C$17,$B91*(AE$60),0)) -> 0 | AF91: =IF(AF$63<=$C$17,($C$34*AF$59*$B91/$C$63)*(IF(COUNTA($D91:AE91)*(12/$C$63)<=$C$9,0,1)),0)+IF(AG$63=$C$17,0,IF(AF$63=$C$17,$B91*(AF$60),0)) -> 0 | AG91: =IF(AG$63<=$C$17,($C$34*AG$59*$B91/$C$63)*(IF(COUNTA($D91:AF91)*(12/$C$63)<=$C$9,0,1)),0)+IF(AH$63=$C$17,0,IF(AG$63=$C$17,$B91*(AG$60),0)) -> 0 | AH91: =IF(AH$63<=$C$17,($C$34*AH$59*$B91/$C$63)*(IF(COUNTA($D91:AG91)*(12/$C$63)<=$C$9,0,1)),0)+IF(AI$63=$C$17,0,IF(AH$63=$C$17,$B91*(AH$60),0)) -> 1.5733333 | AI91: =IF(AI$63<=$C$17,($C$34*AI$59*$B91/$C$63)*(IF(COUNTA($D91:AH91)*(12/$C$63)<=$C$9,0,1)),0)+IF(AJ$63=$C$17,0,IF(AI$63=$C$17,$B91*(AI$60),0)) -> 1.5733333 | AJ91: =IF(AJ$63<=$C$17,($C$34*AJ$59*$B91/$C$63)*(IF(COUNTA($D91:AI91)*(12/$C$63)<=$C$9,0,1)),0)+IF(AK$63=$C$17,0,IF(AJ$63=$C$17,$B91*(AJ$60),0)) -> 1.5733333 | AK91: =IF(AK$63<=$C$17,($C$34*AK$59*$B91/$C$63)*(IF(COUNTA($D91:AJ91)*(12/$C$63)<=$C$9,0,1)),0)+IF(AL$63=$C$17,0,IF(AK$63=$C$17,$B91*(AK$60),0)) -> 1.5733333 | ... IW91: =IF(IW$63<=$C$17,($C$34*IW$59*$B91/$C$63)*(IF(COUNTA($D91:IV91)*(12/$C$63)<=$C$9,0,1)),0)+IF(IX$63=$C$17,0,IF(IW$63=$C$17,$B91*(IW$60),0)) -> 0
A92: Versement programmé | B92: =+OFFSET($D$52,0,COUNTA($B$66:B91),,) -> 3 | C92: =SUM(D92:XEG92) -> 177.80582 | AD92: =IF(AE$63>$C$17,0,-AD$53*(12/$C$63)) -> -612.06 | AE92: =IF(AE$63<=$C$17,($C$34*AE$59*$B92/$C$63)*(IF(COUNTA($D92:AD92)*(12/$C$63)<=$C$9,0,1)),0)+IF(AF$63=$C$17,0,IF(AE$63=$C$17,$B92*(AE$60),0)) -> 0 | AF92: =IF(AF$63<=$C$17,($C$34*AF$59*$B92/$C$63)*(IF(COUNTA($D92:AE92)*(12/$C$63)<=$C$9,0,1)),0)+IF(AG$63=$C$17,0,IF(AF$63=$C$17,$B92*(AF$60),0)) -> 0 | AG92: =IF(AG$63<=$C$17,($C$34*AG$59*$B92/$C$63)*(IF(COUNTA($D92:AF92)*(12/$C$63)<=$C$9,0,1)),0)+IF(AH$63=$C$17,0,IF(AG$63=$C$17,$B92*(AG$60),0)) -> 0 | AH92: =IF(AH$63<=$C$17,($C$34*AH$59*$B92/$C$63)*(IF(COUNTA($D92:AG92)*(12/$C$63)<=$C$9,0,1)),0)+IF(AI$63=$C$17,0,IF(AH$63=$C$17,$B92*(AH$60),0)) -> 0 | AI92: =IF(AI$63<=$C$17,($C$34*AI$59*$B92/$C$63)*(IF(COUNTA($D92:AH92)*(12/$C$63)<=$C$9,0,1)),0)+IF(AJ$63=$C$17,0,IF(AI$63=$C$17,$B92*(AI$60),0)) -> 2.36 | AJ92: =IF(AJ$63<=$C$17,($C$34*AJ$59*$B92/$C$63)*(IF(COUNTA($D92:AI92)*(12/$C$63)<=$C$9,0,1)),0)+IF(AK$63=$C$17,0,IF(AJ$63=$C$17,$B92*(AJ$60),0)) -> 2.36 | AK92: =IF(AK$63<=$C$17,($C$34*AK$59*$B92/$C$63)*(IF(COUNTA($D92:AJ92)*(12/$C$63)<=$C$9,0,1)),0)+IF(AL$63=$C$17,0,IF(AK$63=$C$17,$B92*(AK$60),0)) -> 2.36 | AL92: =IF(AL$63<=$C$17,($C$34*AL$59*$B92/$C$63)*(IF(COUNTA($D92:AK92)*(12/$C$63)<=$C$9,0,1)),0)+IF(AM$63=$C$17,0,IF(AL$63=$C$17,$B92*(AL$60),0)) -> 2.36 | ... IW92: =IF(IW$63<=$C$17,($C$34*IW$59*$B92/$C$63)*(IF(COUNTA($D92:IV92)*(12/$C$63)<=$C$9,0,1)),0)+IF(IX$63=$C$17,0,IF(IW$63=$C$17,$B92*(IW$60),0)) -> 0
A93: Versement programmé | B93: =+OFFSET($D$52,0,COUNTA($B$66:B92),,) -> 2 | C93: =SUM(D93:XEG93) -> 116.96388 | AE93: =IF(AF$63>$C$17,0,-AE$53*(12/$C$63)) -> -408.04 | AF93: =IF(AF$63<=$C$17,($C$34*AF$59*$B93/$C$63)*(IF(COUNTA($D93:AE93)*(12/$C$63)<=$C$9,0,1)),0)+IF(AG$63=$C$17,0,IF(AF$63=$C$17,$B93*(AF$60),0)) -> 0 | AG93: =IF(AG$63<=$C$17,($C$34*AG$59*$B93/$C$63)*(IF(COUNTA($D93:AF93)*(12/$C$63)<=$C$9,0,1)),0)+IF(AH$63=$C$17,0,IF(AG$63=$C$17,$B93*(AG$60),0)) -> 0 | AH93: =IF(AH$63<=$C$17,($C$34*AH$59*$B93/$C$63)*(IF(COUNTA($D93:AG93)*(12/$C$63)<=$C$9,0,1)),0)+IF(AI$63=$C$17,0,IF(AH$63=$C$17,$B93*(AH$60),0)) -> 0 | AI93: =IF(AI$63<=$C$17,($C$34*AI$59*$B93/$C$63)*(IF(COUNTA($D93:AH93)*(12/$C$63)<=$C$9,0,1)),0)+IF(AJ$63=$C$17,0,IF(AI$63=$C$17,$B93*(AI$60),0)) -> 0 | AJ93: =IF(AJ$63<=$C$17,($C$34*AJ$59*$B93/$C$63)*(IF(COUNTA($D93:AI93)*(12/$C$63)<=$C$9,0,1)),0)+IF(AK$63=$C$17,0,IF(AJ$63=$C$17,$B93*(AJ$60),0)) -> 1.5733333 | AK93: =IF(AK$63<=$C$17,($C$34*AK$59*$B93/$C$63)*(IF(COUNTA($D93:AJ93)*(12/$C$63)<=$C$9,0,1)),0)+IF(AL$63=$C$17,0,IF(AK$63=$C$17,$B93*(AK$60),0)) -> 1.5733333 | AL93: =IF(AL$63<=$C$17,($C$34*AL$59*$B93/$C$63)*(IF(COUNTA($D93:AK93)*(12/$C$63)<=$C$9,0,1)),0)+IF(AM$63=$C$17,0,IF(AL$63=$C$17,$B93*(AL$60),0)) -> 1.5733333 | AM93: =IF(AM$63<=$C$17,($C$34*AM$59*$B93/$C$63)*(IF(COUNTA($D93:AL93)*(12/$C$63)<=$C$9,0,1)),0)+IF(AN$63=$C$17,0,IF(AM$63=$C$17,$B93*(AM$60),0)) -> 1.5733333 | ... IW93: =IF(IW$63<=$C$17,($C$34*IW$59*$B93/$C$63)*(IF(COUNTA($D93:IV93)*(12/$C$63)<=$C$9,0,1)),0)+IF(IX$63=$C$17,0,IF(IW$63=$C$17,$B93*(IW$60),0)) -> 0
A94: Versement programmé | B94: =+OFFSET($D$52,0,COUNTA($B$66:B93),,) -> 2 | C94: =SUM(D94:XEG94) -> 115.39055 | AF94: =IF(AG$63>$C$17,0,-AF$53*(12/$C$63)) -> -408.04 | AG94: =IF(AG$63<=$C$17,($C$34*AG$59*$B94/$C$63)*(IF(COUNTA($D94:AF94)*(12/$C$63)<=$C$9,0,1)),0)+IF(AH$63=$C$17,0,IF(AG$63=$C$17,$B94*(AG$60),0)) -> 0 | AH94: =IF(AH$63<=$C$17,($C$34*AH$59*$B94/$C$63)*(IF(COUNTA($D94:AG94)*(12/$C$63)<=$C$9,0,1)),0)+IF(AI$63=$C$17,0,IF(AH$63=$C$17,$B94*(AH$60),0)) -> 0 | AI94: =IF(AI$63<=$C$17,($C$34*AI$59*$B94/$C$63)*(IF(COUNTA($D94:AH94)*(12/$C$63)<=$C$9,0,1)),0)+IF(AJ$63=$C$17,0,IF(AI$63=$C$17,$B94*(AI$60),0)) -> 0 | AJ94: =IF(AJ$63<=$C$17,($C$34*AJ$59*$B94/$C$63)*(IF(COUNTA($D94:AI94)*(12/$C$63)<=$C$9,0,1)),0)+IF(AK$63=$C$17,0,IF(AJ$63=$C$17,$B94*(AJ$60),0)) -> 0 | AK94: =IF(AK$63<=$C$17,($C$34*AK$59*$B94/$C$63)*(IF(COUNTA($D94:AJ94)*(12/$C$63)<=$C$9,0,1)),0)+IF(AL$63=$C$17,0,IF(AK$63=$C$17,$B94*(AK$60),0)) -> 1.5733333 | AL94: =IF(AL$63<=$C$17,($C$34*AL$59*$B94/$C$63)*(IF(COUNTA($D94:AK94)*(12/$C$63)<=$C$9,0,1)),0)+IF(AM$63=$C$17,0,IF(AL$63=$C$17,$B94*(AL$60),0)) -> 1.5733333 | AM94: =IF(AM$63<=$C$17,($C$34*AM$59*$B94/$C$63)*(IF(COUNTA($D94:AL94)*(12/$C$63)<=$C$9,0,1)),0)+IF(AN$63=$C$17,0,IF(AM$63=$C$17,$B94*(AM$60),0)) -> 1.5733333 | AN94: =IF(AN$63<=$C$17,($C$34*AN$59*$B94/$C$63)*(IF(COUNTA($D94:AM94)*(12/$C$63)<=$C$9,0,1)),0)+IF(AO$63=$C$17,0,IF(AN$63=$C$17,$B94*(AN$60),0)) -> 1.5733333 | ... IW94: =IF(IW$63<=$C$17,($C$34*IW$59*$B94/$C$63)*(IF(COUNTA($D94:IV94)*(12/$C$63)<=$C$9,0,1)),0)+IF(IX$63=$C$17,0,IF(IW$63=$C$17,$B94*(IW$60),0)) -> 0
A95: Versement programmé | B95: =+OFFSET($D$52,0,COUNTA($B$66:B94),,) -> 3 | C95: =SUM(D95:XEG95) -> 170.72582 | AG95: =IF(AH$63>$C$17,0,-AG$53*(12/$C$63)) -> -612.06 | AH95: =IF(AH$63<=$C$17,($C$34*AH$59*$B95/$C$63)*(IF(COUNTA($D95:AG95)*(12/$C$63)<=$C$9,0,1)),0)+IF(AI$63=$C$17,0,IF(AH$63=$C$17,$B95*(AH$60),0)) -> 0 | AI95: =IF(AI$63<=$C$17,($C$34*AI$59*$B95/$C$63)*(IF(COUNTA($D95:AH95)*(12/$C$63)<=$C$9,0,1)),0)+IF(AJ$63=$C$17,0,IF(AI$63=$C$17,$B95*(AI$60),0)) -> 0 | AJ95: =IF(AJ$63<=$C$17,($C$34*AJ$59*$B95/$C$63)*(IF(COUNTA($D95:AI95)*(12/$C$63)<=$C$9,0,1)),0)+IF(AK$63=$C$17,0,IF(AJ$63=$C$17,$B95*(AJ$60),0)) -> 0 | AK95: =IF(AK$63<=$C$17,($C$34*AK$59*$B95/$C$63)*(IF(COUNTA($D95:AJ95)*(12/$C$63)<=$C$9,0,1)),0)+IF(AL$63=$C$17,0,IF(AK$63=$C$17,$B95*(AK$60),0)) -> 0 | AL95: =IF(AL$63<=$C$17,($C$34*AL$59*$B95/$C$63)*(IF(COUNTA($D95:AK95)*(12/$C$63)<=$C$9,0,1)),0)+IF(AM$63=$C$17,0,IF(AL$63=$C$17,$B95*(AL$60),0)) -> 2.36 | AM95: =IF(AM$63<=$C$17,($C$34*AM$59*$B95/$C$63)*(IF(COUNTA($D95:AL95)*(12/$C$63)<=$C$9,0,1)),0)+IF(AN$63=$C$17,0,IF(AM$63=$C$17,$B95*(AM$60),0)) -> 2.36 | AN95: =IF(AN$63<=$C$17,($C$34*AN$59*$B95/$C$63)*(IF(COUNTA($D95:AM95)*(12/$C$63)<=$C$9,0,1)),0)+IF(AO$63=$C$17,0,IF(AN$63=$C$17,$B95*(AN$60),0)) -> 2.36 | AO95: =IF(AO$63<=$C$17,($C$34*AO$59*$B95/$C$63)*(IF(COUNTA($D95:AN95)*(12/$C$63)<=$C$9,0,1)),0)+IF(AP$63=$C$17,0,IF(AO$63=$C$17,$B95*(AO$60),0)) -> 2.36 | ... IW95: =IF(IW$63<=$C$17,($C$34*IW$59*$B95/$C$63)*(IF(COUNTA($D95:IV95)*(12/$C$63)<=$C$9,0,1)),0)+IF(IX$63=$C$17,0,IF(IW$63=$C$17,$B95*(IW$60),0)) -> 0
A96: Versement programmé | B96: =+OFFSET($D$52,0,COUNTA($B$66:B95),,) -> 2 | C96: =SUM(D96:XEG96) -> 112.24388 | AH96: =IF(AI$63>$C$17,0,-AH$53*(12/$C$63)) -> -408.04 | AI96: =IF(AI$63<=$C$17,($C$34*AI$59*$B96/$C$63)*(IF(COUNTA($D96:AH96)*(12/$C$63)<=$C$9,0,1)),0)+IF(AJ$63=$C$17,0,IF(AI$63=$C$17,$B96*(AI$60),0)) -> 0 | AJ96: =IF(AJ$63<=$C$17,($C$34*AJ$59*$B96/$C$63)*(IF(COUNTA($D96:AI96)*(12/$C$63)<=$C$9,0,1)),0)+IF(AK$63=$C$17,0,IF(AJ$63=$C$17,$B96*(AJ$60),0)) -> 0 | AK96: =IF(AK$63<=$C$17,($C$34*AK$59*$B96/$C$63)*(IF(COUNTA($D96:AJ96)*(12/$C$63)<=$C$9,0,1)),0)+IF(AL$63=$C$17,0,IF(AK$63=$C$17,$B96*(AK$60),0)) -> 0 | AL96: =IF(AL$63<=$C$17,($C$34*AL$59*$B96/$C$63)*(IF(COUNTA($D96:AK96)*(12/$C$63)<=$C$9,0,1)),0)+IF(AM$63=$C$17,0,IF(AL$63=$C$17,$B96*(AL$60),0)) -> 0 | AM96: =IF(AM$63<=$C$17,($C$34*AM$59*$B96/$C$63)*(IF(COUNTA($D96:AL96)*(12/$C$63)<=$C$9,0,1)),0)+IF(AN$63=$C$17,0,IF(AM$63=$C$17,$B96*(AM$60),0)) -> 1.5733333 | AN96: =IF(AN$63<=$C$17,($C$34*AN$59*$B96/$C$63)*(IF(COUNTA($D96:AM96)*(12/$C$63)<=$C$9,0,1)),0)+IF(AO$63=$C$17,0,IF(AN$63=$C$17,$B96*(AN$60),0)) -> 1.5733333 | AO96: =IF(AO$63<=$C$17,($C$34*AO$59*$B96/$C$63)*(IF(COUNTA($D96:AN96)*(12/$C$63)<=$C$9,0,1)),0)+IF(AP$63=$C$17,0,IF(AO$63=$C$17,$B96*(AO$60),0)) -> 1.5733333 | AP96: =IF(AP$63<=$C$17,($C$34*AP$59*$B96/$C$63)*(IF(COUNTA($D96:AO96)*(12/$C$63)<=$C$9,0,1)),0)+IF(AQ$63=$C$17,0,IF(AP$63=$C$17,$B96*(AP$60),0)) -> 1.5733333 | ... IW96: =IF(IW$63<=$C$17,($C$34*IW$59*$B96/$C$63)*(IF(COUNTA($D96:IV96)*(12/$C$63)<=$C$9,0,1)),0)+IF(IX$63=$C$17,0,IF(IW$63=$C$17,$B96*(IW$60),0)) -> 0
A97: Versement programmé | B97: =+OFFSET($D$52,0,COUNTA($B$66:B96),,) -> 3 | C97: =SUM(D97:XEG97) -> 166.00582 | AI97: =IF(AJ$63>$C$17,0,-AI$53*(12/$C$63)) -> -612.06 | AJ97: =IF(AJ$63<=$C$17,($C$34*AJ$59*$B97/$C$63)*(IF(COUNTA($D97:AI97)*(12/$C$63)<=$C$9,0,1)),0)+IF(AK$63=$C$17,0,IF(AJ$63=$C$17,$B97*(AJ$60),0)) -> 0 | AK97: =IF(AK$63<=$C$17,($C$34*AK$59*$B97/$C$63)*(IF(COUNTA($D97:AJ97)*(12/$C$63)<=$C$9,0,1)),0)+IF(AL$63=$C$17,0,IF(AK$63=$C$17,$B97*(AK$60),0)) -> 0 | AL97: =IF(AL$63<=$C$17,($C$34*AL$59*$B97/$C$63)*(IF(COUNTA($D97:AK97)*(12/$C$63)<=$C$9,0,1)),0)+IF(AM$63=$C$17,0,IF(AL$63=$C$17,$B97*(AL$60),0)) -> 0 | AM97: =IF(AM$63<=$C$17,($C$34*AM$59*$B97/$C$63)*(IF(COUNTA($D97:AL97)*(12/$C$63)<=$C$9,0,1)),0)+IF(AN$63=$C$17,0,IF(AM$63=$C$17,$B97*(AM$60),0)) -> 0 | AN97: =IF(AN$63<=$C$17,($C$34*AN$59*$B97/$C$63)*(IF(COUNTA($D97:AM97)*(12/$C$63)<=$C$9,0,1)),0)+IF(AO$63=$C$17,0,IF(AN$63=$C$17,$B97*(AN$60),0)) -> 2.36 | AO97: =IF(AO$63<=$C$17,($C$34*AO$59*$B97/$C$63)*(IF(COUNTA($D97:AN97)*(12/$C$63)<=$C$9,0,1)),0)+IF(AP$63=$C$17,0,IF(AO$63=$C$17,$B97*(AO$60),0)) -> 2.36 | AP97: =IF(AP$63<=$C$17,($C$34*AP$59*$B97/$C$63)*(IF(COUNTA($D97:AO97)*(12/$C$63)<=$C$9,0,1)),0)+IF(AQ$63=$C$17,0,IF(AP$63=$C$17,$B97*(AP$60),0)) -> 2.36 | AQ97: =IF(AQ$63<=$C$17,($C$34*AQ$59*$B97/$C$63)*(IF(COUNTA($D97:AP97)*(12/$C$63)<=$C$9,0,1)),0)+IF(AR$63=$C$17,0,IF(AQ$63=$C$17,$B97*(AQ$60),0)) -> 2.36 | ... IW97: =IF(IW$63<=$C$17,($C$34*IW$59*$B97/$C$63)*(IF(COUNTA($D97:IV97)*(12/$C$63)<=$C$9,0,1)),0)+IF(IX$63=$C$17,0,IF(IW$63=$C$17,$B97*(IW$60),0)) -> 0
A98: Versement programmé | B98: =+OFFSET($D$52,0,COUNTA($B$66:B97),,) -> 2 | C98: =SUM(D98:XEG98) -> 109.09722 | AJ98: =IF(AK$63>$C$17,0,-AJ$53*(12/$C$63)) -> -408.04 | AK98: =IF(AK$63<=$C$17,($C$34*AK$59*$B98/$C$63)*(IF(COUNTA($D98:AJ98)*(12/$C$63)<=$C$9,0,1)),0)+IF(AL$63=$C$17,0,IF(AK$63=$C$17,$B98*(AK$60),0)) -> 0 | AL98: =IF(AL$63<=$C$17,($C$34*AL$59*$B98/$C$63)*(IF(COUNTA($D98:AK98)*(12/$C$63)<=$C$9,0,1)),0)+IF(AM$63=$C$17,0,IF(AL$63=$C$17,$B98*(AL$60),0)) -> 0 | AM98: =IF(AM$63<=$C$17,($C$34*AM$59*$B98/$C$63)*(IF(COUNTA($D98:AL98)*(12/$C$63)<=$C$9,0,1)),0)+IF(AN$63=$C$17,0,IF(AM$63=$C$17,$B98*(AM$60),0)) -> 0 | AN98: =IF(AN$63<=$C$17,($C$34*AN$59*$B98/$C$63)*(IF(COUNTA($D98:AM98)*(12/$C$63)<=$C$9,0,1)),0)+IF(AO$63=$C$17,0,IF(AN$63=$C$17,$B98*(AN$60),0)) -> 0 | AO98: =IF(AO$63<=$C$17,($C$34*AO$59*$B98/$C$63)*(IF(COUNTA($D98:AN98)*(12/$C$63)<=$C$9,0,1)),0)+IF(AP$63=$C$17,0,IF(AO$63=$C$17,$B98*(AO$60),0)) -> 1.5733333 | AP98: =IF(AP$63<=$C$17,($C$34*AP$59*$B98/$C$63)*(IF(COUNTA($D98:AO98)*(12/$C$63)<=$C$9,0,1)),0)+IF(AQ$63=$C$17,0,IF(AP$63=$C$17,$B98*(AP$60),0)) -> 1.5733333 | AQ98: =IF(AQ$63<=$C$17,($C$34*AQ$59*$B98/$C$63)*(IF(COUNTA($D98:AP98)*(12/$C$63)<=$C$9,0,1)),0)+IF(AR$63=$C$17,0,IF(AQ$63=$C$17,$B98*(AQ$60),0)) -> 1.5733333 | AR98: =IF(AR$63<=$C$17,($C$34*AR$59*$B98/$C$63)*(IF(COUNTA($D98:AQ98)*(12/$C$63)<=$C$9,0,1)),0)+IF(AS$63=$C$17,0,IF(AR$63=$C$17,$B98*(AR$60),0)) -> 1.5733333 | ... IW98: =IF(IW$63<=$C$17,($C$34*IW$59*$B98/$C$63)*(IF(COUNTA($D98:IV98)*(12/$C$63)<=$C$9,0,1)),0)+IF(IX$63=$C$17,0,IF(IW$63=$C$17,$B98*(IW$60),0)) -> 0
A99: Versement programmé | B99: =+OFFSET($D$52,0,COUNTA($B$66:B98),,) -> 3 | C99: =SUM(D99:XEG99) -> 161.28582 | AK99: =IF(AL$63>$C$17,0,-AK$53*(12/$C$63)) -> -612.06 | AL99: =IF(AL$63<=$C$17,($C$34*AL$59*$B99/$C$63)*(IF(COUNTA($D99:AK99)*(12/$C$63)<=$C$9,0,1)),0)+IF(AM$63=$C$17,0,IF(AL$63=$C$17,$B99*(AL$60),0)) -> 0 | AM99: =IF(AM$63<=$C$17,($C$34*AM$59*$B99/$C$63)*(IF(COUNTA($D99:AL99)*(12/$C$63)<=$C$9,0,1)),0)+IF(AN$63=$C$17,0,IF(AM$63=$C$17,$B99*(AM$60),0)) -> 0 | AN99: =IF(AN$63<=$C$17,($C$34*AN$59*$B99/$C$63)*(IF(COUNTA($D99:AM99)*(12/$C$63)<=$C$9,0,1)),0)+IF(AO$63=$C$17,0,IF(AN$63=$C$17,$B99*(AN$60),0)) -> 0 | AO99: =IF(AO$63<=$C$17,($C$34*AO$59*$B99/$C$63)*(IF(COUNTA($D99:AN99)*(12/$C$63)<=$C$9,0,1)),0)+IF(AP$63=$C$17,0,IF(AO$63=$C$17,$B99*(AO$60),0)) -> 0 | AP99: =IF(AP$63<=$C$17,($C$34*AP$59*$B99/$C$63)*(IF(COUNTA($D99:AO99)*(12/$C$63)<=$C$9,0,1)),0)+IF(AQ$63=$C$17,0,IF(AP$63=$C$17,$B99*(AP$60),0)) -> 2.36 | AQ99: =IF(AQ$63<=$C$17,($C$34*AQ$59*$B99/$C$63)*(IF(COUNTA($D99:AP99)*(12/$C$63)<=$C$9,0,1)),0)+IF(AR$63=$C$17,0,IF(AQ$63=$C$17,$B99*(AQ$60),0)) -> 2.36 | AR99: =IF(AR$63<=$C$17,($C$34*AR$59*$B99/$C$63)*(IF(COUNTA($D99:AQ99)*(12/$C$63)<=$C$9,0,1)),0)+IF(AS$63=$C$17,0,IF(AR$63=$C$17,$B99*(AR$60),0)) -> 2.36 | AS99: =IF(AS$63<=$C$17,($C$34*AS$59*$B99/$C$63)*(IF(COUNTA($D99:AR99)*(12/$C$63)<=$C$9,0,1)),0)+IF(AT$63=$C$17,0,IF(AS$63=$C$17,$B99*(AS$60),0)) -> 2.36 | ... IW99: =IF(IW$63<=$C$17,($C$34*IW$59*$B99/$C$63)*(IF(COUNTA($D99:IV99)*(12/$C$63)<=$C$9,0,1)),0)+IF(IX$63=$C$17,0,IF(IW$63=$C$17,$B99*(IW$60),0)) -> 0
A100: Versement programmé | B100: =+OFFSET($D$52,0,COUNTA($B$66:B99),,) -> 2 | C100: =SUM(D100:XEG100) -> 105.95055 | AL100: =IF(AM$63>$C$17,0,-AL$53*(12/$C$63)) -> -408.04 | AM100: =IF(AM$63<=$C$17,($C$34*AM$59*$B100/$C$63)*(IF(COUNTA($D100:AL100)*(12/$C$63)<=$C$9,0,1)),0)+IF(AN$63=$C$17,0,IF(AM$63=$C$17,$B100*(AM$60),0)) -> 0 | AN100: =IF(AN$63<=$C$17,($C$34*AN$59*$B100/$C$63)*(IF(COUNTA($D100:AM100)*(12/$C$63)<=$C$9,0,1)),0)+IF(AO$63=$C$17,0,IF(AN$63=$C$17,$B100*(AN$60),0)) -> 0 | AO100: =IF(AO$63<=$C$17,($C$34*AO$59*$B100/$C$63)*(IF(COUNTA($D100:AN100)*(12/$C$63)<=$C$9,0,1)),0)+IF(AP$63=$C$17,0,IF(AO$63=$C$17,$B100*(AO$60),0)) -> 0 | AP100: =IF(AP$63<=$C$17,($C$34*AP$59*$B100/$C$63)*(IF(COUNTA($D100:AO100)*(12/$C$63)<=$C$9,0,1)),0)+IF(AQ$63=$C$17,0,IF(AP$63=$C$17,$B100*(AP$60),0)) -> 0 | AQ100: =IF(AQ$63<=$C$17,($C$34*AQ$59*$B100/$C$63)*(IF(COUNTA($D100:AP100)*(12/$C$63)<=$C$9,0,1)),0)+IF(AR$63=$C$17,0,IF(AQ$63=$C$17,$B100*(AQ$60),0)) -> 1.5733333 | AR100: =IF(AR$63<=$C$17,($C$34*AR$59*$B100/$C$63)*(IF(COUNTA($D100:AQ100)*(12/$C$63)<=$C$9,0,1)),0)+IF(AS$63=$C$17,0,IF(AR$63=$C$17,$B100*(AR$60),0)) -> 1.5733333 | AS100: =IF(AS$63<=$C$17,($C$34*AS$59*$B100/$C$63)*(IF(COUNTA($D100:AR100)*(12/$C$63)<=$C$9,0,1)),0)+IF(AT$63=$C$17,0,IF(AS$63=$C$17,$B100*(AS$60),0)) -> 1.5733333 | AT100: =IF(AT$63<=$C$17,($C$34*AT$59*$B100/$C$63)*(IF(COUNTA($D100:AS100)*(12/$C$63)<=$C$9,0,1)),0)+IF(AU$63=$C$17,0,IF(AT$63=$C$17,$B100*(AT$60),0)) -> 1.5733333 | ... IW100: =IF(IW$63<=$C$17,($C$34*IW$59*$B100/$C$63)*(IF(COUNTA($D100:IV100)*(12/$C$63)<=$C$9,0,1)),0)+IF(IX$63=$C$17,0,IF(IW$63=$C$17,$B100*(IW$60),0)) -> 0
A101: Versement programmé | B101: =+OFFSET($D$52,0,COUNTA($B$66:B100),,) -> 2 | C101: =SUM(D101:XEG101) -> 104.37722 | AM101: =IF(AN$63>$C$17,0,-AM$53*(12/$C$63)) -> -408.04 | AN101: =IF(AN$63<=$C$17,($C$34*AN$59*$B101/$C$63)*(IF(COUNTA($D101:AM101)*(12/$C$63)<=$C$9,0,1)),0)+IF(AO$63=$C$17,0,IF(AN$63=$C$17,$B101*(AN$60),0)) -> 0 | AO101: =IF(AO$63<=$C$17,($C$34*AO$59*$B101/$C$63)*(IF(COUNTA($D101:AN101)*(12/$C$63)<=$C$9,0,1)),0)+IF(AP$63=$C$17,0,IF(AO$63=$C$17,$B101*(AO$60),0)) -> 0 | AP101: =IF(AP$63<=$C$17,($C$34*AP$59*$B101/$C$63)*(IF(COUNTA($D101:AO101)*(12/$C$63)<=$C$9,0,1)),0)+IF(AQ$63=$C$17,0,IF(AP$63=$C$17,$B101*(AP$60),0)) -> 0 | AQ101: =IF(AQ$63<=$C$17,($C$34*AQ$59*$B101/$C$63)*(IF(COUNTA($D101:AP101)*(12/$C$63)<=$C$9,0,1)),0)+IF(AR$63=$C$17,0,IF(AQ$63=$C$17,$B101*(AQ$60),0)) -> 0 | AR101: =IF(AR$63<=$C$17,($C$34*AR$59*$B101/$C$63)*(IF(COUNTA($D101:AQ101)*(12/$C$63)<=$C$9,0,1)),0)+IF(AS$63=$C$17,0,IF(AR$63=$C$17,$B101*(AR$60),0)) -> 1.5733333 | AS101: =IF(AS$63<=$C$17,($C$34*AS$59*$B101/$C$63)*(IF(COUNTA($D101:AR101)*(12/$C$63)<=$C$9,0,1)),0)+IF(AT$63=$C$17,0,IF(AS$63=$C$17,$B101*(AS$60),0)) -> 1.5733333 | AT101: =IF(AT$63<=$C$17,($C$34*AT$59*$B101/$C$63)*(IF(COUNTA($D101:AS101)*(12/$C$63)<=$C$9,0,1)),0)+IF(AU$63=$C$17,0,IF(AT$63=$C$17,$B101*(AT$60),0)) -> 1.5733333 | AU101: =IF(AU$63<=$C$17,($C$34*AU$59*$B101/$C$63)*(IF(COUNTA($D101:AT101)*(12/$C$63)<=$C$9,0,1)),0)+IF(AV$63=$C$17,0,IF(AU$63=$C$17,$B101*(AU$60),0)) -> 1.5733333 | ... IW101: =IF(IW$63<=$C$17,($C$34*IW$59*$B101/$C$63)*(IF(COUNTA($D101:IV101)*(12/$C$63)<=$C$9,0,1)),0)+IF(IX$63=$C$17,0,IF(IW$63=$C$17,$B101*(IW$60),0)) -> 0
A102: Versement programmé | B102: =+OFFSET($D$52,0,COUNTA($B$66:B101),,) -> 3 | C102: =SUM(D102:XEG102) -> 154.20582 | AN102: =IF(AO$63>$C$17,0,-AN$53*(12/$C$63)) -> -612.06 | AO102: =IF(AO$63<=$C$17,($C$34*AO$59*$B102/$C$63)*(IF(COUNTA($D102:AN102)*(12/$C$63)<=$C$9,0,1)),0)+IF(AP$63=$C$17,0,IF(AO$63=$C$17,$B102*(AO$60),0)) -> 0 | AP102: =IF(AP$63<=$C$17,($C$34*AP$59*$B102/$C$63)*(IF(COUNTA($D102:AO102)*(12/$C$63)<=$C$9,0,1)),0)+IF(AQ$63=$C$17,0,IF(AP$63=$C$17,$B102*(AP$60),0)) -> 0 | AQ102: =IF(AQ$63<=$C$17,($C$34*AQ$59*$B102/$C$63)*(IF(COUNTA($D102:AP102)*(12/$C$63)<=$C$9,0,1)),0)+IF(AR$63=$C$17,0,IF(AQ$63=$C$17,$B102*(AQ$60),0)) -> 0 | AR102: =IF(AR$63<=$C$17,($C$34*AR$59*$B102/$C$63)*(IF(COUNTA($D102:AQ102)*(12/$C$63)<=$C$9,0,1)),0)+IF(AS$63=$C$17,0,IF(AR$63=$C$17,$B102*(AR$60),0)) -> 0 | AS102: =IF(AS$63<=$C$17,($C$34*AS$59*$B102/$C$63)*(IF(COUNTA($D102:AR102)*(12/$C$63)<=$C$9,0,1)),0)+IF(AT$63=$C$17,0,IF(AS$63=$C$17,$B102*(AS$60),0)) -> 2.36 | AT102: =IF(AT$63<=$C$17,($C$34*AT$59*$B102/$C$63)*(IF(COUNTA($D102:AS102)*(12/$C$63)<=$C$9,0,1)),0)+IF(AU$63=$C$17,0,IF(AT$63=$C$17,$B102*(AT$60),0)) -> 2.36 | AU102: =IF(AU$63<=$C$17,($C$34*AU$59*$B102/$C$63)*(IF(COUNTA($D102:AT102)*(12/$C$63)<=$C$9,0,1)),0)+IF(AV$63=$C$17,0,IF(AU$63=$C$17,$B102*(AU$60),0)) -> 2.36 | AV102: =IF(AV$63<=$C$17,($C$34*AV$59*$B102/$C$63)*(IF(COUNTA($D102:AU102)*(12/$C$63)<=$C$9,0,1)),0)+IF(AW$63=$C$17,0,IF(AV$63=$C$17,$B102*(AV$60),0)) -> 2.36 | ... IW102: =IF(IW$63<=$C$17,($C$34*IW$59*$B102/$C$63)*(IF(COUNTA($D102:IV102)*(12/$C$63)<=$C$9,0,1)),0)+IF(IX$63=$C$17,0,IF(IW$63=$C$17,$B102*(IW$60),0)) -> 0
A103: Versement programmé | B103: =+OFFSET($D$52,0,COUNTA($B$66:B102),,) -> 2 | C103: =SUM(D103:XEG103) -> 97.150149 | AO103: =IF(AP$63>$C$17,0,-AO$53*(12/$C$63)) -> -412.1204 | AP103: =IF(AP$63<=$C$17,($C$34*AP$59*$B103/$C$63)*(IF(COUNTA($D103:AO103)*(12/$C$63)<=$C$9,0,1)),0)+IF(AQ$63=$C$17,0,IF(AP$63=$C$17,$B103*(AP$60),0)) -> 0 | AQ103: =IF(AQ$63<=$C$17,($C$34*AQ$59*$B103/$C$63)*(IF(COUNTA($D103:AP103)*(12/$C$63)<=$C$9,0,1)),0)+IF(AR$63=$C$17,0,IF(AQ$63=$C$17,$B103*(AQ$60),0)) -> 0 | AR103: =IF(AR$63<=$C$17,($C$34*AR$59*$B103/$C$63)*(IF(COUNTA($D103:AQ103)*(12/$C$63)<=$C$9,0,1)),0)+IF(AS$63=$C$17,0,IF(AR$63=$C$17,$B103*(AR$60),0)) -> 0 | AS103: =IF(AS$63<=$C$17,($C$34*AS$59*$B103/$C$63)*(IF(COUNTA($D103:AR103)*(12/$C$63)<=$C$9,0,1)),0)+IF(AT$63=$C$17,0,IF(AS$63=$C$17,$B103*(AS$60),0)) -> 0 | AT103: =IF(AT$63<=$C$17,($C$34*AT$59*$B103/$C$63)*(IF(COUNTA($D103:AS103)*(12/$C$63)<=$C$9,0,1)),0)+IF(AU$63=$C$17,0,IF(AT$63=$C$17,$B103*(AT$60),0)) -> 1.5733333 | AU103: =IF(AU$63<=$C$17,($C$34*AU$59*$B103/$C$63)*(IF(COUNTA($D103:AT103)*(12/$C$63)<=$C$9,0,1)),0)+IF(AV$63=$C$17,0,IF(AU$63=$C$17,$B103*(AU$60),0)) -> 1.5733333 | AV103: =IF(AV$63<=$C$17,($C$34*AV$59*$B103/$C$63)*(IF(COUNTA($D103:AU103)*(12/$C$63)<=$C$9,0,1)),0)+IF(AW$63=$C$17,0,IF(AV$63=$C$17,$B103*(AV$60),0)) -> 1.5733333 | AW103: =IF(AW$63<=$C$17,($C$34*AW$59*$B103/$C$63)*(IF(COUNTA($D103:AV103)*(12/$C$63)<=$C$9,0,1)),0)+IF(AX$63=$C$17,0,IF(AW$63=$C$17,$B103*(AW$60),0)) -> 1.5733333 | ... IW103: =IF(IW$63<=$C$17,($C$34*IW$59*$B103/$C$63)*(IF(COUNTA($D103:IV103)*(12/$C$63)<=$C$9,0,1)),0)+IF(IX$63=$C$17,0,IF(IW$63=$C$17,$B103*(IW$60),0)) -> 0
A104: Versement programmé | B104: =+OFFSET($D$52,0,COUNTA($B$66:B103),,) -> 3 | C104: =SUM(D104:XEG104) -> 143.36522 | AP104: =IF(AQ$63>$C$17,0,-AP$53*(12/$C$63)) -> -618.1806 | AQ104: =IF(AQ$63<=$C$17,($C$34*AQ$59*$B104/$C$63)*(IF(COUNTA($D104:AP104)*(12/$C$63)<=$C$9,0,1)),0)+IF(AR$63=$C$17,0,IF(AQ$63=$C$17,$B104*(AQ$60),0)) -> 0 | AR104: =IF(AR$63<=$C$17,($C$34*AR$59*$B104/$C$63)*(IF(COUNTA($D104:AQ104)*(12/$C$63)<=$C$9,0,1)),0)+IF(AS$63=$C$17,0,IF(AR$63=$C$17,$B104*(AR$60),0)) -> 0 | AS104: =IF(AS$63<=$C$17,($C$34*AS$59*$B104/$C$63)*(IF(COUNTA($D104:AR104)*(12/$C$63)<=$C$9,0,1)),0)+IF(AT$63=$C$17,0,IF(AS$63=$C$17,$B104*(AS$60),0)) -> 0 | AT104: =IF(AT$63<=$C$17,($C$34*AT$59*$B104/$C$63)*(IF(COUNTA($D104:AS104)*(12/$C$63)<=$C$9,0,1)),0)+IF(AU$63=$C$17,0,IF(AT$63=$C$17,$B104*(AT$60),0)) -> 0 | AU104: =IF(AU$63<=$C$17,($C$34*AU$59*$B104/$C$63)*(IF(COUNTA($D104:AT104)*(12/$C$63)<=$C$9,0,1)),0)+IF(AV$63=$C$17,0,IF(AU$63=$C$17,$B104*(AU$60),0)) -> 2.36 | AV104: =IF(AV$63<=$C$17,($C$34*AV$59*$B104/$C$63)*(IF(COUNTA($D104:AU104)*(12/$C$63)<=$C$9,0,1)),0)+IF(AW$63=$C$17,0,IF(AV$63=$C$17,$B104*(AV$60),0)) -> 2.36 | AW104: =IF(AW$63<=$C$17,($C$34*AW$59*$B104/$C$63)*(IF(COUNTA($D104:AV104)*(12/$C$63)<=$C$9,0,1)),0)+IF(AX$63=$C$17,0,IF(AW$63=$C$17,$B104*(AW$60),0)) -> 2.36 | AX104: =IF(AX$63<=$C$17,($C$34*AX$59*$B104/$C$63)*(IF(COUNTA($D104:AW104)*(12/$C$63)<=$C$9,0,1)),0)+IF(AY$63=$C$17,0,IF(AX$63=$C$17,$B104*(AX$60),0)) -> 2.36 | ... IW104: =IF(IW$63<=$C$17,($C$34*IW$59*$B104/$C$63)*(IF(COUNTA($D104:IV104)*(12/$C$63)<=$C$9,0,1)),0)+IF(IX$63=$C$17,0,IF(IW$63=$C$17,$B104*(IW$60),0)) -> 0
A105: Versement programmé | B105: =+OFFSET($D$52,0,COUNTA($B$66:B104),,) -> 2 | C105: =SUM(D105:XEG105) -> 94.003483 | AQ105: =IF(AR$63>$C$17,0,-AQ$53*(12/$C$63)) -> -412.1204 | AR105: =IF(AR$63<=$C$17,($C$34*AR$59*$B105/$C$63)*(IF(COUNTA($D105:AQ105)*(12/$C$63)<=$C$9,0,1)),0)+IF(AS$63=$C$17,0,IF(AR$63=$C$17,$B105*(AR$60),0)) -> 0 | AS105: =IF(AS$63<=$C$17,($C$34*AS$59*$B105/$C$63)*(IF(COUNTA($D105:AR105)*(12/$C$63)<=$C$9,0,1)),0)+IF(AT$63=$C$17,0,IF(AS$63=$C$17,$B105*(AS$60),0)) -> 0 | AT105: =IF(AT$63<=$C$17,($C$34*AT$59*$B105/$C$63)*(IF(COUNTA($D105:AS105)*(12/$C$63)<=$C$9,0,1)),0)+IF(AU$63=$C$17,0,IF(AT$63=$C$17,$B105*(AT$60),0)) -> 0 | AU105: =IF(AU$63<=$C$17,($C$34*AU$59*$B105/$C$63)*(IF(COUNTA($D105:AT105)*(12/$C$63)<=$C$9,0,1)),0)+IF(AV$63=$C$17,0,IF(AU$63=$C$17,$B105*(AU$60),0)) -> 0 | AV105: =IF(AV$63<=$C$17,($C$34*AV$59*$B105/$C$63)*(IF(COUNTA($D105:AU105)*(12/$C$63)<=$C$9,0,1)),0)+IF(AW$63=$C$17,0,IF(AV$63=$C$17,$B105*(AV$60),0)) -> 1.5733333 | AW105: =IF(AW$63<=$C$17,($C$34*AW$59*$B105/$C$63)*(IF(COUNTA($D105:AV105)*(12/$C$63)<=$C$9,0,1)),0)+IF(AX$63=$C$17,0,IF(AW$63=$C$17,$B105*(AW$60),0)) -> 1.5733333 | AX105: =IF(AX$63<=$C$17,($C$34*AX$59*$B105/$C$63)*(IF(COUNTA($D105:AW105)*(12/$C$63)<=$C$9,0,1)),0)+IF(AY$63=$C$17,0,IF(AX$63=$C$17,$B105*(AX$60),0)) -> 1.5733333 | AY105: =IF(AY$63<=$C$17,($C$34*AY$59*$B105/$C$63)*(IF(COUNTA($D105:AX105)*(12/$C$63)<=$C$9,0,1)),0)+IF(AZ$63=$C$17,0,IF(AY$63=$C$17,$B105*(AY$60),0)) -> 1.5733333 | ... IW105: =IF(IW$63<=$C$17,($C$34*IW$59*$B105/$C$63)*(IF(COUNTA($D105:IV105)*(12/$C$63)<=$C$9,0,1)),0)+IF(IX$63=$C$17,0,IF(IW$63=$C$17,$B105*(IW$60),0)) -> 0
A106: Versement programmé | B106: =+OFFSET($D$52,0,COUNTA($B$66:B105),,) -> 3 | C106: =SUM(D106:XEG106) -> 138.64522 | AR106: =IF(AS$63>$C$17,0,-AR$53*(12/$C$63)) -> -618.1806 | AS106: =IF(AS$63<=$C$17,($C$34*AS$59*$B106/$C$63)*(IF(COUNTA($D106:AR106)*(12/$C$63)<=$C$9,0,1)),0)+IF(AT$63=$C$17,0,IF(AS$63=$C$17,$B106*(AS$60),0)) -> 0 | AT106: =IF(AT$63<=$C$17,($C$34*AT$59*$B106/$C$63)*(IF(COUNTA($D106:AS106)*(12/$C$63)<=$C$9,0,1)),0)+IF(AU$63=$C$17,0,IF(AT$63=$C$17,$B106*(AT$60),0)) -> 0 | AU106: =IF(AU$63<=$C$17,($C$34*AU$59*$B106/$C$63)*(IF(COUNTA($D106:AT106)*(12/$C$63)<=$C$9,0,1)),0)+IF(AV$63=$C$17,0,IF(AU$63=$C$17,$B106*(AU$60),0)) -> 0 | AV106: =IF(AV$63<=$C$17,($C$34*AV$59*$B106/$C$63)*(IF(COUNTA($D106:AU106)*(12/$C$63)<=$C$9,0,1)),0)+IF(AW$63=$C$17,0,IF(AV$63=$C$17,$B106*(AV$60),0)) -> 0 | AW106: =IF(AW$63<=$C$17,($C$34*AW$59*$B106/$C$63)*(IF(COUNTA($D106:AV106)*(12/$C$63)<=$C$9,0,1)),0)+IF(AX$63=$C$17,0,IF(AW$63=$C$17,$B106*(AW$60),0)) -> 2.36 | AX106: =IF(AX$63<=$C$17,($C$34*AX$59*$B106/$C$63)*(IF(COUNTA($D106:AW106)*(12/$C$63)<=$C$9,0,1)),0)+IF(AY$63=$C$17,0,IF(AX$63=$C$17,$B106*(AX$60),0)) -> 2.36 | AY106: =IF(AY$63<=$C$17,($C$34*AY$59*$B106/$C$63)*(IF(COUNTA($D106:AX106)*(12/$C$63)<=$C$9,0,1)),0)+IF(AZ$63=$C$17,0,IF(AY$63=$C$17,$B106*(AY$60),0)) -> 2.36 | AZ106: =IF(AZ$63<=$C$17,($C$34*AZ$59*$B106/$C$63)*(IF(COUNTA($D106:AY106)*(12/$C$63)<=$C$9,0,1)),0)+IF(BA$63=$C$17,0,IF(AZ$63=$C$17,$B106*(AZ$60),0)) -> 2.36 | ... IW106: =IF(IW$63<=$C$17,($C$34*IW$59*$B106/$C$63)*(IF(COUNTA($D106:IV106)*(12/$C$63)<=$C$9,0,1)),0)+IF(IX$63=$C$17,0,IF(IW$63=$C$17,$B106*(IW$60),0)) -> 0
A107: Versement programmé | B107: =+OFFSET($D$52,0,COUNTA($B$66:B106),,) -> 2 | C107: =SUM(D107:XEG107) -> 90.856816 | AS107: =IF(AT$63>$C$17,0,-AS$53*(12/$C$63)) -> -412.1204 | AT107: =IF(AT$63<=$C$17,($C$34*AT$59*$B107/$C$63)*(IF(COUNTA($D107:AS107)*(12/$C$63)<=$C$9,0,1)),0)+IF(AU$63=$C$17,0,IF(AT$63=$C$17,$B107*(AT$60),0)) -> 0 | AU107: =IF(AU$63<=$C$17,($C$34*AU$59*$B107/$C$63)*(IF(COUNTA($D107:AT107)*(12/$C$63)<=$C$9,0,1)),0)+IF(AV$63=$C$17,0,IF(AU$63=$C$17,$B107*(AU$60),0)) -> 0 | AV107: =IF(AV$63<=$C$17,($C$34*AV$59*$B107/$C$63)*(IF(COUNTA($D107:AU107)*(12/$C$63)<=$C$9,0,1)),0)+IF(AW$63=$C$17,0,IF(AV$63=$C$17,$B107*(AV$60),0)) -> 0 | AW107: =IF(AW$63<=$C$17,($C$34*AW$59*$B107/$C$63)*(IF(COUNTA($D107:AV107)*(12/$C$63)<=$C$9,0,1)),0)+IF(AX$63=$C$17,0,IF(AW$63=$C$17,$B107*(AW$60),0)) -> 0 | AX107: =IF(AX$63<=$C$17,($C$34*AX$59*$B107/$C$63)*(IF(COUNTA($D107:AW107)*(12/$C$63)<=$C$9,0,1)),0)+IF(AY$63=$C$17,0,IF(AX$63=$C$17,$B107*(AX$60),0)) -> 1.5733333 | AY107: =IF(AY$63<=$C$17,($C$34*AY$59*$B107/$C$63)*(IF(COUNTA($D107:AX107)*(12/$C$63)<=$C$9,0,1)),0)+IF(AZ$63=$C$17,0,IF(AY$63=$C$17,$B107*(AY$60),0)) -> 1.5733333 | AZ107: =IF(AZ$63<=$C$17,($C$34*AZ$59*$B107/$C$63)*(IF(COUNTA($D107:AY107)*(12/$C$63)<=$C$9,0,1)),0)+IF(BA$63=$C$17,0,IF(AZ$63=$C$17,$B107*(AZ$60),0)) -> 1.5733333 | BA107: =IF(BA$63<=$C$17,($C$34*BA$59*$B107/$C$63)*(IF(COUNTA($D107:AZ107)*(12/$C$63)<=$C$9,0,1)),0)+IF(BB$63=$C$17,0,IF(BA$63=$C$17,$B107*(BA$60),0)) -> 1.5733333 | ... IW107: =IF(IW$63<=$C$17,($C$34*IW$59*$B107/$C$63)*(IF(COUNTA($D107:IV107)*(12/$C$63)<=$C$9,0,1)),0)+IF(IX$63=$C$17,0,IF(IW$63=$C$17,$B107*(IW$60),0)) -> 0
A108: Versement programmé | B108: =+OFFSET($D$52,0,COUNTA($B$66:B107),,) -> 3 | C108: =SUM(D108:XEG108) -> 133.92522 | AT108: =IF(AU$63>$C$17,0,-AT$53*(12/$C$63)) -> -618.1806 | AU108: =IF(AU$63<=$C$17,($C$34*AU$59*$B108/$C$63)*(IF(COUNTA($D108:AT108)*(12/$C$63)<=$C$9,0,1)),0)+IF(AV$63=$C$17,0,IF(AU$63=$C$17,$B108*(AU$60),0)) -> 0 | AV108: =IF(AV$63<=$C$17,($C$34*AV$59*$B108/$C$63)*(IF(COUNTA($D108:AU108)*(12/$C$63)<=$C$9,0,1)),0)+IF(AW$63=$C$17,0,IF(AV$63=$C$17,$B108*(AV$60),0)) -> 0 | AW108: =IF(AW$63<=$C$17,($C$34*AW$59*$B108/$C$63)*(IF(COUNTA($D108:AV108)*(12/$C$63)<=$C$9,0,1)),0)+IF(AX$63=$C$17,0,IF(AW$63=$C$17,$B108*(AW$60),0)) -> 0 | AX108: =IF(AX$63<=$C$17,($C$34*AX$59*$B108/$C$63)*(IF(COUNTA($D108:AW108)*(12/$C$63)<=$C$9,0,1)),0)+IF(AY$63=$C$17,0,IF(AX$63=$C$17,$B108*(AX$60),0)) -> 0 | AY108: =IF(AY$63<=$C$17,($C$34*AY$59*$B108/$C$63)*(IF(COUNTA($D108:AX108)*(12/$C$63)<=$C$9,0,1)),0)+IF(AZ$63=$C$17,0,IF(AY$63=$C$17,$B108*(AY$60),0)) -> 2.36 | AZ108: =IF(AZ$63<=$C$17,($C$34*AZ$59*$B108/$C$63)*(IF(COUNTA($D108:AY108)*(12/$C$63)<=$C$9,0,1)),0)+IF(BA$63=$C$17,0,IF(AZ$63=$C$17,$B108*(AZ$60),0)) -> 2.36 | BA108: =IF(BA$63<=$C$17,($C$34*BA$59*$B108/$C$63)*(IF(COUNTA($D108:AZ108)*(12/$C$63)<=$C$9,0,1)),0)+IF(BB$63=$C$17,0,IF(BA$63=$C$17,$B108*(BA$60),0)) -> 2.36 | BB108: =IF(BB$63<=$C$17,($C$34*BB$59*$B108/$C$63)*(IF(COUNTA($D108:BA108)*(12/$C$63)<=$C$9,0,1)),0)+IF(BC$63=$C$17,0,IF(BB$63=$C$17,$B108*(BB$60),0)) -> 2.36 | ... IW108: =IF(IW$63<=$C$17,($C$34*IW$59*$B108/$C$63)*(IF(COUNTA($D108:IV108)*(12/$C$63)<=$C$9,0,1)),0)+IF(IX$63=$C$17,0,IF(IW$63=$C$17,$B108*(IW$60),0)) -> 0
A109: Versement programmé | B109: =+OFFSET($D$52,0,COUNTA($B$66:B108),,) -> 2 | C109: =SUM(D109:XEG109) -> 87.710149 | AU109: =IF(AV$63>$C$17,0,-AU$53*(12/$C$63)) -> -412.1204 | AV109: =IF(AV$63<=$C$17,($C$34*AV$59*$B109/$C$63)*(IF(COUNTA($D109:AU109)*(12/$C$63)<=$C$9,0,1)),0)+IF(AW$63=$C$17,0,IF(AV$63=$C$17,$B109*(AV$60),0)) -> 0 | AW109: =IF(AW$63<=$C$17,($C$34*AW$59*$B109/$C$63)*(IF(COUNTA($D109:AV109)*(12/$C$63)<=$C$9,0,1)),0)+IF(AX$63=$C$17,0,IF(AW$63=$C$17,$B109*(AW$60),0)) -> 0 | AX109: =IF(AX$63<=$C$17,($C$34*AX$59*$B109/$C$63)*(IF(COUNTA($D109:AW109)*(12/$C$63)<=$C$9,0,1)),0)+IF(AY$63=$C$17,0,IF(AX$63=$C$17,$B109*(AX$60),0)) -> 0 | AY109: =IF(AY$63<=$C$17,($C$34*AY$59*$B109/$C$63)*(IF(COUNTA($D109:AX109)*(12/$C$63)<=$C$9,0,1)),0)+IF(AZ$63=$C$17,0,IF(AY$63=$C$17,$B109*(AY$60),0)) -> 0 | AZ109: =IF(AZ$63<=$C$17,($C$34*AZ$59*$B109/$C$63)*(IF(COUNTA($D109:AY109)*(12/$C$63)<=$C$9,0,1)),0)+IF(BA$63=$C$17,0,IF(AZ$63=$C$17,$B109*(AZ$60),0)) -> 1.5733333 | BA109: =IF(BA$63<=$C$17,($C$34*BA$59*$B109/$C$63)*(IF(COUNTA($D109:AZ109)*(12/$C$63)<=$C$9,0,1)),0)+IF(BB$63=$C$17,0,IF(BA$63=$C$17,$B109*(BA$60),0)) -> 1.5733333 | BB109: =IF(BB$63<=$C$17,($C$34*BB$59*$B109/$C$63)*(IF(COUNTA($D109:BA109)*(12/$C$63)<=$C$9,0,1)),0)+IF(BC$63=$C$17,0,IF(BB$63=$C$17,$B109*(BB$60),0)) -> 1.5733333 | BC109: =IF(BC$63<=$C$17,($C$34*BC$59*$B109/$C$63)*(IF(COUNTA($D109:BB109)*(12/$C$63)<=$C$9,0,1)),0)+IF(BD$63=$C$17,0,IF(BC$63=$C$17,$B109*(BC$60),0)) -> 1.5733333 | ... IW109: =IF(IW$63<=$C$17,($C$34*IW$59*$B109/$C$63)*(IF(COUNTA($D109:IV109)*(12/$C$63)<=$C$9,0,1)),0)+IF(IX$63=$C$17,0,IF(IW$63=$C$17,$B109*(IW$60),0)) -> 0
A110: Versement programmé | B110: =+OFFSET($D$52,0,COUNTA($B$66:B109),,) -> 3 | C110: =SUM(D110:XEG110) -> 129.20522 | AV110: =IF(AW$63>$C$17,0,-AV$53*(12/$C$63)) -> -618.1806 | AW110: =IF(AW$63<=$C$17,($C$34*AW$59*$B110/$C$63)*(IF(COUNTA($D110:AV110)*(12/$C$63)<=$C$9,0,1)),0)+IF(AX$63=$C$17,0,IF(AW$63=$C$17,$B110*(AW$60),0)) -> 0 | AX110: =IF(AX$63<=$C$17,($C$34*AX$59*$B110/$C$63)*(IF(COUNTA($D110:AW110)*(12/$C$63)<=$C$9,0,1)),0)+IF(AY$63=$C$17,0,IF(AX$63=$C$17,$B110*(AX$60),0)) -> 0 | AY110: =IF(AY$63<=$C$17,($C$34*AY$59*$B110/$C$63)*(IF(COUNTA($D110:AX110)*(12/$C$63)<=$C$9,0,1)),0)+IF(AZ$63=$C$17,0,IF(AY$63=$C$17,$B110*(AY$60),0)) -> 0 | AZ110: =IF(AZ$63<=$C$17,($C$34*AZ$59*$B110/$C$63)*(IF(COUNTA($D110:AY110)*(12/$C$63)<=$C$9,0,1)),0)+IF(BA$63=$C$17,0,IF(AZ$63=$C$17,$B110*(AZ$60),0)) -> 0 | BA110: =IF(BA$63<=$C$17,($C$34*BA$59*$B110/$C$63)*(IF(COUNTA($D110:AZ110)*(12/$C$63)<=$C$9,0,1)),0)+IF(BB$63=$C$17,0,IF(BA$63=$C$17,$B110*(BA$60),0)) -> 2.36 | BB110: =IF(BB$63<=$C$17,($C$34*BB$59*$B110/$C$63)*(IF(COUNTA($D110:BA110)*(12/$C$63)<=$C$9,0,1)),0)+IF(BC$63=$C$17,0,IF(BB$63=$C$17,$B110*(BB$60),0)) -> 2.36 | BC110: =IF(BC$63<=$C$17,($C$34*BC$59*$B110/$C$63)*(IF(COUNTA($D110:BB110)*(12/$C$63)<=$C$9,0,1)),0)+IF(BD$63=$C$17,0,IF(BC$63=$C$17,$B110*(BC$60),0)) -> 2.36 | BD110: =IF(BD$63<=$C$17,($C$34*BD$59*$B110/$C$63)*(IF(COUNTA($D110:BC110)*(12/$C$63)<=$C$9,0,1)),0)+IF(BE$63=$C$17,0,IF(BD$63=$C$17,$B110*(BD$60),0)) -> 2.36 | ... IW110: =IF(IW$63<=$C$17,($C$34*IW$59*$B110/$C$63)*(IF(COUNTA($D110:IV110)*(12/$C$63)<=$C$9,0,1)),0)+IF(IX$63=$C$17,0,IF(IW$63=$C$17,$B110*(IW$60),0)) -> 0
A111: Versement programmé | B111: =+OFFSET($D$52,0,COUNTA($B$66:B110),,) -> 2 | C111: =SUM(D111:XEG111) -> 84.563483 | AW111: =IF(AX$63>$C$17,0,-AW$53*(12/$C$63)) -> -412.1204 | AX111: =IF(AX$63<=$C$17,($C$34*AX$59*$B111/$C$63)*(IF(COUNTA($D111:AW111)*(12/$C$63)<=$C$9,0,1)),0)+IF(AY$63=$C$17,0,IF(AX$63=$C$17,$B111*(AX$60),0)) -> 0 | AY111: =IF(AY$63<=$C$17,($C$34*AY$59*$B111/$C$63)*(IF(COUNTA($D111:AX111)*(12/$C$63)<=$C$9,0,1)),0)+IF(AZ$63=$C$17,0,IF(AY$63=$C$17,$B111*(AY$60),0)) -> 0 | AZ111: =IF(AZ$63<=$C$17,($C$34*AZ$59*$B111/$C$63)*(IF(COUNTA($D111:AY111)*(12/$C$63)<=$C$9,0,1)),0)+IF(BA$63=$C$17,0,IF(AZ$63=$C$17,$B111*(AZ$60),0)) -> 0 | BA111: =IF(BA$63<=$C$17,($C$34*BA$59*$B111/$C$63)*(IF(COUNTA($D111:AZ111)*(12/$C$63)<=$C$9,0,1)),0)+IF(BB$63=$C$17,0,IF(BA$63=$C$17,$B111*(BA$60),0)) -> 0 | BB111: =IF(BB$63<=$C$17,($C$34*BB$59*$B111/$C$63)*(IF(COUNTA($D111:BA111)*(12/$C$63)<=$C$9,0,1)),0)+IF(BC$63=$C$17,0,IF(BB$63=$C$17,$B111*(BB$60),0)) -> 1.5733333 | BC111: =IF(BC$63<=$C$17,($C$34*BC$59*$B111/$C$63)*(IF(COUNTA($D111:BB111)*(12/$C$63)<=$C$9,0,1)),0)+IF(BD$63=$C$17,0,IF(BC$63=$C$17,$B111*(BC$60),0)) -> 1.5733333 | BD111: =IF(BD$63<=$C$17,($C$34*BD$59*$B111/$C$63)*(IF(COUNTA($D111:BC111)*(12/$C$63)<=$C$9,0,1)),0)+IF(BE$63=$C$17,0,IF(BD$63=$C$17,$B111*(BD$60),0)) -> 1.5733333 | BE111: =IF(BE$63<=$C$17,($C$34*BE$59*$B111/$C$63)*(IF(COUNTA($D111:BD111)*(12/$C$63)<=$C$9,0,1)),0)+IF(BF$63=$C$17,0,IF(BE$63=$C$17,$B111*(BE$60),0)) -> 1.5733333 | ... IW111: =IF(IW$63<=$C$17,($C$34*IW$59*$B111/$C$63)*(IF(COUNTA($D111:IV111)*(12/$C$63)<=$C$9,0,1)),0)+IF(IX$63=$C$17,0,IF(IW$63=$C$17,$B111*(IW$60),0)) -> 0
A112: Versement programmé | B112: =+OFFSET($D$52,0,COUNTA($B$66:B111),,) -> 3 | C112: =SUM(D112:XEG112) -> 124.48522 | AX112: =IF(AY$63>$C$17,0,-AX$53*(12/$C$63)) -> -618.1806 | AY112: =IF(AY$63<=$C$17,($C$34*AY$59*$B112/$C$63)*(IF(COUNTA($D112:AX112)*(12/$C$63)<=$C$9,0,1)),0)+IF(AZ$63=$C$17,0,IF(AY$63=$C$17,$B112*(AY$60),0)) -> 0 | AZ112: =IF(AZ$63<=$C$17,($C$34*AZ$59*$B112/$C$63)*(IF(COUNTA($D112:AY112)*(12/$C$63)<=$C$9,0,1)),0)+IF(BA$63=$C$17,0,IF(AZ$63=$C$17,$B112*(AZ$60),0)) -> 0 | BA112: =IF(BA$63<=$C$17,($C$34*BA$59*$B112/$C$63)*(IF(COUNTA($D112:AZ112)*(12/$C$63)<=$C$9,0,1)),0)+IF(BB$63=$C$17,0,IF(BA$63=$C$17,$B112*(BA$60),0)) -> 0 | BB112: =IF(BB$63<=$C$17,($C$34*BB$59*$B112/$C$63)*(IF(COUNTA($D112:BA112)*(12/$C$63)<=$C$9,0,1)),0)+IF(BC$63=$C$17,0,IF(BB$63=$C$17,$B112*(BB$60),0)) -> 0 | BC112: =IF(BC$63<=$C$17,($C$34*BC$59*$B112/$C$63)*(IF(COUNTA($D112:BB112)*(12/$C$63)<=$C$9,0,1)),0)+IF(BD$63=$C$17,0,IF(BC$63=$C$17,$B112*(BC$60),0)) -> 2.36 | BD112: =IF(BD$63<=$C$17,($C$34*BD$59*$B112/$C$63)*(IF(COUNTA($D112:BC112)*(12/$C$63)<=$C$9,0,1)),0)+IF(BE$63=$C$17,0,IF(BD$63=$C$17,$B112*(BD$60),0)) -> 2.36 | BE112: =IF(BE$63<=$C$17,($C$34*BE$59*$B112/$C$63)*(IF(COUNTA($D112:BD112)*(12/$C$63)<=$C$9,0,1)),0)+IF(BF$63=$C$17,0,IF(BE$63=$C$17,$B112*(BE$60),0)) -> 2.36 | BF112: =IF(BF$63<=$C$17,($C$34*BF$59*$B112/$C$63)*(IF(COUNTA($D112:BE112)*(12/$C$63)<=$C$9,0,1)),0)+IF(BG$63=$C$17,0,IF(BF$63=$C$17,$B112*(BF$60),0)) -> 2.36 | ... IW112: =IF(IW$63<=$C$17,($C$34*IW$59*$B112/$C$63)*(IF(COUNTA($D112:IV112)*(12/$C$63)<=$C$9,0,1)),0)+IF(IX$63=$C$17,0,IF(IW$63=$C$17,$B112*(IW$60),0)) -> 0
A113: Versement programmé | B113: =+OFFSET($D$52,0,COUNTA($B$66:B112),,) -> 3 | C113: =SUM(D113:XEG113) -> 122.12522 | AY113: =IF(AZ$63>$C$17,0,-AY$53*(12/$C$63)) -> -618.1806 | AZ113: =IF(AZ$63<=$C$17,($C$34*AZ$59*$B113/$C$63)*(IF(COUNTA($D113:AY113)*(12/$C$63)<=$C$9,0,1)),0)+IF(BA$63=$C$17,0,IF(AZ$63=$C$17,$B113*(AZ$60),0)) -> 0 | BA113: =IF(BA$63<=$C$17,($C$34*BA$59*$B113/$C$63)*(IF(COUNTA($D113:AZ113)*(12/$C$63)<=$C$9,0,1)),0)+IF(BB$63=$C$17,0,IF(BA$63=$C$17,$B113*(BA$60),0)) -> 0 | BB113: =IF(BB$63<=$C$17,($C$34*BB$59*$B113/$C$63)*(IF(COUNTA($D113:BA113)*(12/$C$63)<=$C$9,0,1)),0)+IF(BC$63=$C$17,0,IF(BB$63=$C$17,$B113*(BB$60),0)) -> 0 | BC113: =IF(BC$63<=$C$17,($C$34*BC$59*$B113/$C$63)*(IF(COUNTA($D113:BB113)*(12/$C$63)<=$C$9,0,1)),0)+IF(BD$63=$C$17,0,IF(BC$63=$C$17,$B113*(BC$60),0)) -> 0 | BD113: =IF(BD$63<=$C$17,($C$34*BD$59*$B113/$C$63)*(IF(COUNTA($D113:BC113)*(12/$C$63)<=$C$9,0,1)),0)+IF(BE$63=$C$17,0,IF(BD$63=$C$17,$B113*(BD$60),0)) -> 2.36 | BE113: =IF(BE$63<=$C$17,($C$34*BE$59*$B113/$C$63)*(IF(COUNTA($D113:BD113)*(12/$C$63)<=$C$9,0,1)),0)+IF(BF$63=$C$17,0,IF(BE$63=$C$17,$B113*(BE$60),0)) -> 2.36 | BF113: =IF(BF$63<=$C$17,($C$34*BF$59*$B113/$C$63)*(IF(COUNTA($D113:BE113)*(12/$C$63)<=$C$9,0,1)),0)+IF(BG$63=$C$17,0,IF(BF$63=$C$17,$B113*(BF$60),0)) -> 2.36 | BG113: =IF(BG$63<=$C$17,($C$34*BG$59*$B113/$C$63)*(IF(COUNTA($D113:BF113)*(12/$C$63)<=$C$9,0,1)),0)+IF(BH$63=$C$17,0,IF(BG$63=$C$17,$B113*(BG$60),0)) -> 2.36 | ... IW113: =IF(IW$63<=$C$17,($C$34*IW$59*$B113/$C$63)*(IF(COUNTA($D113:IV113)*(12/$C$63)<=$C$9,0,1)),0)+IF(IX$63=$C$17,0,IF(IW$63=$C$17,$B113*(IW$60),0)) -> 0
A114: Versement programmé | B114: =+OFFSET($D$52,0,COUNTA($B$66:B113),,) -> 2 | C114: =SUM(D114:XEG114) -> 79.843483 | AZ114: =IF(BA$63>$C$17,0,-AZ$53*(12/$C$63)) -> -412.1204 | BA114: =IF(BA$63<=$C$17,($C$34*BA$59*$B114/$C$63)*(IF(COUNTA($D114:AZ114)*(12/$C$63)<=$C$9,0,1)),0)+IF(BB$63=$C$17,0,IF(BA$63=$C$17,$B114*(BA$60),0)) -> 0 | BB114: =IF(BB$63<=$C$17,($C$34*BB$59*$B114/$C$63)*(IF(COUNTA($D114:BA114)*(12/$C$63)<=$C$9,0,1)),0)+IF(BC$63=$C$17,0,IF(BB$63=$C$17,$B114*(BB$60),0)) -> 0 | BC114: =IF(BC$63<=$C$17,($C$34*BC$59*$B114/$C$63)*(IF(COUNTA($D114:BB114)*(12/$C$63)<=$C$9,0,1)),0)+IF(BD$63=$C$17,0,IF(BC$63=$C$17,$B114*(BC$60),0)) -> 0 | BD114: =IF(BD$63<=$C$17,($C$34*BD$59*$B114/$C$63)*(IF(COUNTA($D114:BC114)*(12/$C$63)<=$C$9,0,1)),0)+IF(BE$63=$C$17,0,IF(BD$63=$C$17,$B114*(BD$60),0)) -> 0 | BE114: =IF(BE$63<=$C$17,($C$34*BE$59*$B114/$C$63)*(IF(COUNTA($D114:BD114)*(12/$C$63)<=$C$9,0,1)),0)+IF(BF$63=$C$17,0,IF(BE$63=$C$17,$B114*(BE$60),0)) -> 1.5733333 | BF114: =IF(BF$63<=$C$17,($C$34*BF$59*$B114/$C$63)*(IF(COUNTA($D114:BE114)*(12/$C$63)<=$C$9,0,1)),0)+IF(BG$63=$C$17,0,IF(BF$63=$C$17,$B114*(BF$60),0)) -> 1.5733333 | BG114: =IF(BG$63<=$C$17,($C$34*BG$59*$B114/$C$63)*(IF(COUNTA($D114:BF114)*(12/$C$63)<=$C$9,0,1)),0)+IF(BH$63=$C$17,0,IF(BG$63=$C$17,$B114*(BG$60),0)) -> 1.5733333 | BH114: =IF(BH$63<=$C$17,($C$34*BH$59*$B114/$C$63)*(IF(COUNTA($D114:BG114)*(12/$C$63)<=$C$9,0,1)),0)+IF(BI$63=$C$17,0,IF(BH$63=$C$17,$B114*(BH$60),0)) -> 1.5733333 | ... IW114: =IF(IW$63<=$C$17,($C$34*IW$59*$B114/$C$63)*(IF(COUNTA($D114:IV114)*(12/$C$63)<=$C$9,0,1)),0)+IF(IX$63=$C$17,0,IF(IW$63=$C$17,$B114*(IW$60),0)) -> 0
A115: Versement programmé | B115: =+OFFSET($D$52,0,COUNTA($B$66:B114),,) -> 3 | C115: =SUM(D115:XEG115) -> 111.22342 | BA115: =IF(BB$63>$C$17,0,-BA$53*(12/$C$63)) -> -624.36241 | BB115: =IF(BB$63<=$C$17,($C$34*BB$59*$B115/$C$63)*(IF(COUNTA($D115:BA115)*(12/$C$63)<=$C$9,0,1)),0)+IF(BC$63=$C$17,0,IF(BB$63=$C$17,$B115*(BB$60),0)) -> 0 | BC115: =IF(BC$63<=$C$17,($C$34*BC$59*$B115/$C$63)*(IF(COUNTA($D115:BB115)*(12/$C$63)<=$C$9,0,1)),0)+IF(BD$63=$C$17,0,IF(BC$63=$C$17,$B115*(BC$60),0)) -> 0 | BD115: =IF(BD$63<=$C$17,($C$34*BD$59*$B115/$C$63)*(IF(COUNTA($D115:BC115)*(12/$C$63)<=$C$9,0,1)),0)+IF(BE$63=$C$17,0,IF(BD$63=$C$17,$B115*(BD$60),0)) -> 0 | BE115: =IF(BE$63<=$C$17,($C$34*BE$59*$B115/$C$63)*(IF(COUNTA($D115:BD115)*(12/$C$63)<=$C$9,0,1)),0)+IF(BF$63=$C$17,0,IF(BE$63=$C$17,$B115*(BE$60),0)) -> 0 | BF115: =IF(BF$63<=$C$17,($C$34*BF$59*$B115/$C$63)*(IF(COUNTA($D115:BE115)*(12/$C$63)<=$C$9,0,1)),0)+IF(BG$63=$C$17,0,IF(BF$63=$C$17,$B115*(BF$60),0)) -> 2.36 | BG115: =IF(BG$63<=$C$17,($C$34*BG$59*$B115/$C$63)*(IF(COUNTA($D115:BF115)*(12/$C$63)<=$C$9,0,1)),0)+IF(BH$63=$C$17,0,IF(BG$63=$C$17,$B115*(BG$60),0)) -> 2.36 | BH115: =IF(BH$63<=$C$17,($C$34*BH$59*$B115/$C$63)*(IF(COUNTA($D115:BG115)*(12/$C$63)<=$C$9,0,1)),0)+IF(BI$63=$C$17,0,IF(BH$63=$C$17,$B115*(BH$60),0)) -> 2.36 | BI115: =IF(BI$63<=$C$17,($C$34*BI$59*$B115/$C$63)*(IF(COUNTA($D115:BH115)*(12/$C$63)<=$C$9,0,1)),0)+IF(BJ$63=$C$17,0,IF(BI$63=$C$17,$B115*(BI$60),0)) -> 2.36 | ... IW115: =IF(IW$63<=$C$17,($C$34*IW$59*$B115/$C$63)*(IF(COUNTA($D115:IV115)*(12/$C$63)<=$C$9,0,1)),0)+IF(IX$63=$C$17,0,IF(IW$63=$C$17,$B115*(IW$60),0)) -> 0
A116: Versement programmé | B116: =+OFFSET($D$52,0,COUNTA($B$66:B115),,) -> 2 | C116: =SUM(D116:XEG116) -> 72.575612 | BB116: =IF(BC$63>$C$17,0,-BB$53*(12/$C$63)) -> -416.2416 | BC116: =IF(BC$63<=$C$17,($C$34*BC$59*$B116/$C$63)*(IF(COUNTA($D116:BB116)*(12/$C$63)<=$C$9,0,1)),0)+IF(BD$63=$C$17,0,IF(BC$63=$C$17,$B116*(BC$60),0)) -> 0 | BD116: =IF(BD$63<=$C$17,($C$34*BD$59*$B116/$C$63)*(IF(COUNTA($D116:BC116)*(12/$C$63)<=$C$9,0,1)),0)+IF(BE$63=$C$17,0,IF(BD$63=$C$17,$B116*(BD$60),0)) -> 0 | BE116: =IF(BE$63<=$C$17,($C$34*BE$59*$B116/$C$63)*(IF(COUNTA($D116:BD116)*(12/$C$63)<=$C$9,0,1)),0)+IF(BF$63=$C$17,0,IF(BE$63=$C$17,$B116*(BE$60),0)) -> 0 | BF116: =IF(BF$63<=$C$17,($C$34*BF$59*$B116/$C$63)*(IF(COUNTA($D116:BE116)*(12/$C$63)<=$C$9,0,1)),0)+IF(BG$63=$C$17,0,IF(BF$63=$C$17,$B116*(BF$60),0)) -> 0 | BG116: =IF(BG$63<=$C$17,($C$34*BG$59*$B116/$C$63)*(IF(COUNTA($D116:BF116)*(12/$C$63)<=$C$9,0,1)),0)+IF(BH$63=$C$17,0,IF(BG$63=$C$17,$B116*(BG$60),0)) -> 1.5733333 | BH116: =IF(BH$63<=$C$17,($C$34*BH$59*$B116/$C$63)*(IF(COUNTA($D116:BG116)*(12/$C$63)<=$C$9,0,1)),0)+IF(BI$63=$C$17,0,IF(BH$63=$C$17,$B116*(BH$60),0)) -> 1.5733333 | BI116: =IF(BI$63<=$C$17,($C$34*BI$59*$B116/$C$63)*(IF(COUNTA($D116:BH116)*(12/$C$63)<=$C$9,0,1)),0)+IF(BJ$63=$C$17,0,IF(BI$63=$C$17,$B116*(BI$60),0)) -> 1.5733333 | BJ116: =IF(BJ$63<=$C$17,($C$34*BJ$59*$B116/$C$63)*(IF(COUNTA($D116:BI116)*(12/$C$63)<=$C$9,0,1)),0)+IF(BK$63=$C$17,0,IF(BJ$63=$C$17,$B116*(BJ$60),0)) -> 1.5733333 | ... IW116: =IF(IW$63<=$C$17,($C$34*IW$59*$B116/$C$63)*(IF(COUNTA($D116:IV116)*(12/$C$63)<=$C$9,0,1)),0)+IF(IX$63=$C$17,0,IF(IW$63=$C$17,$B116*(IW$60),0)) -> 0
A117: Versement programmé | B117: =+OFFSET($D$52,0,COUNTA($B$66:B116),,) -> 3 | C117: =SUM(D117:XEG117) -> 106.50342 | BC117: =IF(BD$63>$C$17,0,-BC$53*(12/$C$63)) -> -624.36241 | BD117: =IF(BD$63<=$C$17,($C$34*BD$59*$B117/$C$63)*(IF(COUNTA($D117:BC117)*(12/$C$63)<=$C$9,0,1)),0)+IF(BE$63=$C$17,0,IF(BD$63=$C$17,$B117*(BD$60),0)) -> 0 | BE117: =IF(BE$63<=$C$17,($C$34*BE$59*$B117/$C$63)*(IF(COUNTA($D117:BD117)*(12/$C$63)<=$C$9,0,1)),0)+IF(BF$63=$C$17,0,IF(BE$63=$C$17,$B117*(BE$60),0)) -> 0 | BF117: =IF(BF$63<=$C$17,($C$34*BF$59*$B117/$C$63)*(IF(COUNTA($D117:BE117)*(12/$C$63)<=$C$9,0,1)),0)+IF(BG$63=$C$17,0,IF(BF$63=$C$17,$B117*(BF$60),0)) -> 0 | BG117: =IF(BG$63<=$C$17,($C$34*BG$59*$B117/$C$63)*(IF(COUNTA($D117:BF117)*(12/$C$63)<=$C$9,0,1)),0)+IF(BH$63=$C$17,0,IF(BG$63=$C$17,$B117*(BG$60),0)) -> 0 | BH117: =IF(BH$63<=$C$17,($C$34*BH$59*$B117/$C$63)*(IF(COUNTA($D117:BG117)*(12/$C$63)<=$C$9,0,1)),0)+IF(BI$63=$C$17,0,IF(BH$63=$C$17,$B117*(BH$60),0)) -> 2.36 | BI117: =IF(BI$63<=$C$17,($C$34*BI$59*$B117/$C$63)*(IF(COUNTA($D117:BH117)*(12/$C$63)<=$C$9,0,1)),0)+IF(BJ$63=$C$17,0,IF(BI$63=$C$17,$B117*(BI$60),0)) -> 2.36 | BJ117: =IF(BJ$63<=$C$17,($C$34*BJ$59*$B117/$C$63)*(IF(COUNTA($D117:BI117)*(12/$C$63)<=$C$9,0,1)),0)+IF(BK$63=$C$17,0,IF(BJ$63=$C$17,$B117*(BJ$60),0)) -> 2.36 | BK117: =IF(BK$63<=$C$17,($C$34*BK$59*$B117/$C$63)*(IF(COUNTA($D117:BJ117)*(12/$C$63)<=$C$9,0,1)),0)+IF(BL$63=$C$17,0,IF(BK$63=$C$17,$B117*(BK$60),0)) -> 2.36 | ... IW117: =IF(IW$63<=$C$17,($C$34*IW$59*$B117/$C$63)*(IF(COUNTA($D117:IV117)*(12/$C$63)<=$C$9,0,1)),0)+IF(IX$63=$C$17,0,IF(IW$63=$C$17,$B117*(IW$60),0)) -> 0
A118: Versement programmé | B118: =+OFFSET($D$52,0,COUNTA($B$66:B117),,) -> 2 | C118: =SUM(D118:XEG118) -> 69.428945 | BD118: =IF(BE$63>$C$17,0,-BD$53*(12/$C$63)) -> -416.2416 | BE118: =IF(BE$63<=$C$17,($C$34*BE$59*$B118/$C$63)*(IF(COUNTA($D118:BD118)*(12/$C$63)<=$C$9,0,1)),0)+IF(BF$63=$C$17,0,IF(BE$63=$C$17,$B118*(BE$60),0)) -> 0 | BF118: =IF(BF$63<=$C$17,($C$34*BF$59*$B118/$C$63)*(IF(COUNTA($D118:BE118)*(12/$C$63)<=$C$9,0,1)),0)+IF(BG$63=$C$17,0,IF(BF$63=$C$17,$B118*(BF$60),0)) -> 0 | BG118: =IF(BG$63<=$C$17,($C$34*BG$59*$B118/$C$63)*(IF(COUNTA($D118:BF118)*(12/$C$63)<=$C$9,0,1)),0)+IF(BH$63=$C$17,0,IF(BG$63=$C$17,$B118*(BG$60),0)) -> 0 | BH118: =IF(BH$63<=$C$17,($C$34*BH$59*$B118/$C$63)*(IF(COUNTA($D118:BG118)*(12/$C$63)<=$C$9,0,1)),0)+IF(BI$63=$C$17,0,IF(BH$63=$C$17,$B118*(BH$60),0)) -> 0 | BI118: =IF(BI$63<=$C$17,($C$34*BI$59*$B118/$C$63)*(IF(COUNTA($D118:BH118)*(12/$C$63)<=$C$9,0,1)),0)+IF(BJ$63=$C$17,0,IF(BI$63=$C$17,$B118*(BI$60),0)) -> 1.5733333 | BJ118: =IF(BJ$63<=$C$17,($C$34*BJ$59*$B118/$C$63)*(IF(COUNTA($D118:BI118)*(12/$C$63)<=$C$9,0,1)),0)+IF(BK$63=$C$17,0,IF(BJ$63=$C$17,$B118*(BJ$60),0)) -> 1.5733333 | BK118: =IF(BK$63<=$C$17,($C$34*BK$59*$B118/$C$63)*(IF(COUNTA($D118:BJ118)*(12/$C$63)<=$C$9,0,1)),0)+IF(BL$63=$C$17,0,IF(BK$63=$C$17,$B118*(BK$60),0)) -> 1.5733333 | BL118: =IF(BL$63<=$C$17,($C$34*BL$59*$B118/$C$63)*(IF(COUNTA($D118:BK118)*(12/$C$63)<=$C$9,0,1)),0)+IF(BM$63=$C$17,0,IF(BL$63=$C$17,$B118*(BL$60),0)) -> 1.5733333 | ... IW118: =IF(IW$63<=$C$17,($C$34*IW$59*$B118/$C$63)*(IF(COUNTA($D118:IV118)*(12/$C$63)<=$C$9,0,1)),0)+IF(IX$63=$C$17,0,IF(IW$63=$C$17,$B118*(IW$60),0)) -> 0
...

Sheet Résumé
F1: Variables
F2: Non Fondateur
F3: 10 | G3: Durée de souscription
F4: 50 | G4: NB de part(s) initiale(s)
F5: 2 | G5: =+IF(F5=0,"","NB de part(s) récurrente(s) durant "&Détails!B63&" année(s)") -> NB de part(s) récurrente(s) durant 7,41666666666667 année(s)
B6: Simulation de placement - SCPI Fair Invest | F6: Oui | G6: Réinvestissement des loyers
B7: (éléments à titre indicatifs qui n'ont aucune valeur contractuelle) | F7: 0.0472 | G7: DVM
B8: Versement initial | C8: =+F4*Détails!C26 -> 10100 | F8: 0.01 | G8: Revalorisation des parts
B9: Versements mensuels | C9: =F5*Détails!C26 -> 404
B10: Durée du placement | C10: =Détails!C32 -> 10 | F10: TRI (Avec réinvestissement des loyers) | G10: 3 | H10: 4 | I10: 5 | J10: 6 | K10: 7 | L10: 8
B11: Versements cumulés * | C11: =+Détails!C49 -> 46803.789 | G11: =+Détails!J32 -> #REF! | H11: =+Détails!K32 -> #REF! | I11: =+Détails!L32 -> #REF! | J11: =+Détails!M32 -> #REF! | K11: =+Détails!N32 -> #REF! | L11: =+Détails!O32 -> 0.034366289
B12: Placements cumulés (loyers réinvestis) * | C12: =+Détails!C53 -> 56487.232 | G12: 9 | H12: 10 | I12: 11 | J12: 12 | K12: 13 | L12: 14
B13: Pour des raisons de performance, l'achat programmé de parts est interrompu après | C13: =+(C10*12-Détails!A63)/12 -> 7.4166667 | G13: =+Détails!P32 -> 0.038743731 | H13: =+Détails!Q32 -> 0.041718391 | I13: =+Détails!R32 -> 0.043862954 | J13: =+Détails!S32 -> 0.045453891 | K13: =+Détails!T32 -> 0.046663108 | L13: =+Détails!U32 -> 0.047588769
B14: Soit nombre de parts | C14: =C12/Détails!C26 -> 279.63976 | G14: 15 | H14: 16 | I14: 17 | J14: 18 | K14: 19 | L14: 20
B15: Rendement espéré** | C15: =Détails!C34 -> 0.0472 | G15: =+Détails!V32 -> 0.048321977 | H15: =+Détails!W32 -> 0.048901322 | I15: =+Détails!X32 -> 0.04936147 | J15: =+Détails!Y32 -> 0.046696177 | K15: =+Détails!Z32 -> 0.045964125 | L15: =+Détails!AA32 -> 0.045416412
B16: Loyers trimestriels | C16: =+Détails!L66*3 -> 119.18 | G16: 21
B17: Revenus cumulés (soumis à impôt)** | C17: =+Détails!J27-C18 -> 19978.735 | G17: =+Détails!AB32 -> 0.045060536
B18: Frais de souscription (10%HT) | C18: =-(C14*Détails!C28) -> -5592.7953
B19: Capital réel | C19: =+C12+C18 -> 50894.437
B20: Valeur à la sortie (avec revalorisation des parts)** | C20: =+Détails!C53+Détails!C65 -> 70873.172 | E20: =C20*(F7/12) -> 278.76781
B22: En laissant ces fonds sur un compte courant, vous auriez atteint à terme un capital de : | C22: =+C11-Détails!C55 -> 40644.979
F23: GAINS (Avec réinvestissement des loyers) | G23: 3 | H23: 4 | I23: 5 | J23: 6 | K23: 7 | L23: 8
G24: =+Détails!J35 -> #REF! | H24: =+Détails!K35 -> #REF! | I24: =+Détails!L35 -> #REF! | J24: =+Détails!M35 -> #REF! | K24: =+Détails!N35 -> #REF! | L24: =+Détails!O35 -> 8854.3553
B25: * L'achat des parts pendant la durée du placement est effectué aux prix des parts revalorisées au moment de l'achat. ** Ces informations sont données à titre indicatif, elles n'ont rien de définitif ni contractuel. Les performances passées ne préjugent pas des performances futures. Risque de perte en capital : Le capital investi dans la SCPI ne bénéficie d’aucune garantie ni protection. La valorisation du capital dépendra de la valorisation des biens immobiliers détenus par la SCPI dont vous détenez des parts. Revenus non garantis : Les revenus de la SCPI proviennent essentiellement des loyers encaissés et ne sont en conséquence pas garantis, même si la multitude des locataires permet de réduire sensiblement ce risque. Placement peu liquide : Ce placement est considéré comme peu liquide. La société de gestion ne peut garantir ni le retrait, ni la vente des parts, ni leur remboursement. Un marché secondaire permettant aux investisseurs de revendre leurs parts à d’autres investisseurs est en général organisé mais la revente de parts de SCPI reste, à titre de comparaison, plus difficile que la revente d’actions ou de parts d’OPCVM. Par ailleurs, lorsque vous achetez des parts de SCPI, vous payez un prix de souscription comportant un ensemble de frais fixes non négociables d’environ 10%. Cela signifie que si vous revendez vos parts le lendemain de votre investissement, vous perdrez 10%. C’est la raison pourquoi il est recommandé d’envisager une durée d’investissement relativement longue (plus de 5 ans). | G25: 9 | H25: 10 | I25: 11 | J25: 12 | K25: 13 | L25: 14
G26: =+Détails!P35 -> 12223.619 | H26: =+Détails!Q35 -> 15605.198 | I26: =+Détails!R35 -> 18999.278 | J26: =+Détails!S35 -> 22406.046 | K26: =+Détails!T35 -> 25825.692 | L26: =+Détails!U35 -> 29258.411
G27: 15 | H27: 16 | I27: 17 | J27: 18 | K27: 19 | L27: 20
G28: =+Détails!V35 -> 32704.397 | H28: =+Détails!W35 -> 36163.85 | I28: =+Détails!X35 -> 39636.971 | J28: =+Détails!Y35 -> 40790.485 | K28: =+Détails!Z35 -> 46235.894 | L28: =+Détails!AA35 -> 53124.883
G29: 21
G30: =+Détails!AB35 -> 61607.739
F33: Valeur à la sortie (Avec réinvestissement des loyers) | G33: 3 | H33: 4 | I33: 5 | J33: 6 | K33: 7 | L33: 8
G34: =+Détails!J38 -> #REF! | H34: =+Détails!K38 -> #REF! | I34: =+Détails!L38 -> #REF! | J34: =+Détails!M38 -> #REF! | K34: =+Détails!N38 -> #REF! | L34: =+Détails!O38 -> 56224.417
G35: 9 | H35: 10 | I35: 11 | J35: 12 | K35: 13 | L35: 14
G36: =+Détails!P38 -> 59593.681 | H36: =+Détails!Q38 -> 62975.26 | I36: =+Détails!R38 -> 66369.34 | J36: =+Détails!S38 -> 69776.108 | K36: =+Détails!T38 -> 73195.754 | L36: =+Détails!U38 -> 76628.473
G37: 15 | H37: 16 | I37: 17 | J37: 18 | K37: 19 | L37: 20
G38: =+Détails!V38 -> 80074.459 | H38: =+Détails!W38 -> 83533.912 | I38: =+Détails!X38 -> 87007.033 | J38: =+Détails!Y38 -> 94335.431 | K38: =+Détails!Z38 -> 112131.98 | L38: =+Détails!AA38 -> 131376.21
G39: 21
G40: =+Détails!AB38 -> 152221.15
